Workbook
Name _DEP1: '[1]Internal Data'!$P$4:$P$36
Name _ECHO: '[2]Internal Data'!$A$4:$A$6
Name _PRO1: '[1]Internal Data'!$D$4:$D$23
Name _REV1: '[1]Internal Data'!$D$29:$D$47
Name CHECK: '[3]Internal Data'!$B$4:$B$6
Name CPRO1: '[1]Internal Data'!$N$4:$N$16
Name CPROV: Données!$R$25:$R$38
Name CPTES: Données!$J$7:$J$9
Name CREDIT: Données!$L$25:$L$47
Name DATE: Données!$N$25:$N$56
Name DEBUDGET: Données!$H$8:$H$23
Name DEBUDGET1: Données!$H$8:$H$15
Name DEPFIXE: '[4]Données internes'!$Q$4:$Q$44
Name DEPVAR: '[4]Données internes'!$S$4:$S$14
Name DFIX: Données!$T$25:$T$56
Name DIME: Données!$F$33:$F$34
Name DVAR: Données!$V$25:$V$34
Name ECHO: '[1]Internal Data'!$A$4:$A$6
Name EPAR: Données!$H$25:$H$51
Name EPAR0: '[1]Internal Data'!$H$3:$H$25
Name EPAR1: '[1]Internal Data'!$F$3:$F$30
Name EPARBUT: Données!$J$25:$J$43
Name EPAROBJ: '[3]Internal Data'!$H$4:$H$23
Name MOISP: '[5]Internal Data'!$L$4:$L$35
Name MOISP1: '[1]Internal Data'!$L$3:$L$35
Name NBMAJ: Données!$F$7:$F$14
Name NBMAJ1: Données!$F$8:$F$14
Name NBMIN: Données!$D$7:$D$14
Name NBMIN1: Données!$D$8:$D$14
Name OBJEPAR: '[4]Données internes'!$E$4:$E$28
Name OK: Données!$F$25:$F$27
Name PASS1: '[1]Internal Data'!$J$4:$J$27
Name PASSIFS: '[4]Données internes'!$I$4:$I$31
Name PRELEV: '[4]Données internes'!$K$4:$K$36
Name PROV: Données!$P$25:$P$45
Name PROVCOM: '[4]Données internes'!$M$4:$M$17
Name REV: Données!$D$25:$D$45
Name REVENUS: '[4]Données internes'!$C$4:$C$28
Name SITFA: Données!$B$7:$B$11
Name SITFA1: Données!$B$8:$B$11
Name TYPEPAR: '[4]Données internes'!$G$4:$G$36
Name VCDE: Données!$B$64:$B$94

Sheet Menu
B5: Cliquer pour accéder à votre Budget Gold
I6: Version 2026 Révision VMAX EUR
J7: par Christian Saboukoulou
B9: L'expérience de la planification budgétaire au service de vos finances et de vos projets
B12: MENU DE CONFIGURATION GENERALE
B14: Etape 1 | C14: Nom | F14: PIZEUIL | G14: <- | H14: à remplir | J14: Gestion immobilière ImmoView 1
B16: Etape 2 | C16: Situation familiale | F16: célibataire | G16: <- | H16: sélectionner
B18: Etape 3 | C18: Nombre d'enfants mineurs | F18: 0 | G18: <- | H18: sélectionner | J18: Gestion immobilière ImmoView 2
B20: Etape 4 | C20: Nombre d'enfants majeurs | F20: 0 | G20: <- | H20: sélectionner
B22: Etape 5 | C22: Mois de démarrage du budget | F22: 46174 | G22: <- | H22: sélectionner | J22: Gestion immobilière ImmoView 3
B24: Etape 6 | C24: Configurer vos comptes bancaires et vos solutions d'épargne en cliquant ici
B26: Etape 7 | C26: Accéder à votre tableau Budget Gold | J26: Budget d'un mariage Mariage-Gold
C32: Informations et avertissements :
C33: Cet ouvrage est la propriété unique de l’auteur. Il est protégé par le Code de la propriété intellectuelle (CPI) qui stipule que « l’auteur
C34: d’une œuvre de l’esprit jouit sur cette œuvre, du seul fait de sa création, d’un droit de propriété incorporelle exclusif et opposable à tous.
C35: Ce droit comporte des attributs d’ordre intellectuel et moral ainsi que des attributs d’ordre patrimonial ». L’ensemble de ces droits figure
C36: dans la première partie du code de la propriété intellectuelle qui codifie les lois du 11 mars 1957 et du 3 juillet 1985.
C37: Tous droits réservés pour tous pays. En application des lois rappelées ci-dessus, aucun extrait de ce livret ne peut être reproduit, par
C38: quelque procédé que ce soit, sans l’autorisation écrite de l’auteur.
C40: Limitations et risques :
C41: Budget Gold est un outil d'aide à la planification budgétaire. Son usage adéquat peut permettre l'amélioration de la gestion budgétaire de
C42: celui qui l'utilise. Toutefois, cela n'est pas une garantie absolue, car plusieurs paramètres externes peuvent le rendre inefficace.
C43: Par ailleurs, une vérification des formules a été faite, néanmoins, il est toujours possible qu'une erreur se soit glissée, faussant ainsi certains
C44: résultats de formules. Le concepteur du fichier Budget Gold ne peut être tenu pour responsable des éventuels problèmes financiers
... C46: Toute utilisation de Budget Gold par l'utilisateur entraine l'acceptation de ces limitations et risques.
H47: © Copyright 2003-2026, Christian SABOUKOULOU, Tous droits réservés

Sheet Menu 2
B2: Retour au Budget | E2: Retour au Menu
B6: Listez tous vos comptes courants :
B7: Les comptes courants que vous possédez.
C8: 1 | E8: Compte courant - BANXO | G8: Exemples : | H8: Compte courant - Romuald (BNP Paribas)
C9: 2 | E9: Compte courant - Revolut | H9: Compte courant - Romuald (CIC)
C10: 3 | H10: Compte courant - Esther (Banque Postale)
C11: =C10+1 -> 4 | H11: Enveloppe
C12: =C11+1 -> 5 | H12: Caisse
C13: =C12+1 -> 6
C14: =C13+1 -> 7
C15: =C14+1 -> 8
C16: =C15+1 -> 9
C17: =C16+1 -> 10
C18: =C17+1 -> 11
C19: =C18+1 -> 12
B22: Listez toutes vos formules d'épargne :
B23: Comptes d'épargne, assurances-vie
B24: Comptes d'investissements, tirelires, etc. | C24: 1 | E24: Livret A - BANXO | G24: Exemples : | H24: Livret d'épargne - Romuald
C25: 2 | E25: PEA - Bourse direct | H25: Livret A - Bébé Bambino
C26: 3 | E26: Assurance vie - Finarylife | H26: Livret Jeune - Romuald
C27: =C26+1 -> 4 | E27: Placements financiers | H27: PEA BNP Paribas - Esther
C28: =C27+1 -> 5 | E28: Fonds euros - Finarylife | H28: Tirelire
C29: =C28+1 -> 6 | H29: Enveloppe
C30: =C29+1 -> 7
C31: =C30+1 -> 8
C32: =C31+1 -> 9
C33: =C32+1 -> 10
C34: =C33+1 -> 11
C35: =C34+1 -> 12
C36: =C35+1 -> 13
C37: =C36+1 -> 14
C38: =C37+1 -> 15
C39: =C38+1 -> 16
C40: =C39+1 -> 17
C41: =C40+1 -> 18
... C52: =C51+1 -> 29
C53: =C52+1 -> 30 | E53: PATRIMOINE

Sheet Budget Gold
A2: Accès au MENU | F2: Si la vie commençait par la fin, on prendrait davantage le temps de bien préparer les choses importantes
AT3: EXTRA-PROJECTION
A4: Simulateur d'épargne | F4: =CONCATENATE("Budget de ",IF(Menu!F14="","",Menu!F14)) -> Budget de PIZEUIL | I4: =IF(BB28>0,CONCATENATE("Total des revenus annuels : ",INT(BB28),"€ (",INT(BB29),"€/mois)"),"") -> Total des revenus annuels : 42000€ (3500€/mois) | S4: =Menu!I6 -> Version 2026 Révision VMAX EUR | AA4: =I4 -> Total des revenus annuels : 42000€ (3500€/mois) | AY4: BILAN ANNUEL
I5: =IF(I4="","",CONCATENATE("Balance annuelle générale : ",INT(BB267),"€ (",INT(BB267/12),"€/mois)")) -> Balance annuelle générale : 21642€ (1803€/mois) | AA5: =I5 -> Balance annuelle générale : 21642€ (1803€/mois) | AT5: Horizon 2 ans | AU5: Horizon 5 ans
I7: =(Menu!F22) -> 46174 | L7: =32+I7 -> 46206 | O7: =32+L7 -> 46238 | R7: =32+O7 -> 46270 | U7: =32+R7 -> 46302 | X7: =32+U7 -> 46334 | AA7: =32+X7 -> 46366 | AD7: =32+AA7 -> 46398 | AG7: =32+AD7 -> 46430 | AJ7: =32+AG7 -> 46462 | AM7: =32+AJ7 -> 46494 | AP7: =32+AM7 -> 46526 | AY7: REVENUS
E8: REVENUS
E9: Dîme | F9: Configurez vos comptes courants (en cliquant ici) | BB9: Cumul annuel | BC9: % | BD9: Moy. mensuelle | BE9: Rang
D10: 1 | E10: oui | F10: SALAIRE | G10: Compte courant - BANXO | I10: 3500 | K10: ea | L10: 3500 | N10: ea | O10: 3500 | Q10: ea | R10: 3500 | T10: ea | U10: 3500 | W10: ea | X10: 3500 | Z10: ea | AA10: 3500 | AC10: ea | AD10: 3500 | AF10: ea | AG10: 3500 | AI10: ea | AJ10: 3500 | AL10: ea | AM10: 3500 | AO10: ea | AP10: 3500 | AR10: ea | AY10: =F10 -> SALAIRE | BB10: =SUM(I10:AR10) -> 42000 | BC10: =IF(BB28=0,0,BB10/BB28) -> 1 | BD10: =BB10/12 -> 3500 | BE10: =IF(BD10=0,"",RANK(BD10,BD$10:BD$27,0)) -> 1 | BF10: =IF(BD10=0,"",IF(BE10=1,"er","ème")) -> er
D11: =1+D10 -> 2 | E11: non | F11: Revenu à configurer | G11: - sélectionner - | AY11: =F11 -> Revenu à configurer | BB11: =SUM(I11:AR11) -> 0 | BC11: =IF(BB28=0,0,BB11/BB28) -> 0 | BD11: =BB11/12 -> 0 | BE11: =IF(BD11=0,"",RANK(BD11,BD$10:BD$27,0)) | BF11: =IF(BD11=0,"",IF(BE11=1,"er","ème"))
D12: =1+D11 -> 3 | E12: non | F12: Revenu à configurer | G12: - sélectionner - | AY12: =F12 -> Revenu à configurer | BB12: =SUM(I12:AR12) -> 0 | BC12: =IF(BB28=0,0,BB12/BB28) -> 0 | BD12: =BB12/12 -> 0 | BE12: =IF(BD12=0,"",RANK(BD12,BD$10:BD$27,0)) | BF12: =IF(BD12=0,"",IF(BE12=1,"er","ème"))
D13: =1+D12 -> 4 | E13: non | F13: Revenu à configurer | G13: - sélectionner - | AY13: =F13 -> Revenu à configurer | BB13: =SUM(I13:AR13) -> 0 | BC13: =IF(BB28=0,0,BB13/BB28) -> 0 | BD13: =BB13/12 -> 0 | BE13: =IF(BD13=0,"",RANK(BD13,BD$10:BD$27,0)) | BF13: =IF(BD13=0,"",IF(BE13=1,"er","ème"))
D14: =1+D13 -> 5 | E14: non | F14: Revenu à configurer | G14: - sélectionner - | AY14: =F14 -> Revenu à configurer | BB14: =SUM(I14:AR14) -> 0 | BC14: =IF(BB28=0,0,BB14/BB28) -> 0 | BD14: =BB14/12 -> 0 | BE14: =IF(BD14=0,"",RANK(BD14,BD$10:BD$27,0)) | BF14: =IF(BD14=0,"",IF(BE14=1,"er","ème"))
D15: =1+D14 -> 6 | E15: non | F15: Revenu à configurer | G15: - sélectionner - | AY15: =F15 -> Revenu à configurer | BB15: =SUM(I15:AR15) -> 0 | BC15: =IF(BB28=0,0,BB15/BB28) -> 0 | BD15: =BB15/12 -> 0 | BE15: =IF(BD15=0,"",RANK(BD15,BD$10:BD$27,0)) | BF15: =IF(BD15=0,"",IF(BE15=1,"er","ème"))
D16: =1+D15 -> 7 | E16: non | F16: Revenu à configurer | G16: - sélectionner - | AY16: =F16 -> Revenu à configurer | BB16: =SUM(I16:AR16) -> 0 | BC16: =IF(BB28=0,0,BB16/BB28) -> 0 | BD16: =BB16/12 -> 0 | BE16: =IF(BD16=0,"",RANK(BD16,BD$10:BD$27,0)) | BF16: =IF(BD16=0,"",IF(BE16=1,"er","ème"))
D17: =1+D16 -> 8 | E17: non | F17: Revenu à configurer | G17: - sélectionner - | AY17: =F17 -> Revenu à configurer | BB17: =SUM(I17:AR17) -> 0 | BC17: =IF(BB28=0,0,BB17/BB28) -> 0 | BD17: =BB17/12 -> 0 | BE17: =IF(BD17=0,"",RANK(BD17,BD$10:BD$27,0)) | BF17: =IF(BD17=0,"",IF(BE17=1,"er","ème"))
D18: =1+D17 -> 9 | E18: non | F18: Revenu à configurer | G18: - sélectionner - | AY18: =F18 -> Revenu à configurer | BB18: =SUM(I18:AR18) -> 0 | BC18: =IF(BB28=0,0,BB18/BB28) -> 0 | BD18: =BB18/12 -> 0 | BE18: =IF(BD18=0,"",RANK(BD18,BD$10:BD$27,0)) | BF18: =IF(BD18=0,"",IF(BE18=1,"er","ème"))
D19: =1+D18 -> 10 | E19: non | F19: Revenu à configurer | G19: - sélectionner - | AY19: =F19 -> Revenu à configurer | BB19: =SUM(I19:AR19) -> 0 | BC19: =IF(BB28=0,0,BB19/BB28) -> 0 | BD19: =BB19/12 -> 0 | BE19: =IF(BD19=0,"",RANK(BD19,BD$10:BD$27,0)) | BF19: =IF(BD19=0,"",IF(BE19=1,"er","ème"))
D20: =1+D19 -> 11 | E20: non | F20: Revenu à configurer | G20: - sélectionner - | AY20: =F20 -> Revenu à configurer | BB20: =SUM(I20:AR20) -> 0 | BC20: =IF(BB28=0,0,BB20/BB28) -> 0 | BD20: =BB20/12 -> 0 | BE20: =IF(BD20=0,"",RANK(BD20,BD$10:BD$27,0)) | BF20: =IF(BD20=0,"",IF(BE20=1,"er","ème"))
D21: =1+D20 -> 12 | E21: non | F21: Revenu à configurer | G21: - sélectionner - | AY21: =F21 -> Revenu à configurer | BB21: =SUM(I21:AR21) -> 0 | BC21: =IF(BB28=0,0,BB21/BB28) -> 0 | BD21: =BB21/12 -> 0 | BE21: =IF(BD21=0,"",RANK(BD21,BD$10:BD$27,0)) | BF21: =IF(BD21=0,"",IF(BE21=1,"er","ème"))
D22: =1+D21 -> 13 | E22: non | F22: Revenu à configurer | G22: - sélectionner - | AY22: =F22 -> Revenu à configurer | BB22: =SUM(I22:AR22) -> 0 | BC22: =IF(BB28=0,0,BB22/BB28) -> 0 | BD22: =BB22/12 -> 0 | BE22: =IF(BD22=0,"",RANK(BD22,BD$10:BD$27,0)) | BF22: =IF(BD22=0,"",IF(BE22=1,"er","ème"))
D23: =1+D22 -> 14 | E23: non | F23: Revenu à configurer | G23: - sélectionner - | AY23: =F23 -> Revenu à configurer | BB23: =SUM(I23:AR23) -> 0 | BC23: =IF(BB28=0,0,BB23/BB28) -> 0 | BD23: =BB23/12 -> 0 | BE23: =IF(BD23=0,"",RANK(BD23,BD$10:BD$27,0)) | BF23: =IF(BD23=0,"",IF(BE23=1,"er","ème"))
D24: =1+D23 -> 15 | E24: non | F24: Revenu à configurer | G24: - sélectionner - | AY24: =F24 -> Revenu à configurer | BB24: =SUM(I24:AR24) -> 0 | BC24: =IF(BB28=0,0,BB24/BB28) -> 0 | BD24: =BB24/12 -> 0 | BE24: =IF(BD24=0,"",RANK(BD24,BD$10:BD$27,0)) | BF24: =IF(BD24=0,"",IF(BE24=1,"er","ème"))
D25: =1+D24 -> 16 | E25: non | F25: Revenu à configurer | G25: - sélectionner - | AY25: =F25 -> Revenu à configurer | BB25: =SUM(I25:AR25) -> 0 | BC25: =IF(BB28=0,0,BB25/BB28) -> 0 | BD25: =BB25/12 -> 0 | BE25: =IF(BD25=0,"",RANK(BD25,BD$10:BD$27,0)) | BF25: =IF(BD25=0,"",IF(BE25=1,"er","ème"))
D26: =1+D25 -> 17 | E26: non | F26: Revenu à configurer | G26: - sélectionner - | AY26: =F26 -> Revenu à configurer | BB26: =SUM(I26:AR26) -> 0 | BC26: =IF(BB28=0,0,BB26/BB28) -> 0 | BD26: =BB26/12 -> 0 | BE26: =IF(BD26=0,"",RANK(BD26,BD$10:BD$27,0)) | BF26: =IF(BD26=0,"",IF(BE26=1,"er","ème"))
D27: =1+D26 -> 18 | E27: non | F27: Revenu à configurer | G27: - sélectionner - | AY27: =F27 -> Revenu à configurer | BB27: =SUM(I27:AR27) -> 0 | BC27: =IF(BB28=0,0,BB27/BB28) -> 0 | BD27: =BB27/12 -> 0 | BE27: =IF(BD27=0,"",RANK(BD27,BD$10:BD$27,0)) | BF27: =IF(BD27=0,"",IF(BE27=1,"er","ème"))
F28: TOTAL des REVENUS = | I28: =SUM(I10:J27) -> 3500 | L28: =SUM(L10:M27) -> 3500 | O28: =SUM(O10:P27) -> 3500 | R28: =SUM(R10:S27) -> 3500 | U28: =SUM(U10:V27) -> 3500 | X28: =SUM(X10:Y27) -> 3500 | AA28: =SUM(AA10:AB27) -> 3500 | AD28: =SUM(AD10:AE27) -> 3500 | AG28: =SUM(AG10:AH27) -> 3500 | AJ28: =SUM(AJ10:AK27) -> 3500 | AM28: =SUM(AM10:AN27) -> 3500 | AP28: =SUM(AP10:AQ27) -> 3500 | AY28: TOTAL Annuel des REVENUS = | BB28: =SUM(BB10:BB27) -> 42000
G29: Cumul des revenus mensuels = | I29: =I28 -> 3500 | L29: =I29+L28 -> 7000 | O29: =L29+O28 -> 10500 | R29: =O29+R28 -> 14000 | U29: =R29+U28 -> 17500 | X29: =U29+X28 -> 21000 | AA29: =X29+AA28 -> 24500 | AD29: =AA29+AD28 -> 28000 | AG29: =AD29+AG28 -> 31500 | AJ29: =AG29+AJ28 -> 35000 | AM29: =AJ29+AM28 -> 38500 | AP29: =AM29+AP28 -> 42000 | AZ29: Moyenne mensuelle des revenus = | BB29: =BB28/12 -> 3500
G30: Moy. mensuelle progressive = | I30: =I29 -> 3500 | L30: =L29/2 -> 3500 | O30: =O29/3 -> 3500 | R30: =R29/4 -> 3500 | U30: =U29/5 -> 3500 | X30: =X29/6 -> 3500 | AA30: =AA29/7 -> 3500 | AD30: =AD29/8 -> 3500 | AG30: =AG29/9 -> 3500 | AJ30: =AJ29/10 -> 3500 | AM30: =AM29/11 -> 3500 | AP30: =AP29/12 -> 3500
G32: Epargne/Placements/Provisions existantes rendues disponibles = | BA32: TOTAL annuel Epargne/Placements/Provisions existantes rendues dispo. = | BB32: =SUM(I32:AR32) -> 0
G34: TOTAL mensuel des RESSOURCES DISPONIBLES = | I34: =I28+I32 -> 3500 | L34: =L28+L32 -> 3500 | O34: =O28+O32 -> 3500 | R34: =R28+R32 -> 3500 | U34: =U28+U32 -> 3500 | X34: =X28+X32 -> 3500 | AA34: =AA28+AA32 -> 3500 | AD34: =AD28+AD32 -> 3500 | AG34: =AG28+AG32 -> 3500 | AJ34: =AJ28+AJ32 -> 3500 | AM34: =AM28+AM32 -> 3500 | AP34: =AP28+AP32 -> 3500 | BA34: TOTAL annuel des RESSOURCES DISPONIBLES = | BB34: =BB28+BB32 -> 42000
D37: Activé | E37: GRAND DISPATCHING | I37: =I7 -> 46174 | L37: =L7 -> 46206 | O37: =O7 -> 46238 | R37: =R7 -> 46270 | U37: =U7 -> 46302 | X37: =X7 -> 46334 | AA37: =AA7 -> 46366 | AD37: =AD7 -> 46398 | AG37: =AG7 -> 46430 | AJ37: =AJ7 -> 46462 | AM37: =AM7 -> 46494 | AP37: =AP7 -> 46526
E38: Equilibre dans les sections -> | I38: =IF($D$37="Désactivé","",CONCATENATE(IF(AND(I129>=0,I155>=0,I221>=0,I263>=0),"Sections équilibrées",CONCATENATE("Ajuster : ", IF(I129<0,"S1 ",""),IF(I155<0,"S2 ",""),IF(I222<0,"S3 ",""),IF(I263<0,"S4 ",""))))) -> Ajuster : S4 | L38: =IF($D$37="Désactivé","",CONCATENATE(IF(AND(L129>=0,L155>=0,L221>=0,L263>=0),"Sections équilibrées",CONCATENATE("Ajuster : ", IF(L129<0,"S1 ",""),IF(L155<0,"S2 ",""),IF(L222<0,"S3 ",""),IF(L263<0,"S4 ",""))))) -> Ajuster : S4 | O38: =IF($D$37="Désactivé","",CONCATENATE(IF(AND(O129>=0,O155>=0,O221>=0,O263>=0),"Sections équilibrées",CONCATENATE("Ajuster : ", IF(O129<0,"S1 ",""),IF(O155<0,"S2 ",""),IF(O222<0,"S3 ",""),IF(O263<0,"S4 ",""))))) -> Ajuster : S4 | R38: =IF($D$37="Désactivé","",CONCATENATE(IF(AND(R129>=0,R155>=0,R221>=0,R263>=0),"Sections équilibrées",CONCATENATE("Ajuster : ", IF(R129<0,"S1 ",""),IF(R155<0,"S2 ",""),IF(R222<0,"S3 ",""),IF(R263<0,"S4 ",""))))) -> Ajuster : S4 | U38: =IF($D$37="Désactivé","",CONCATENATE(IF(AND(U129>=0,U155>=0,U221>=0,U263>=0),"Sections équilibrées",CONCATENATE("Ajuster : ", IF(U129<0,"S1 ",""),IF(U155<0,"S2 ",""),IF(U222<0,"S3 ",""),IF(U263<0,"S4 ",""))))) -> Ajuster : S1 S3 S4 | X38: =IF($D$37="Désactivé","",CONCATENATE(IF(AND(X129>=0,X155>=0,X221>=0,X263>=0),"Sections équilibrées",CONCATENATE("Ajuster : ", IF(X129<0,"S1 ",""),IF(X155<0,"S2 ",""),IF(X222<0,"S3 ",""),IF(X263<0,"S4 ",""))))) -> Ajuster : S1 S3 S4 | AA38: =IF($D$37="Désactivé","",CONCATENATE(IF(AND(AA129>=0,AA155>=0,AA221>=0,AA263>=0),"Sections équilibrées",CONCATENATE("Ajuster : ", IF(AA129<0,"S1 ",""),IF(AA155<0,"S2 ",""),IF(AA222<0,"S3 ",""),IF(AA263<0,"S4 ",""))))) -> Ajuster : S1 S3 S4 | AD38: =IF($D$37="Désactivé","",CONCATENATE(IF(AND(AD129>=0,AD155>=0,AD221>=0,AD263>=0),"Sections équilibrées",CONCATENATE("Ajuster : ", IF(AD129<0,"S1 ",""),IF(AD155<0,"S2 ",""),IF(AD222<0,"S3 ",""),IF(AD263<0,"S4 ",""))))) -> Ajuster : S1 S3 S4 | AG38: =IF($D$37="Désactivé","",CONCATENATE(IF(AND(AG129>=0,AG155>=0,AG221>=0,AG263>=0),"Sections équilibrées",CONCATENATE("Ajuster : ", IF(AG129<0,"S1 ",""),IF(AG155<0,"S2 ",""),IF(AG222<0,"S3 ",""),IF(AG263<0,"S4 ",""))))) -> Ajuster : S1 S3 S4 | AJ38: =IF($D$37="Désactivé","",CONCATENATE(IF(AND(AJ129>=0,AJ155>=0,AJ221>=0,AJ263>=0),"Sections équilibrées",CONCATENATE("Ajuster : ", IF(AJ129<0,"S1 ",""),IF(AJ155<0,"S2 ",""),IF(AJ222<0,"S3 ",""),IF(AJ263<0,"S4 ",""))))) -> Ajuster : S1 S3 S4 | AM38: =IF($D$37="Désactivé","",CONCATENATE(IF(AND(AM129>=0,AM155>=0,AM221>=0,AM263>=0),"Sections équilibrées",CONCATENATE("Ajuster : ", IF(AM129<0,"S1 ",""),IF(AM155<0,"S2 ",""),IF(AM222<0,"S3 ",""),IF(AM263<0,"S4 ",""))))) -> Ajuster : S1 S3 S4 | AP38: =IF($D$37="Désactivé","",CONCATENATE(IF(AND(AP129>=0,AP155>=0,AP221>=0,AP263>=0),"Sections équilibrées",CONCATENATE("Ajuster : ", IF(AP129<0,"S1 ",""),IF(AP155<0,"S2 ",""),IF(AP222<0,"S3 ",""),IF(AP263<0,"S4 ",""))))) -> Ajuster : S1 S3 S4
E39: S1 | F39: Section EPARGNE & PLACEMENTS | I39: 1048 | K39: € | L39: 1048 | N39: € | O39: 1048 | Q39: € | R39: 1048 | T39: € | U39: 0 | W39: € | X39: 0 | Z39: % | AA39: 0 | AC39: % | AD39: 0 | AF39: % | AG39: 0 | AI39: % | AJ39: 0 | AL39: % | AM39: 0 | AO39: % | AP39: 0 | AR39: %
E41: S2 | F41: Section DETTES & CREDITS | I41: 0 | K41: € | L41: 0 | N41: € | O41: 0 | Q41: € | R41: 0 | T41: € | U41: 0 | W41: % | X41: 0 | Z41: € | AA41: 0 | AC41: € | AD41: 0 | AF41: € | AG41: 0 | AI41: € | AJ41: 0 | AL41: € | AM41: 0 | AO41: € | AP41: 0 | AR41: €
E43: S3 | F43: Section RESERVES & PROVISIONS | I43: 3010 | K43: € | L43: 3010 | N43: € | O43: 3010 | Q43: € | R43: 3010 | T43: € | U43: 0 | W43: € | X43: 0 | Z43: % | AA43: 0 | AC43: % | AD43: 0 | AF43: % | AG43: 0 | AI43: % | AJ43: 0 | AL43: % | AM43: 0 | AO43: % | AP43: 0 | AR43: %
E45: S4 | F45: Section CHARGES & DEPENSES COURANTES | I45: 1031.3 | K45: € | L45: 1031.3 | N45: € | O45: 1031.3 | Q45: € | R45: 1031.3 | T45: € | U45: 0 | W45: € | X45: 0 | Z45: € | AA45: 0 | AC45: € | AD45: 0 | AF45: € | AG45: 0 | AI45: € | AJ45: 0 | AL45: € | AM45: 0 | AO45: € | AP45: 0 | AR45: %
F47: REGULATEUR de DISPATCHING - Ajuster jusqu'à atteindre "0" (VERT) | I47: =INT((I28+I32)-SUM(IF(K39="€",I39,(I39*(I28+I32))/100),IF(K41="€",I41,(I41*(I28+I32))/100),IF(K43="€",I43,(I43*(I28+I32))/100),IF(K45="€",I45,(I45*(I28+I32))/100))) -> -1590 | L47: =INT((L28+L32)-SUM(IF(N39="€",L39,(L39*(L28+L32))/100),IF(N41="€",L41,(L41*(L28+L32))/100),IF(N43="€",L43,(L43*(L28+L32))/100),IF(N45="€",L45,(L45*(L28+L32))/100))) -> -1590 | O47: =INT((O28+O32)-SUM(IF(Q39="€",O39,(O39*(O28+O32))/100),IF(Q41="€",O41,(O41*(O28+O32))/100),IF(Q43="€",O43,(O43*(O28+O32))/100),IF(Q45="€",O45,(O45*(O28+O32))/100))) -> -1590 | R47: =INT((R28+R32)-SUM(IF(T39="€",R39,(R39*(R28+R32))/100),IF(T41="€",R41,(R41*(R28+R32))/100),IF(T43="€",R43,(R43*(R28+R32))/100),IF(T45="€",R45,(R45*(R28+R32))/100))) -> -1590 | U47: =INT((U28+U32)-SUM(IF(W39="€",U39,(U39*(U28+U32))/100),IF(W41="€",U41,(U41*(U28+U32))/100),IF(W43="€",U43,(U43*(U28+U32))/100),IF(W45="€",U45,(U45*(U28+U32))/100))) -> 3500 | X47: =INT((X28+X32)-SUM(IF(Z39="€",X39,(X39*(X28+X32))/100),IF(Z41="€",X41,(X41*(X28+X32))/100),IF(Z43="€",X43,(X43*(X28+X32))/100),IF(Z45="€",X45,(X45*(X28+X32))/100))) -> 3500 | AA47: =INT((AA28+AA32)-SUM(IF(AC39="€",AA39,(AA39*(AA28+AA32))/100),IF(AC41="€",AA41,(AA41*(AA28+AA32))/100),IF(AC43="€",AA43,(AA43*(AA28+AA32))/100),IF(AC45="€",AA45,(AA45*(AA28+AA32))/100))) -> 3500 | AD47: =INT((AD28+AD32)-SUM(IF(AF39="€",AD39,(AD39*(AD28+AD32))/100),IF(AF41="€",AD41,(AD41*(AD28+AD32))/100),IF(AF43="€",AD43,(AD43*(AD28+AD32))/100),IF(AF45="€",AD45,(AD45*(AD28+AD32))/100))) -> 3500 | AG47: =INT((AG28+AG32)-SUM(IF(AI39="€",AG39,(AG39*(AG28+AG32))/100),IF(AI41="€",AG41,(AG41*(AG28+AG32))/100),IF(AI43="€",AG43,(AG43*(AG28+AG32))/100),IF(AI45="€",AG45,(AG45*(AG28+AG32))/100))) -> 3500 | AJ47: =INT((AJ28+AJ32)-SUM(IF(AL39="€",AJ39,(AJ39*(AJ28+AJ32))/100),IF(AL41="€",AJ41,(AJ41*(AJ28+AJ32))/100),IF(AL43="€",AJ43,(AJ43*(AJ28+AJ32))/100),IF(AL45="€",AJ45,(AJ45*(AJ28+AJ32))/100))) -> 3500 | AM47: =INT((AM28+AM32)-SUM(IF(AO39="€",AM39,(AM39*(AM28+AM32))/100),IF(AO41="€",AM41,(AM41*(AM28+AM32))/100),IF(AO43="€",AM43,(AM43*(AM28+AM32))/100),IF(AO45="€",AM45,(AM45*(AM28+AM32))/100))) -> 3500 | AP47: =INT((AP28+AP32)-SUM(IF(AR39="€",AP39,(AP39*(AP28+AP32))/100),IF(AR41="€",AP41,(AP41*(AP28+AP32))/100),IF(AR43="€",AP43,(AP43*(AP28+AP32))/100),IF(AR45="€",AP45,(AP45*(AP28+AP32))/100))) -> 3500
D51: Mouvements d'épargne et de provisions | E51: S1 | F51: EPARGNE & PLACEMENTS | I51: =I7 -> 46174 | L51: =L7 -> 46206 | O51: =O7 -> 46238 | R51: =R7 -> 46270 | U51: =U7 -> 46302 | X51: =X7 -> 46334 | AA51: =AA7 -> 46366 | AD51: =AD7 -> 46398 | AG51: =AG7 -> 46430 | AJ51: =AJ7 -> 46462 | AM51: =AM7 -> 46494 | AP51: =AP7 -> 46526 | AT51: EXTRA | AU51: EXTRA | AY51: EPARGNE & PLACEMENTS
F52: =IF($D$37="Activé","Budgets mensuels disponibles pour l'épargne et les placements ->","Balances mensuelles ->") -> Budgets mensuels disponibles pour l'épargne et les placements -> | I52: =IF($D$37="Activé",IF(K39="%",INT(I39*I28/100),I39),I267) -> 1048 | L52: =IF($D$37="Activé",IF(N39="%",INT(L39*L28/100),L39),L267) -> 1048 | O52: =IF($D$37="Activé",IF(Q39="%",INT(O39*O28/100),O39),O267) -> 1048 | R52: =IF($D$37="Activé",IF(T39="%",INT(R39*R28/100),R39),R267) -> 1048 | U52: =IF($D$37="Activé",IF(W39="%",INT(U39*U28/100),U39),U267) -> 0 | X52: =IF($D$37="Activé",IF(Z39="%",INT(X39*X28/100),X39),X267) -> 0 | AA52: =IF($D$37="Activé",IF(AC39="%",INT(AA39*AA28/100),AA39),AA267) -> 0 | AD52: =IF($D$37="Activé",IF(AF39="%",INT(AD39*AD28/100),AD39),AD267) -> 0 | AG52: =IF($D$37="Activé",IF(AI39="%",INT(AG39*AG28/100),AG39),AG267) -> 0 | AJ52: =IF($D$37="Activé",IF(AL39="%",INT(AJ39*AJ28/100),AJ39),AJ267) -> 0 | AM52: =IF($D$37="Activé",IF(AO39="%",INT(AM39*AM28/100),AM39),AM267) -> 0 | AP52: =IF($D$37="Activé",IF(AR39="%",INT(AP39*AP28/100),AP39),AP267) -> 0 | AT52: PROJECTION | AU52: PROJECTION
E53: Configurez vos comptes d'épargne (en cliquant ici) | I53: Suivi | J53: Budget | L53: Suivi | M53: Budget | O53: Suivi | P53: Budget | R53: Suivi | S53: Budget | U53: Suivi | V53: Budget | X53: Suivi | Y53: Budget | AA53: Suivi | AB53: Budget | AD53: Suivi | AE53: Budget | AG53: Suivi | AH53: Budget | AJ53: Suivi | AK53: Budget | AM53: Suivi | AN53: Budget | AP53: Suivi | AQ53: Budget | AT53: Horizon 2 ans | AU53: Horizon 5 ans | AY53: Configurez vos comptes d'épargne (en cliquant ici) | BB53: Cumul annuel | BD53: Moy. mensuelle
D54: 1 | E54: PEA - INVESTISSEMENTS | J54: 250 | K54: ea | M54: 250 | N54: ea | P54: 250 | Q54: ea | S54: 250 | T54: ea | V54: 250 | W54: ea | Y54: 250 | Z54: ea | AB54: 250 | AC54: ea | AE54: 250 | AF54: ea | AH54: 250 | AI54: ea | AK54: 250 | AL54: ea | AN54: 250 | AO54: ea | AQ54: 250 | AR54: ea | AT54: =CONCATENATE("Moy. de ",INT(BB54/12)," €/mois") -> Moy. de 250 €/mois | AU54: =CONCATENATE("Moy. de ",INT(BB54/12)," €/mois") -> Moy. de 250 €/mois | AY54: =IF(E54="","",E54) -> PEA - INVESTISSEMENTS | BB54: =SUM(MAX(I54,J54),MAX(L54,M54),MAX(O54,P54),MAX(R54,S54),MAX(U54,V54),MAX(X54,Y54),MAX(AA54,AB54),MAX(AD54,AE54),MAX(AG54,AH54),MAX(AJ54,AK54),MAX(AM54,AN54),MAX(AP54,AQ54)) -> 3000 | BD54: =BB54/12 -> 250
D55: ExtraP Off | E55: =IF(BB54=0,"",INT(SUM(IF(K54="ok",J54,0),IF(N54="ok",M54,0),IF(Q54="ok",P54,0),IF(T54="ok",S54,0),IF(W54="ok",V54,0),IF(Z54="ok",Y54,0),IF(AC54="ok",AB54,0),IF(AF54="ok",AE54,0),IF(AI54="ok",AH54,0),IF(AL54="ok",AK54,0),IF(AO54="ok",AN54,0),IF(AR54="ok",AQ54,0))*100/BB54)/100) -> 0 | F55: =IF(BB54=0,"",CONCATENATE("de l'objectif annuel atteint ","(",INT(SUM(IF(K54="ok",J54,0),IF(N54="ok",M54,0),IF(Q54="ok",P54,0),IF(T54="ok",S54,0),IF(W54="ok",V54,0),IF(Z54="ok",Y54,0),IF(AC54="ok",AB54,0),IF(AF54="ok",AE54,0),IF(AI54="ok",AH54,0),IF(AL54="ok",AK54,0),IF(AO54="ok",AN54,0),IF(AR54="ok",AQ54,0)))," € / ",BB54,")",IF(BB54=INT(SUM(IF(K54="ok",J54,0),IF(N54="ok",M54,0),IF(Q54="ok",P54,0),IF(T54="ok",S54,0),IF(W54="ok",V54,0),IF(Z54="ok",Y54,0),IF(AC54="ok",AB54,0),IF(AF54="ok",AE54,0),IF(AI54="ok",AH54,0),IF(AL54="ok",AK54,0),IF(AO54="ok",AN54,0),IF(AR54="ok",AQ54,0))),"",CONCATENATE(" : manque ",BB54-INT(SUM(IF(K54="ok",J54,0),IF(N54="ok",M54,0),IF(Q54="ok",P54,0),IF(T54="ok",S54,0),IF(W54="ok",V54,0),IF(Z54="ok",Y54,0),IF(AC54="ok",AB54,0),IF(AF54="ok",AE54,0),IF(AI54="ok",AH54,0),IF(AL54="ok",AK54,0),IF(AO54="ok",AN54,0),IF(AR54="ok",AQ54,0)))," €")))) -> de l'objectif annuel atteint (0 € / 3000) : manque 3000 € | G55: Les retraits du mois -> | AY55: Somme totale des retraits -> | BB55: =SUM(MAX(I55,J55),MAX(L55,M55),MAX(O55,P55),MAX(R55,S55),MAX(U55,V55),MAX(X55,Y55),MAX(AA55,AB55),MAX(AD55,AE55),MAX(AG55,AH55),MAX(AJ55,AK55),MAX(AM55,AN55),MAX(AP55,AQ55)) -> 0 | BD55: épargnés/mois
D56: 39530 | E56: PEA - Bourse direct | I56: =D56+IF(I54>J54,I54,J54)-IF(J55<I55,I55,J55) -> 39780 | L56: =I56+IF(L54>M54,L54,M54)-IF(M55<L55,L55,M55) -> 40030 | O56: =L56+IF(O54>P54,O54,P54)-IF(P55<O55,O55,P55) -> 40280 | R56: =O56+IF(R54>S54,R54,S54)-IF(S55<R55,R55,S55) -> 40530 | U56: =R56+IF(U54>V54,U54,V54)-IF(V55<U55,U55,V55) -> 40780 | X56: =U56+IF(X54>Y54,X54,Y54)-IF(Y55<X55,X55,Y55) -> 41030 | AA56: =X56+IF(AA54>AB54,AA54,AB54)-IF(AB55<AA55,AA55,AB55) -> 41280 | AD56: =AA56+IF(AD54>AE54,AD54,AE54)-IF(AE55<AD55,AD55,AE55) -> 41530 | AG56: =AD56+IF(AG54>AH54,AG54,AH54)-IF(AH55<AG55,AG55,AH55) -> 41780 | AJ56: =AG56+IF(AJ54>AK54,AJ54,AK54)-IF(AK55<AJ55,AJ55,AK55) -> 42030 | AM56: =AJ56+IF(AM54>AN54,AM54,AN54)-IF(AN55<AM55,AM55,AN55) -> 42280 | AP56: =AM56+IF(AP54>AQ54,AP54,AQ54)-IF(AQ55<AP55,AP55,AQ55) -> 42530 | AT56: =AP56+BB54 -> 45530 | AU56: =AP56+BB54*4 -> 54530 | AY56: =IF(E56="","",E56) -> PEA - Bourse direct | BB56: =AP56 -> 42530
D57: =1+D54 -> 2 | E57: Assurance vie "INVESTISSEMENTS" | J57: 200 | K57: ea | M57: 200 | N57: ea | P57: 200 | Q57: ea | S57: 200 | T57: ea | V57: 200 | W57: ea | Y57: 200 | Z57: ea | AB57: 200 | AC57: ea | AE57: 200 | AF57: ea | AH57: 200 | AI57: ea | AK57: 200 | AL57: ea | AN57: 200 | AO57: ea | AQ57: 200 | AR57: ea | AT57: =CONCATENATE("Moy. de ",INT(BB57/12)," €/mois") -> Moy. de 200 €/mois | AU57: =CONCATENATE("Moy. de ",INT(BB57/12)," €/mois") -> Moy. de 200 €/mois | AY57: =IF(E57="","",E57) -> Assurance vie "INVESTISSEMENTS" | BB57: =SUM(MAX(I57,J57),MAX(L57,M57),MAX(O57,P57),MAX(R57,S57),MAX(U57,V57),MAX(X57,Y57),MAX(AA57,AB57),MAX(AD57,AE57),MAX(AG57,AH57),MAX(AJ57,AK57),MAX(AM57,AN57),MAX(AP57,AQ57)) -> 2400 | BD57: =BB57/12 -> 200
D58: ExtraP Off | E58: =IF(BB57=0,"",INT(SUM(IF(K57="ok",J57,0),IF(N57="ok",M57,0),IF(Q57="ok",P57,0),IF(T57="ok",S57,0),IF(W57="ok",V57,0),IF(Z57="ok",Y57,0),IF(AC57="ok",AB57,0),IF(AF57="ok",AE57,0),IF(AI57="ok",AH57,0),IF(AL57="ok",AK57,0),IF(AO57="ok",AN57,0),IF(AR57="ok",AQ57,0))*100/BB57)/100) -> 0 | F58: =IF(BB57=0,"",CONCATENATE("de l'objectif annuel atteint ","(",INT(SUM(IF(K57="ok",J57,0),IF(N57="ok",M57,0),IF(Q57="ok",P57,0),IF(T57="ok",S57,0),IF(W57="ok",V57,0),IF(Z57="ok",Y57,0),IF(AC57="ok",AB57,0),IF(AF57="ok",AE57,0),IF(AI57="ok",AH57,0),IF(AL57="ok",AK57,0),IF(AO57="ok",AN57,0),IF(AR57="ok",AQ57,0)))," € / ",BB57,")",IF(BB57=INT(SUM(IF(K57="ok",J57,0),IF(N57="ok",M57,0),IF(Q57="ok",P57,0),IF(T57="ok",S57,0),IF(W57="ok",V57,0),IF(Z57="ok",Y57,0),IF(AC57="ok",AB57,0),IF(AF57="ok",AE57,0),IF(AI57="ok",AH57,0),IF(AL57="ok",AK57,0),IF(AO57="ok",AN57,0),IF(AR57="ok",AQ57,0))),"",CONCATENATE(" : manque ",BB57-INT(SUM(IF(K57="ok",J57,0),IF(N57="ok",M57,0),IF(Q57="ok",P57,0),IF(T57="ok",S57,0),IF(W57="ok",V57,0),IF(Z57="ok",Y57,0),IF(AC57="ok",AB57,0),IF(AF57="ok",AE57,0),IF(AI57="ok",AH57,0),IF(AL57="ok",AK57,0),IF(AO57="ok",AN57,0),IF(AR57="ok",AQ57,0)))," €")))) -> de l'objectif annuel atteint (0 € / 2400) : manque 2400 € | G58: Les retraits du mois -> | AY58: Somme totale des retraits -> | BB58: =SUM(MAX(I58,J58),MAX(L58,M58),MAX(O58,P58),MAX(R58,S58),MAX(U58,V58),MAX(X58,Y58),MAX(AA58,AB58),MAX(AD58,AE58),MAX(AG58,AH58),MAX(AJ58,AK58),MAX(AM58,AN58),MAX(AP58,AQ58)) -> 0 | BD58: épargnés/mois
D59: 2311 | E59: Assurance vie - Finarylife | I59: =D59+IF(I57>J57,I57,J57)-IF(J58<I58,I58,J58) -> 2511 | L59: =I59+IF(L57>M57,L57,M57)-IF(M58<L58,L58,M58) -> 2711 | O59: =L59+IF(O57>P57,O57,P57)-IF(P58<O58,O58,P58) -> 2911 | R59: =O59+IF(R57>S57,R57,S57)-IF(S58<R58,R58,S58) -> 3111 | U59: =R59+IF(U57>V57,U57,V57)-IF(V58<U58,U58,V58) -> 3311 | X59: =U59+IF(X57>Y57,X57,Y57)-IF(Y58<X58,X58,Y58) -> 3511 | AA59: =X59+IF(AA57>AB57,AA57,AB57)-IF(AB58<AA58,AA58,AB58) -> 3711 | AD59: =AA59+IF(AD57>AE57,AD57,AE57)-IF(AE58<AD58,AD58,AE58) -> 3911 | AG59: =AD59+IF(AG57>AH57,AG57,AH57)-IF(AH58<AG58,AG58,AH58) -> 4111 | AJ59: =AG59+IF(AJ57>AK57,AJ57,AK57)-IF(AK58<AJ58,AJ58,AK58) -> 4311 | AM59: =AJ59+IF(AM57>AN57,AM57,AN57)-IF(AN58<AM58,AM58,AN58) -> 4511 | AP59: =AM59+IF(AP57>AQ57,AP57,AQ57)-IF(AQ58<AP58,AP58,AQ58) -> 4711 | AT59: =AP59+BB57 -> 7111 | AU59: =AP59+BB57*4 -> 14311 | AY59: =IF(E59="","",E59) -> Assurance vie - Finarylife | BB59: =AP59 -> 4711
D60: =1+D57 -> 3 | E60: Trésorerie "Service pour DIEU & Bonnes Œuvres" | J60: 100 | M60: 100 | N60: ea | P60: 100 | S60: 100 | AT60: =CONCATENATE("Moy. de ",INT(BB60/12)," €/mois") -> Moy. de 33 €/mois | AU60: =CONCATENATE("Moy. de ",INT(BB60/12)," €/mois") -> Moy. de 33 €/mois | AY60: =IF(E60="","",E60) -> Trésorerie "Service pour DIEU & Bonnes Œuvres" | BB60: =SUM(MAX(I60,J60),MAX(L60,M60),MAX(O60,P60),MAX(R60,S60),MAX(U60,V60),MAX(X60,Y60),MAX(AA60,AB60),MAX(AD60,AE60),MAX(AG60,AH60),MAX(AJ60,AK60),MAX(AM60,AN60),MAX(AP60,AQ60)) -> 400 | BD60: =BB60/12 -> 33.333333
D61: ExtraP Off | E61: =IF(BB60=0,"",INT(SUM(IF(K60="ok",J60,0),IF(N60="ok",M60,0),IF(Q60="ok",P60,0),IF(T60="ok",S60,0),IF(W60="ok",V60,0),IF(Z60="ok",Y60,0),IF(AC60="ok",AB60,0),IF(AF60="ok",AE60,0),IF(AI60="ok",AH60,0),IF(AL60="ok",AK60,0),IF(AO60="ok",AN60,0),IF(AR60="ok",AQ60,0))*100/BB60)/100) -> 0 | F61: =IF(BB60=0,"",CONCATENATE("de l'objectif annuel atteint ","(",INT(SUM(IF(K60="ok",J60,0),IF(N60="ok",M60,0),IF(Q60="ok",P60,0),IF(T60="ok",S60,0),IF(W60="ok",V60,0),IF(Z60="ok",Y60,0),IF(AC60="ok",AB60,0),IF(AF60="ok",AE60,0),IF(AI60="ok",AH60,0),IF(AL60="ok",AK60,0),IF(AO60="ok",AN60,0),IF(AR60="ok",AQ60,0)))," € / ",BB60,")",IF(BB60=INT(SUM(IF(K60="ok",J60,0),IF(N60="ok",M60,0),IF(Q60="ok",P60,0),IF(T60="ok",S60,0),IF(W60="ok",V60,0),IF(Z60="ok",Y60,0),IF(AC60="ok",AB60,0),IF(AF60="ok",AE60,0),IF(AI60="ok",AH60,0),IF(AL60="ok",AK60,0),IF(AO60="ok",AN60,0),IF(AR60="ok",AQ60,0))),"",CONCATENATE(" : manque ",BB60-INT(SUM(IF(K60="ok",J60,0),IF(N60="ok",M60,0),IF(Q60="ok",P60,0),IF(T60="ok",S60,0),IF(W60="ok",V60,0),IF(Z60="ok",Y60,0),IF(AC60="ok",AB60,0),IF(AF60="ok",AE60,0),IF(AI60="ok",AH60,0),IF(AL60="ok",AK60,0),IF(AO60="ok",AN60,0),IF(AR60="ok",AQ60,0)))," €")))) -> de l'objectif annuel atteint (0 € / 400) : manque 400 € | G61: Les retraits du mois -> | AY61: Somme totale des retraits -> | BB61: =SUM(MAX(I61,J61),MAX(L61,M61),MAX(O61,P61),MAX(R61,S61),MAX(U61,V61),MAX(X61,Y61),MAX(AA61,AB61),MAX(AD61,AE61),MAX(AG61,AH61),MAX(AJ61,AK61),MAX(AM61,AN61),MAX(AP61,AQ61)) -> 0 | BD61: épargnés/mois
E62: Livret A - BANXO | I62: =D62+IF(I60>J60,I60,J60)-IF(J61<I61,I61,J61) -> 100 | L62: =I62+IF(L60>M60,L60,M60)-IF(M61<L61,L61,M61) -> 200 | O62: =L62+IF(O60>P60,O60,P60)-IF(P61<O61,O61,P61) -> 300 | R62: =O62+IF(R60>S60,R60,S60)-IF(S61<R61,R61,S61) -> 400 | U62: =R62+IF(U60>V60,U60,V60)-IF(V61<U61,U61,V61) -> 400 | X62: =U62+IF(X60>Y60,X60,Y60)-IF(Y61<X61,X61,Y61) -> 400 | AA62: =X62+IF(AA60>AB60,AA60,AB60)-IF(AB61<AA61,AA61,AB61) -> 400 | AD62: =AA62+IF(AD60>AE60,AD60,AE60)-IF(AE61<AD61,AD61,AE61) -> 400 | AG62: =AD62+IF(AG60>AH60,AG60,AH60)-IF(AH61<AG61,AG61,AH61) -> 400 | AJ62: =AG62+IF(AJ60>AK60,AJ60,AK60)-IF(AK61<AJ61,AJ61,AK61) -> 400 | AM62: =AJ62+IF(AM60>AN60,AM60,AN60)-IF(AN61<AM61,AM61,AN61) -> 400 | AP62: =AM62+IF(AP60>AQ60,AP60,AQ60)-IF(AQ61<AP61,AP61,AQ61) -> 400 | AT62: =AP62+BB60 -> 800 | AU62: =AP62+BB60*4 -> 2000 | AY62: =IF(E62="","",E62) -> Livret A - BANXO | BB62: =AP62 -> 400
D63: =1+D60 -> 4 | E63: Réserve de "SOUTIEN FAMILIAL" | J63: 25 | M63: 25 | P63: 25 | S63: 25 | AT63: =CONCATENATE("Moy. de ",INT(BB63/12)," €/mois") -> Moy. de 8 €/mois | AU63: =CONCATENATE("Moy. de ",INT(BB63/12)," €/mois") -> Moy. de 8 €/mois | AY63: =IF(E63="","",E63) -> Réserve de "SOUTIEN FAMILIAL" | BB63: =SUM(MAX(I63,J63),MAX(L63,M63),MAX(O63,P63),MAX(R63,S63),MAX(U63,V63),MAX(X63,Y63),MAX(AA63,AB63),MAX(AD63,AE63),MAX(AG63,AH63),MAX(AJ63,AK63),MAX(AM63,AN63),MAX(AP63,AQ63)) -> 100 | BD63: =BB63/12 -> 8.3333333
D64: ExtraP Off | E64: =IF(BB63=0,"",INT(SUM(IF(K63="ok",J63,0),IF(N63="ok",M63,0),IF(Q63="ok",P63,0),IF(T63="ok",S63,0),IF(W63="ok",V63,0),IF(Z63="ok",Y63,0),IF(AC63="ok",AB63,0),IF(AF63="ok",AE63,0),IF(AI63="ok",AH63,0),IF(AL63="ok",AK63,0),IF(AO63="ok",AN63,0),IF(AR63="ok",AQ63,0))*100/BB63)/100) -> 0 | F64: =IF(BB63=0,"",CONCATENATE("de l'objectif annuel atteint ","(",INT(SUM(IF(K63="ok",J63,0),IF(N63="ok",M63,0),IF(Q63="ok",P63,0),IF(T63="ok",S63,0),IF(W63="ok",V63,0),IF(Z63="ok",Y63,0),IF(AC63="ok",AB63,0),IF(AF63="ok",AE63,0),IF(AI63="ok",AH63,0),IF(AL63="ok",AK63,0),IF(AO63="ok",AN63,0),IF(AR63="ok",AQ63,0)))," € / ",BB63,")",IF(BB63=INT(SUM(IF(K63="ok",J63,0),IF(N63="ok",M63,0),IF(Q63="ok",P63,0),IF(T63="ok",S63,0),IF(W63="ok",V63,0),IF(Z63="ok",Y63,0),IF(AC63="ok",AB63,0),IF(AF63="ok",AE63,0),IF(AI63="ok",AH63,0),IF(AL63="ok",AK63,0),IF(AO63="ok",AN63,0),IF(AR63="ok",AQ63,0))),"",CONCATENATE(" : manque ",BB63-INT(SUM(IF(K63="ok",J63,0),IF(N63="ok",M63,0),IF(Q63="ok",P63,0),IF(T63="ok",S63,0),IF(W63="ok",V63,0),IF(Z63="ok",Y63,0),IF(AC63="ok",AB63,0),IF(AF63="ok",AE63,0),IF(AI63="ok",AH63,0),IF(AL63="ok",AK63,0),IF(AO63="ok",AN63,0),IF(AR63="ok",AQ63,0)))," €")))) -> de l'objectif annuel atteint (0 € / 100) : manque 100 € | G64: Les retraits du mois -> | AY64: Somme totale des retraits -> | BB64: =SUM(MAX(I64,J64),MAX(L64,M64),MAX(O64,P64),MAX(R64,S64),MAX(U64,V64),MAX(X64,Y64),MAX(AA64,AB64),MAX(AD64,AE64),MAX(AG64,AH64),MAX(AJ64,AK64),MAX(AM64,AN64),MAX(AP64,AQ64)) -> 0 | BD64: épargnés/mois
E65: Livret A - BANXO | I65: =D65+IF(I63>J63,I63,J63)-IF(J64<I64,I64,J64) -> 25 | L65: =I65+IF(L63>M63,L63,M63)-IF(M64<L64,L64,M64) -> 50 | O65: =L65+IF(O63>P63,O63,P63)-IF(P64<O64,O64,P64) -> 75 | R65: =O65+IF(R63>S63,R63,S63)-IF(S64<R64,R64,S64) -> 100 | U65: =R65+IF(U63>V63,U63,V63)-IF(V64<U64,U64,V64) -> 100 | X65: =U65+IF(X63>Y63,X63,Y63)-IF(Y64<X64,X64,Y64) -> 100 | AA65: =X65+IF(AA63>AB63,AA63,AB63)-IF(AB64<AA64,AA64,AB64) -> 100 | AD65: =AA65+IF(AD63>AE63,AD63,AE63)-IF(AE64<AD64,AD64,AE64) -> 100 | AG65: =AD65+IF(AG63>AH63,AG63,AH63)-IF(AH64<AG64,AG64,AH64) -> 100 | AJ65: =AG65+IF(AJ63>AK63,AJ63,AK63)-IF(AK64<AJ64,AJ64,AK64) -> 100 | AM65: =AJ65+IF(AM63>AN63,AM63,AN63)-IF(AN64<AM64,AM64,AN64) -> 100 | AP65: =AM65+IF(AP63>AQ63,AP63,AQ63)-IF(AQ64<AP64,AP64,AQ64) -> 100 | AT65: =AP65+BB63 -> 200 | AU65: =AP65+BB63*4 -> 500 | AY65: =IF(E65="","",E65) -> Livret A - BANXO | BB65: =AP65 -> 100
D66: =1+D63 -> 5 | E66: Epargne pour "Mariage" | J66: 50 | M66: 50 | P66: 50 | S66: 50 | AT66: =CONCATENATE("Moy. de ",INT(BB66/12)," €/mois") -> Moy. de 16 €/mois | AU66: =CONCATENATE("Moy. de ",INT(BB66/12)," €/mois") -> Moy. de 16 €/mois | AY66: =IF(E66="","",E66) -> Epargne pour "Mariage" | BB66: =SUM(MAX(I66,J66),MAX(L66,M66),MAX(O66,P66),MAX(R66,S66),MAX(U66,V66),MAX(X66,Y66),MAX(AA66,AB66),MAX(AD66,AE66),MAX(AG66,AH66),MAX(AJ66,AK66),MAX(AM66,AN66),MAX(AP66,AQ66)) -> 200 | BD66: =BB66/12 -> 16.666667
D67: ExtraP Off | E67: =IF(BB66=0,"",INT(SUM(IF(K66="ok",J66,0),IF(N66="ok",M66,0),IF(Q66="ok",P66,0),IF(T66="ok",S66,0),IF(W66="ok",V66,0),IF(Z66="ok",Y66,0),IF(AC66="ok",AB66,0),IF(AF66="ok",AE66,0),IF(AI66="ok",AH66,0),IF(AL66="ok",AK66,0),IF(AO66="ok",AN66,0),IF(AR66="ok",AQ66,0))*100/BB66)/100) -> 0 | F67: =IF(BB66=0,"",CONCATENATE("de l'objectif annuel atteint ","(",INT(SUM(IF(K66="ok",J66,0),IF(N66="ok",M66,0),IF(Q66="ok",P66,0),IF(T66="ok",S66,0),IF(W66="ok",V66,0),IF(Z66="ok",Y66,0),IF(AC66="ok",AB66,0),IF(AF66="ok",AE66,0),IF(AI66="ok",AH66,0),IF(AL66="ok",AK66,0),IF(AO66="ok",AN66,0),IF(AR66="ok",AQ66,0)))," € / ",BB66,")",IF(BB66=INT(SUM(IF(K66="ok",J66,0),IF(N66="ok",M66,0),IF(Q66="ok",P66,0),IF(T66="ok",S66,0),IF(W66="ok",V66,0),IF(Z66="ok",Y66,0),IF(AC66="ok",AB66,0),IF(AF66="ok",AE66,0),IF(AI66="ok",AH66,0),IF(AL66="ok",AK66,0),IF(AO66="ok",AN66,0),IF(AR66="ok",AQ66,0))),"",CONCATENATE(" : manque ",BB66-INT(SUM(IF(K66="ok",J66,0),IF(N66="ok",M66,0),IF(Q66="ok",P66,0),IF(T66="ok",S66,0),IF(W66="ok",V66,0),IF(Z66="ok",Y66,0),IF(AC66="ok",AB66,0),IF(AF66="ok",AE66,0),IF(AI66="ok",AH66,0),IF(AL66="ok",AK66,0),IF(AO66="ok",AN66,0),IF(AR66="ok",AQ66,0)))," €")))) -> de l'objectif annuel atteint (0 € / 200) : manque 200 € | G67: Les retraits du mois -> | AY67: Somme totale des retraits -> | BB67: =SUM(MAX(I67,J67),MAX(L67,M67),MAX(O67,P67),MAX(R67,S67),MAX(U67,V67),MAX(X67,Y67),MAX(AA67,AB67),MAX(AD67,AE67),MAX(AG67,AH67),MAX(AJ67,AK67),MAX(AM67,AN67),MAX(AP67,AQ67)) -> 0 | BD67: épargnés/mois
E68: Livret A - BANXO | I68: =D68+IF(I66>J66,I66,J66)-IF(J67<I67,I67,J67) -> 50 | L68: =I68+IF(L66>M66,L66,M66)-IF(M67<L67,L67,M67) -> 100 | O68: =L68+IF(O66>P66,O66,P66)-IF(P67<O67,O67,P67) -> 150 | R68: =O68+IF(R66>S66,R66,S66)-IF(S67<R67,R67,S67) -> 200 | U68: =R68+IF(U66>V66,U66,V66)-IF(V67<U67,U67,V67) -> 200 | X68: =U68+IF(X66>Y66,X66,Y66)-IF(Y67<X67,X67,Y67) -> 200 | AA68: =X68+IF(AA66>AB66,AA66,AB66)-IF(AB67<AA67,AA67,AB67) -> 200 | AD68: =AA68+IF(AD66>AE66,AD66,AE66)-IF(AE67<AD67,AD67,AE67) -> 200 | AG68: =AD68+IF(AG66>AH66,AG66,AH66)-IF(AH67<AG67,AG67,AH67) -> 200 | AJ68: =AG68+IF(AJ66>AK66,AJ66,AK66)-IF(AK67<AJ67,AJ67,AK67) -> 200 | AM68: =AJ68+IF(AM66>AN66,AM66,AN66)-IF(AN67<AM67,AM67,AN67) -> 200 | AP68: =AM68+IF(AP66>AQ66,AP66,AQ66)-IF(AQ67<AP67,AP67,AQ67) -> 200 | AT68: =AP68+BB66 -> 400 | AU68: =AP68+BB66*4 -> 1000 | AY68: =IF(E68="","",E68) -> Livret A - BANXO | BB68: =AP68 -> 200
D69: =1+D66 -> 6 | E69: Epargne pour "IMPREVUS" | J69: 100 | M69: 100 | P69: 100 | S69: 100 | AT69: =CONCATENATE("Moy. de ",INT(BB69/12)," €/mois") -> Moy. de 33 €/mois | AU69: =CONCATENATE("Moy. de ",INT(BB69/12)," €/mois") -> Moy. de 33 €/mois | AY69: =IF(E69="","",E69) -> Epargne pour "IMPREVUS" | BB69: =SUM(MAX(I69,J69),MAX(L69,M69),MAX(O69,P69),MAX(R69,S69),MAX(U69,V69),MAX(X69,Y69),MAX(AA69,AB69),MAX(AD69,AE69),MAX(AG69,AH69),MAX(AJ69,AK69),MAX(AM69,AN69),MAX(AP69,AQ69)) -> 400 | BD69: =BB69/12 -> 33.333333
D70: ExtraP Off | E70: =IF(BB69=0,"",INT(SUM(IF(K69="ok",J69,0),IF(N69="ok",M69,0),IF(Q69="ok",P69,0),IF(T69="ok",S69,0),IF(W69="ok",V69,0),IF(Z69="ok",Y69,0),IF(AC69="ok",AB69,0),IF(AF69="ok",AE69,0),IF(AI69="ok",AH69,0),IF(AL69="ok",AK69,0),IF(AO69="ok",AN69,0),IF(AR69="ok",AQ69,0))*100/BB69)/100) -> 0 | F70: =IF(BB69=0,"",CONCATENATE("de l'objectif annuel atteint ","(",INT(SUM(IF(K69="ok",J69,0),IF(N69="ok",M69,0),IF(Q69="ok",P69,0),IF(T69="ok",S69,0),IF(W69="ok",V69,0),IF(Z69="ok",Y69,0),IF(AC69="ok",AB69,0),IF(AF69="ok",AE69,0),IF(AI69="ok",AH69,0),IF(AL69="ok",AK69,0),IF(AO69="ok",AN69,0),IF(AR69="ok",AQ69,0)))," € / ",BB69,")",IF(BB69=INT(SUM(IF(K69="ok",J69,0),IF(N69="ok",M69,0),IF(Q69="ok",P69,0),IF(T69="ok",S69,0),IF(W69="ok",V69,0),IF(Z69="ok",Y69,0),IF(AC69="ok",AB69,0),IF(AF69="ok",AE69,0),IF(AI69="ok",AH69,0),IF(AL69="ok",AK69,0),IF(AO69="ok",AN69,0),IF(AR69="ok",AQ69,0))),"",CONCATENATE(" : manque ",BB69-INT(SUM(IF(K69="ok",J69,0),IF(N69="ok",M69,0),IF(Q69="ok",P69,0),IF(T69="ok",S69,0),IF(W69="ok",V69,0),IF(Z69="ok",Y69,0),IF(AC69="ok",AB69,0),IF(AF69="ok",AE69,0),IF(AI69="ok",AH69,0),IF(AL69="ok",AK69,0),IF(AO69="ok",AN69,0),IF(AR69="ok",AQ69,0)))," €")))) -> de l'objectif annuel atteint (0 € / 400) : manque 400 € | G70: Les retraits du mois -> | AB70: 10000 | AY70: Somme totale des retraits -> | BB70: =SUM(MAX(I70,J70),MAX(L70,M70),MAX(O70,P70),MAX(R70,S70),MAX(U70,V70),MAX(X70,Y70),MAX(AA70,AB70),MAX(AD70,AE70),MAX(AG70,AH70),MAX(AJ70,AK70),MAX(AM70,AN70),MAX(AP70,AQ70)) -> 10000 | BD70: épargnés/mois
D71: 8000 | E71: Livret A - BANXO | I71: =D71+IF(I69>J69,I69,J69)-IF(J70<I70,I70,J70) -> 8100 | L71: =I71+IF(L69>M69,L69,M69)-IF(M70<L70,L70,M70) -> 8200 | O71: =L71+IF(O69>P69,O69,P69)-IF(P70<O70,O70,P70) -> 8300 | R71: =O71+IF(R69>S69,R69,S69)-IF(S70<R70,R70,S70) -> 8400 | U71: =R71+IF(U69>V69,U69,V69)-IF(V70<U70,U70,V70) -> 8400 | X71: =U71+IF(X69>Y69,X69,Y69)-IF(Y70<X70,X70,Y70) -> 8400 | AA71: =X71+IF(AA69>AB69,AA69,AB69)-IF(AB70<AA70,AA70,AB70) -> -1600 | AD71: =AA71+IF(AD69>AE69,AD69,AE69)-IF(AE70<AD70,AD70,AE70) -> -1600 | AG71: =AD71+IF(AG69>AH69,AG69,AH69)-IF(AH70<AG70,AG70,AH70) -> -1600 | AJ71: =AG71+IF(AJ69>AK69,AJ69,AK69)-IF(AK70<AJ70,AJ70,AK70) -> -1600 | AM71: =AJ71+IF(AM69>AN69,AM69,AN69)-IF(AN70<AM70,AM70,AN70) -> -1600 | AP71: =AM71+IF(AP69>AQ69,AP69,AQ69)-IF(AQ70<AP70,AP70,AQ70) -> -1600 | AT71: =AP71+BB69 -> -1200 | AU71: =AP71+BB69*4 -> 0 | AY71: =IF(E71="","",E71) -> Livret A - BANXO | BB71: =AP71 -> -1600
D72: =1+D69 -> 7 | E72: Epargne pour 'FORMATION" (compétences, etc.) | J72: 25 | M72: 25 | P72: 25 | S72: 25 | AT72: =CONCATENATE("Moy. de ",INT(BB72/12)," €/mois") -> Moy. de 8 €/mois | AU72: =CONCATENATE("Moy. de ",INT(BB72/12)," €/mois") -> Moy. de 8 €/mois | AY72: =IF(E72="","",E72) -> Epargne pour 'FORMATION" (compétences, etc.) | BB72: =SUM(MAX(I72,J72),MAX(L72,M72),MAX(O72,P72),MAX(R72,S72),MAX(U72,V72),MAX(X72,Y72),MAX(AA72,AB72),MAX(AD72,AE72),MAX(AG72,AH72),MAX(AJ72,AK72),MAX(AM72,AN72),MAX(AP72,AQ72)) -> 100 | BD72: =BB72/12 -> 8.3333333
D73: ExtraP Off | E73: =IF(BB72=0,"",INT(SUM(IF(K72="ok",J72,0),IF(N72="ok",M72,0),IF(Q72="ok",P72,0),IF(T72="ok",S72,0),IF(W72="ok",V72,0),IF(Z72="ok",Y72,0),IF(AC72="ok",AB72,0),IF(AF72="ok",AE72,0),IF(AI72="ok",AH72,0),IF(AL72="ok",AK72,0),IF(AO72="ok",AN72,0),IF(AR72="ok",AQ72,0))*100/BB72)/100) -> 0 | F73: =IF(BB72=0,"",CONCATENATE("de l'objectif annuel atteint ","(",INT(SUM(IF(K72="ok",J72,0),IF(N72="ok",M72,0),IF(Q72="ok",P72,0),IF(T72="ok",S72,0),IF(W72="ok",V72,0),IF(Z72="ok",Y72,0),IF(AC72="ok",AB72,0),IF(AF72="ok",AE72,0),IF(AI72="ok",AH72,0),IF(AL72="ok",AK72,0),IF(AO72="ok",AN72,0),IF(AR72="ok",AQ72,0)))," € / ",BB72,")",IF(BB72=INT(SUM(IF(K72="ok",J72,0),IF(N72="ok",M72,0),IF(Q72="ok",P72,0),IF(T72="ok",S72,0),IF(W72="ok",V72,0),IF(Z72="ok",Y72,0),IF(AC72="ok",AB72,0),IF(AF72="ok",AE72,0),IF(AI72="ok",AH72,0),IF(AL72="ok",AK72,0),IF(AO72="ok",AN72,0),IF(AR72="ok",AQ72,0))),"",CONCATENATE(" : manque ",BB72-INT(SUM(IF(K72="ok",J72,0),IF(N72="ok",M72,0),IF(Q72="ok",P72,0),IF(T72="ok",S72,0),IF(W72="ok",V72,0),IF(Z72="ok",Y72,0),IF(AC72="ok",AB72,0),IF(AF72="ok",AE72,0),IF(AI72="ok",AH72,0),IF(AL72="ok",AK72,0),IF(AO72="ok",AN72,0),IF(AR72="ok",AQ72,0)))," €")))) -> de l'objectif annuel atteint (0 € / 100) : manque 100 € | G73: Les retraits du mois -> | AY73: Somme totale des retraits -> | BB73: =SUM(MAX(I73,J73),MAX(L73,M73),MAX(O73,P73),MAX(R73,S73),MAX(U73,V73),MAX(X73,Y73),MAX(AA73,AB73),MAX(AD73,AE73),MAX(AG73,AH73),MAX(AJ73,AK73),MAX(AM73,AN73),MAX(AP73,AQ73)) -> 0 | BD73: épargnés/mois
E74: Livret A - BANXO | I74: =D74+IF(I72>J72,I72,J72)-IF(J73<I73,I73,J73) -> 25 | L74: =I74+IF(L72>M72,L72,M72)-IF(M73<L73,L73,M73) -> 50 | O74: =L74+IF(O72>P72,O72,P72)-IF(P73<O73,O73,P73) -> 75 | R74: =O74+IF(R72>S72,R72,S72)-IF(S73<R73,R73,S73) -> 100 | U74: =R74+IF(U72>V72,U72,V72)-IF(V73<U73,U73,V73) -> 100 | X74: =U74+IF(X72>Y72,X72,Y72)-IF(Y73<X73,X73,Y73) -> 100 | AA74: =X74+IF(AA72>AB72,AA72,AB72)-IF(AB73<AA73,AA73,AB73) -> 100 | AD74: =AA74+IF(AD72>AE72,AD72,AE72)-IF(AE73<AD73,AD73,AE73) -> 100 | AG74: =AD74+IF(AG72>AH72,AG72,AH72)-IF(AH73<AG73,AG73,AH73) -> 100 | AJ74: =AG74+IF(AJ72>AK72,AJ72,AK72)-IF(AK73<AJ73,AJ73,AK73) -> 100 | AM74: =AJ74+IF(AM72>AN72,AM72,AN72)-IF(AN73<AM73,AM73,AN73) -> 100 | AP74: =AM74+IF(AP72>AQ72,AP72,AQ72)-IF(AQ73<AP73,AP73,AQ73) -> 100 | AT74: =AP74+BB72 -> 200 | AU74: =AP74+BB72*4 -> 500 | AY74: =IF(E74="","",E74) -> Livret A - BANXO | BB74: =AP74 -> 100
D75: =1+D72 -> 8 | E75: Epargne "ACHAT VOITURE" | J75: 100 | M75: 100 | P75: 100 | S75: 100 | V75: 350 | AT75: =CONCATENATE("Moy. de ",INT(BB75/12)," €/mois") -> Moy. de 62 €/mois | AU75: =CONCATENATE("Moy. de ",INT(BB75/12)," €/mois") -> Moy. de 62 €/mois | AY75: =IF(E75="","",E75) -> Epargne "ACHAT VOITURE" | BB75: =SUM(MAX(I75,J75),MAX(L75,M75),MAX(O75,P75),MAX(R75,S75),MAX(U75,V75),MAX(X75,Y75),MAX(AA75,AB75),MAX(AD75,AE75),MAX(AG75,AH75),MAX(AJ75,AK75),MAX(AM75,AN75),MAX(AP75,AQ75)) -> 750 | BD75: =BB75/12 -> 62.5
D76: ExtraP Off | E76: =IF(BB75=0,"",INT(SUM(IF(K75="ok",J75,0),IF(N75="ok",M75,0),IF(Q75="ok",P75,0),IF(T75="ok",S75,0),IF(W75="ok",V75,0),IF(Z75="ok",Y75,0),IF(AC75="ok",AB75,0),IF(AF75="ok",AE75,0),IF(AI75="ok",AH75,0),IF(AL75="ok",AK75,0),IF(AO75="ok",AN75,0),IF(AR75="ok",AQ75,0))*100/BB75)/100) -> 0 | F76: =IF(BB75=0,"",CONCATENATE("de l'objectif annuel atteint ","(",INT(SUM(IF(K75="ok",J75,0),IF(N75="ok",M75,0),IF(Q75="ok",P75,0),IF(T75="ok",S75,0),IF(W75="ok",V75,0),IF(Z75="ok",Y75,0),IF(AC75="ok",AB75,0),IF(AF75="ok",AE75,0),IF(AI75="ok",AH75,0),IF(AL75="ok",AK75,0),IF(AO75="ok",AN75,0),IF(AR75="ok",AQ75,0)))," € / ",BB75,")",IF(BB75=INT(SUM(IF(K75="ok",J75,0),IF(N75="ok",M75,0),IF(Q75="ok",P75,0),IF(T75="ok",S75,0),IF(W75="ok",V75,0),IF(Z75="ok",Y75,0),IF(AC75="ok",AB75,0),IF(AF75="ok",AE75,0),IF(AI75="ok",AH75,0),IF(AL75="ok",AK75,0),IF(AO75="ok",AN75,0),IF(AR75="ok",AQ75,0))),"",CONCATENATE(" : manque ",BB75-INT(SUM(IF(K75="ok",J75,0),IF(N75="ok",M75,0),IF(Q75="ok",P75,0),IF(T75="ok",S75,0),IF(W75="ok",V75,0),IF(Z75="ok",Y75,0),IF(AC75="ok",AB75,0),IF(AF75="ok",AE75,0),IF(AI75="ok",AH75,0),IF(AL75="ok",AK75,0),IF(AO75="ok",AN75,0),IF(AR75="ok",AQ75,0)))," €")))) -> de l'objectif annuel atteint (0 € / 750) : manque 750 € | G76: Les retraits du mois -> | AY76: Somme totale des retraits -> | BB76: =SUM(MAX(I76,J76),MAX(L76,M76),MAX(O76,P76),MAX(R76,S76),MAX(U76,V76),MAX(X76,Y76),MAX(AA76,AB76),MAX(AD76,AE76),MAX(AG76,AH76),MAX(AJ76,AK76),MAX(AM76,AN76),MAX(AP76,AQ76)) -> 0 | BD76: épargnés/mois
E77: Livret A - BANXO | I77: =D77+IF(I75>J75,I75,J75)-IF(J76<I76,I76,J76) -> 100 | L77: =I77+IF(L75>M75,L75,M75)-IF(M76<L76,L76,M76) -> 200 | O77: =L77+IF(O75>P75,O75,P75)-IF(P76<O76,O76,P76) -> 300 | R77: =O77+IF(R75>S75,R75,S75)-IF(S76<R76,R76,S76) -> 400 | U77: =R77+IF(U75>V75,U75,V75)-IF(V76<U76,U76,V76) -> 750 | X77: =U77+IF(X75>Y75,X75,Y75)-IF(Y76<X76,X76,Y76) -> 750 | AA77: =X77+IF(AA75>AB75,AA75,AB75)-IF(AB76<AA76,AA76,AB76) -> 750 | AD77: =AA77+IF(AD75>AE75,AD75,AE75)-IF(AE76<AD76,AD76,AE76) -> 750 | AG77: =AD77+IF(AG75>AH75,AG75,AH75)-IF(AH76<AG76,AG76,AH76) -> 750 | AJ77: =AG77+IF(AJ75>AK75,AJ75,AK75)-IF(AK76<AJ76,AJ76,AK76) -> 750 | AM77: =AJ77+IF(AM75>AN75,AM75,AN75)-IF(AN76<AM76,AM76,AN76) -> 750 | AP77: =AM77+IF(AP75>AQ75,AP75,AQ75)-IF(AQ76<AP76,AP76,AQ76) -> 750 | AT77: =AP77+BB75 -> 1500 | AU77: =AP77+BB75*4 -> 3750 | AY77: =IF(E77="","",E77) -> Livret A - BANXO | BB77: =AP77 -> 750
D78: =1+D75 -> 9 | E78: Epargne pour "Projet personnel" | J78: 25 | M78: 25 | P78: 25 | S78: 25 | AT78: =CONCATENATE("Moy. de ",INT(BB78/12)," €/mois") -> Moy. de 8 €/mois | AU78: =CONCATENATE("Moy. de ",INT(BB78/12)," €/mois") -> Moy. de 8 €/mois | AY78: =IF(E78="","",E78) -> Epargne pour "Projet personnel" | BB78: =SUM(MAX(I78,J78),MAX(L78,M78),MAX(O78,P78),MAX(R78,S78),MAX(U78,V78),MAX(X78,Y78),MAX(AA78,AB78),MAX(AD78,AE78),MAX(AG78,AH78),MAX(AJ78,AK78),MAX(AM78,AN78),MAX(AP78,AQ78)) -> 100 | BD78: =BB78/12 -> 8.3333333
D79: ExtraP Off | E79: =IF(BB78=0,"",INT(SUM(IF(K78="ok",J78,0),IF(N78="ok",M78,0),IF(Q78="ok",P78,0),IF(T78="ok",S78,0),IF(W78="ok",V78,0),IF(Z78="ok",Y78,0),IF(AC78="ok",AB78,0),IF(AF78="ok",AE78,0),IF(AI78="ok",AH78,0),IF(AL78="ok",AK78,0),IF(AO78="ok",AN78,0),IF(AR78="ok",AQ78,0))*100/BB78)/100) -> 0 | F79: =IF(BB78=0,"",CONCATENATE("de l'objectif annuel atteint ","(",INT(SUM(IF(K78="ok",J78,0),IF(N78="ok",M78,0),IF(Q78="ok",P78,0),IF(T78="ok",S78,0),IF(W78="ok",V78,0),IF(Z78="ok",Y78,0),IF(AC78="ok",AB78,0),IF(AF78="ok",AE78,0),IF(AI78="ok",AH78,0),IF(AL78="ok",AK78,0),IF(AO78="ok",AN78,0),IF(AR78="ok",AQ78,0)))," € / ",BB78,")",IF(BB78=INT(SUM(IF(K78="ok",J78,0),IF(N78="ok",M78,0),IF(Q78="ok",P78,0),IF(T78="ok",S78,0),IF(W78="ok",V78,0),IF(Z78="ok",Y78,0),IF(AC78="ok",AB78,0),IF(AF78="ok",AE78,0),IF(AI78="ok",AH78,0),IF(AL78="ok",AK78,0),IF(AO78="ok",AN78,0),IF(AR78="ok",AQ78,0))),"",CONCATENATE(" : manque ",BB78-INT(SUM(IF(K78="ok",J78,0),IF(N78="ok",M78,0),IF(Q78="ok",P78,0),IF(T78="ok",S78,0),IF(W78="ok",V78,0),IF(Z78="ok",Y78,0),IF(AC78="ok",AB78,0),IF(AF78="ok",AE78,0),IF(AI78="ok",AH78,0),IF(AL78="ok",AK78,0),IF(AO78="ok",AN78,0),IF(AR78="ok",AQ78,0)))," €")))) -> de l'objectif annuel atteint (0 € / 100) : manque 100 € | G79: Les retraits du mois -> | AY79: Somme totale des retraits -> | BB79: =SUM(MAX(I79,J79),MAX(L79,M79),MAX(O79,P79),MAX(R79,S79),MAX(U79,V79),MAX(X79,Y79),MAX(AA79,AB79),MAX(AD79,AE79),MAX(AG79,AH79),MAX(AJ79,AK79),MAX(AM79,AN79),MAX(AP79,AQ79)) -> 0 | BD79: épargnés/mois
E80: Livret A - BANXO | I80: =D80+IF(I78>J78,I78,J78)-IF(J79<I79,I79,J79) -> 25 | L80: =I80+IF(L78>M78,L78,M78)-IF(M79<L79,L79,M79) -> 50 | O80: =L80+IF(O78>P78,O78,P78)-IF(P79<O79,O79,P79) -> 75 | R80: =O80+IF(R78>S78,R78,S78)-IF(S79<R79,R79,S79) -> 100 | U80: =R80+IF(U78>V78,U78,V78)-IF(V79<U79,U79,V79) -> 100 | X80: =U80+IF(X78>Y78,X78,Y78)-IF(Y79<X79,X79,Y79) -> 100 | AA80: =X80+IF(AA78>AB78,AA78,AB78)-IF(AB79<AA79,AA79,AB79) -> 100 | AD80: =AA80+IF(AD78>AE78,AD78,AE78)-IF(AE79<AD79,AD79,AE79) -> 100 | AG80: =AD80+IF(AG78>AH78,AG78,AH78)-IF(AH79<AG79,AG79,AH79) -> 100 | AJ80: =AG80+IF(AJ78>AK78,AJ78,AK78)-IF(AK79<AJ79,AJ79,AK79) -> 100 | AM80: =AJ80+IF(AM78>AN78,AM78,AN78)-IF(AN79<AM79,AM79,AN79) -> 100 | AP80: =AM80+IF(AP78>AQ78,AP78,AQ78)-IF(AQ79<AP79,AP79,AQ79) -> 100 | AT80: =AP80+BB78 -> 200 | AU80: =AP80+BB78*4 -> 500 | AY80: =IF(E80="","",E80) -> Livret A - BANXO | BB80: =AP80 -> 100
D81: =1+D78 -> 10 | E81: Trésorerie "Jeune prodige conférence" | J81: 100 | M81: 100 | P81: 100 | S81: 100 | AT81: =CONCATENATE("Moy. de ",INT(BB81/12)," €/mois") -> Moy. de 33 €/mois | AU81: =CONCATENATE("Moy. de ",INT(BB81/12)," €/mois") -> Moy. de 33 €/mois | AY81: =IF(E81="","",E81) -> Trésorerie "Jeune prodige conférence" | BB81: =SUM(MAX(I81,J81),MAX(L81,M81),MAX(O81,P81),MAX(R81,S81),MAX(U81,V81),MAX(X81,Y81),MAX(AA81,AB81),MAX(AD81,AE81),MAX(AG81,AH81),MAX(AJ81,AK81),MAX(AM81,AN81),MAX(AP81,AQ81)) -> 400 | BD81: =BB81/12 -> 33.333333
D82: ExtraP Off | E82: =IF(BB81=0,"",INT(SUM(IF(K81="ok",J81,0),IF(N81="ok",M81,0),IF(Q81="ok",P81,0),IF(T81="ok",S81,0),IF(W81="ok",V81,0),IF(Z81="ok",Y81,0),IF(AC81="ok",AB81,0),IF(AF81="ok",AE81,0),IF(AI81="ok",AH81,0),IF(AL81="ok",AK81,0),IF(AO81="ok",AN81,0),IF(AR81="ok",AQ81,0))*100/BB81)/100) -> 0 | F82: =IF(BB81=0,"",CONCATENATE("de l'objectif annuel atteint ","(",INT(SUM(IF(K81="ok",J81,0),IF(N81="ok",M81,0),IF(Q81="ok",P81,0),IF(T81="ok",S81,0),IF(W81="ok",V81,0),IF(Z81="ok",Y81,0),IF(AC81="ok",AB81,0),IF(AF81="ok",AE81,0),IF(AI81="ok",AH81,0),IF(AL81="ok",AK81,0),IF(AO81="ok",AN81,0),IF(AR81="ok",AQ81,0)))," € / ",BB81,")",IF(BB81=INT(SUM(IF(K81="ok",J81,0),IF(N81="ok",M81,0),IF(Q81="ok",P81,0),IF(T81="ok",S81,0),IF(W81="ok",V81,0),IF(Z81="ok",Y81,0),IF(AC81="ok",AB81,0),IF(AF81="ok",AE81,0),IF(AI81="ok",AH81,0),IF(AL81="ok",AK81,0),IF(AO81="ok",AN81,0),IF(AR81="ok",AQ81,0))),"",CONCATENATE(" : manque ",BB81-INT(SUM(IF(K81="ok",J81,0),IF(N81="ok",M81,0),IF(Q81="ok",P81,0),IF(T81="ok",S81,0),IF(W81="ok",V81,0),IF(Z81="ok",Y81,0),IF(AC81="ok",AB81,0),IF(AF81="ok",AE81,0),IF(AI81="ok",AH81,0),IF(AL81="ok",AK81,0),IF(AO81="ok",AN81,0),IF(AR81="ok",AQ81,0)))," €")))) -> de l'objectif annuel atteint (0 € / 400) : manque 400 € | G82: Les retraits du mois -> | AY82: Somme totale des retraits -> | BB82: =SUM(MAX(I82,J82),MAX(L82,M82),MAX(O82,P82),MAX(R82,S82),MAX(U82,V82),MAX(X82,Y82),MAX(AA82,AB82),MAX(AD82,AE82),MAX(AG82,AH82),MAX(AJ82,AK82),MAX(AM82,AN82),MAX(AP82,AQ82)) -> 0 | BD82: épargnés/mois
E83: - compte d'épargne à saisir - | I83: =D83+IF(I81>J81,I81,J81)-IF(J82<I82,I82,J82) -> 100 | L83: =I83+IF(L81>M81,L81,M81)-IF(M82<L82,L82,M82) -> 200 | O83: =L83+IF(O81>P81,O81,P81)-IF(P82<O82,O82,P82) -> 300 | R83: =O83+IF(R81>S81,R81,S81)-IF(S82<R82,R82,S82) -> 400 | U83: =R83+IF(U81>V81,U81,V81)-IF(V82<U82,U82,V82) -> 400 | X83: =U83+IF(X81>Y81,X81,Y81)-IF(Y82<X82,X82,Y82) -> 400 | AA83: =X83+IF(AA81>AB81,AA81,AB81)-IF(AB82<AA82,AA82,AB82) -> 400 | AD83: =AA83+IF(AD81>AE81,AD81,AE81)-IF(AE82<AD82,AD82,AE82) -> 400 | AG83: =AD83+IF(AG81>AH81,AG81,AH81)-IF(AH82<AG82,AG82,AH82) -> 400 | AJ83: =AG83+IF(AJ81>AK81,AJ81,AK81)-IF(AK82<AJ82,AJ82,AK82) -> 400 | AM83: =AJ83+IF(AM81>AN81,AM81,AN81)-IF(AN82<AM82,AM82,AN82) -> 400 | AP83: =AM83+IF(AP81>AQ81,AP81,AQ81)-IF(AQ82<AP82,AP82,AQ82) -> 400 | AT83: =AP83+BB81 -> 800 | AU83: =AP83+BB81*4 -> 2000 | AY83: =IF(E83="","",E83) -> - compte d'épargne à saisir - | BB83: =AP83 -> 400
D84: =1+D81 -> 11 | E84: Capital "NAISSANCE" - Enfant 1 | J84: 36.5 | M84: 36.5 | P84: 36.5 | S84: 36.5 | AT84: =CONCATENATE("Moy. de ",INT(BB84/12)," €/mois") -> Moy. de 12 €/mois | AU84: =CONCATENATE("Moy. de ",INT(BB84/12)," €/mois") -> Moy. de 12 €/mois | AY84: =IF(E84="","",E84) -> Capital "NAISSANCE" - Enfant 1 | BB84: =SUM(MAX(I84,J84),MAX(L84,M84),MAX(O84,P84),MAX(R84,S84),MAX(U84,V84),MAX(X84,Y84),MAX(AA84,AB84),MAX(AD84,AE84),MAX(AG84,AH84),MAX(AJ84,AK84),MAX(AM84,AN84),MAX(AP84,AQ84)) -> 146 | BD84: =BB84/12 -> 12.166667
D85: ExtraP Off | E85: =IF(BB84=0,"",INT(SUM(IF(K84="ok",J84,0),IF(N84="ok",M84,0),IF(Q84="ok",P84,0),IF(T84="ok",S84,0),IF(W84="ok",V84,0),IF(Z84="ok",Y84,0),IF(AC84="ok",AB84,0),IF(AF84="ok",AE84,0),IF(AI84="ok",AH84,0),IF(AL84="ok",AK84,0),IF(AO84="ok",AN84,0),IF(AR84="ok",AQ84,0))*100/BB84)/100) -> 0 | F85: =IF(BB84=0,"",CONCATENATE("de l'objectif annuel atteint ","(",INT(SUM(IF(K84="ok",J84,0),IF(N84="ok",M84,0),IF(Q84="ok",P84,0),IF(T84="ok",S84,0),IF(W84="ok",V84,0),IF(Z84="ok",Y84,0),IF(AC84="ok",AB84,0),IF(AF84="ok",AE84,0),IF(AI84="ok",AH84,0),IF(AL84="ok",AK84,0),IF(AO84="ok",AN84,0),IF(AR84="ok",AQ84,0)))," € / ",BB84,")",IF(BB84=INT(SUM(IF(K84="ok",J84,0),IF(N84="ok",M84,0),IF(Q84="ok",P84,0),IF(T84="ok",S84,0),IF(W84="ok",V84,0),IF(Z84="ok",Y84,0),IF(AC84="ok",AB84,0),IF(AF84="ok",AE84,0),IF(AI84="ok",AH84,0),IF(AL84="ok",AK84,0),IF(AO84="ok",AN84,0),IF(AR84="ok",AQ84,0))),"",CONCATENATE(" : manque ",BB84-INT(SUM(IF(K84="ok",J84,0),IF(N84="ok",M84,0),IF(Q84="ok",P84,0),IF(T84="ok",S84,0),IF(W84="ok",V84,0),IF(Z84="ok",Y84,0),IF(AC84="ok",AB84,0),IF(AF84="ok",AE84,0),IF(AI84="ok",AH84,0),IF(AL84="ok",AK84,0),IF(AO84="ok",AN84,0),IF(AR84="ok",AQ84,0)))," €")))) -> de l'objectif annuel atteint (0 € / 146) : manque 146 € | G85: Les retraits du mois -> | AY85: Somme totale des retraits -> | BB85: =SUM(MAX(I85,J85),MAX(L85,M85),MAX(O85,P85),MAX(R85,S85),MAX(U85,V85),MAX(X85,Y85),MAX(AA85,AB85),MAX(AD85,AE85),MAX(AG85,AH85),MAX(AJ85,AK85),MAX(AM85,AN85),MAX(AP85,AQ85)) -> 0 | BD85: épargnés/mois
E86: - compte d'épargne à saisir - | I86: =D86+IF(I84>J84,I84,J84)-IF(J85<I85,I85,J85) -> 36.5 | L86: =I86+IF(L84>M84,L84,M84)-IF(M85<L85,L85,M85) -> 73 | O86: =L86+IF(O84>P84,O84,P84)-IF(P85<O85,O85,P85) -> 109.5 | R86: =O86+IF(R84>S84,R84,S84)-IF(S85<R85,R85,S85) -> 146 | U86: =R86+IF(U84>V84,U84,V84)-IF(V85<U85,U85,V85) -> 146 | X86: =U86+IF(X84>Y84,X84,Y84)-IF(Y85<X85,X85,Y85) -> 146 | AA86: =X86+IF(AA84>AB84,AA84,AB84)-IF(AB85<AA85,AA85,AB85) -> 146 | AD86: =AA86+IF(AD84>AE84,AD84,AE84)-IF(AE85<AD85,AD85,AE85) -> 146 | AG86: =AD86+IF(AG84>AH84,AG84,AH84)-IF(AH85<AG85,AG85,AH85) -> 146 | AJ86: =AG86+IF(AJ84>AK84,AJ84,AK84)-IF(AK85<AJ85,AJ85,AK85) -> 146 | AM86: =AJ86+IF(AM84>AN84,AM84,AN84)-IF(AN85<AM85,AM85,AN85) -> 146 | AP86: =AM86+IF(AP84>AQ84,AP84,AQ84)-IF(AQ85<AP85,AP85,AQ85) -> 146 | AT86: =AP86+BB84 -> 292 | AU86: =AP86+BB84*4 -> 730 | AY86: =IF(E86="","",E86) -> - compte d'épargne à saisir - | BB86: =AP86 -> 146
D87: =1+D84 -> 12 | E87: Capital "NAISSANCE" - Enfant 2 | J87: 36.5 | M87: 36.5 | P87: 36.5 | S87: 36.5 | AT87: =CONCATENATE("Moy. de ",INT(BB87/12)," €/mois") -> Moy. de 12 €/mois | AU87: =CONCATENATE("Moy. de ",INT(BB87/12)," €/mois") -> Moy. de 12 €/mois | AY87: =IF(E87="","",E87) -> Capital "NAISSANCE" - Enfant 2 | BB87: =SUM(MAX(I87,J87),MAX(L87,M87),MAX(O87,P87),MAX(R87,S87),MAX(U87,V87),MAX(X87,Y87),MAX(AA87,AB87),MAX(AD87,AE87),MAX(AG87,AH87),MAX(AJ87,AK87),MAX(AM87,AN87),MAX(AP87,AQ87)) -> 146 | BD87: =BB87/12 -> 12.166667
D88: ExtraP Off | E88: =IF(BB87=0,"",INT(SUM(IF(K87="ok",J87,0),IF(N87="ok",M87,0),IF(Q87="ok",P87,0),IF(T87="ok",S87,0),IF(W87="ok",V87,0),IF(Z87="ok",Y87,0),IF(AC87="ok",AB87,0),IF(AF87="ok",AE87,0),IF(AI87="ok",AH87,0),IF(AL87="ok",AK87,0),IF(AO87="ok",AN87,0),IF(AR87="ok",AQ87,0))*100/BB87)/100) -> 0 | F88: =IF(BB87=0,"",CONCATENATE("de l'objectif annuel atteint ","(",INT(SUM(IF(K87="ok",J87,0),IF(N87="ok",M87,0),IF(Q87="ok",P87,0),IF(T87="ok",S87,0),IF(W87="ok",V87,0),IF(Z87="ok",Y87,0),IF(AC87="ok",AB87,0),IF(AF87="ok",AE87,0),IF(AI87="ok",AH87,0),IF(AL87="ok",AK87,0),IF(AO87="ok",AN87,0),IF(AR87="ok",AQ87,0)))," € / ",BB87,")",IF(BB87=INT(SUM(IF(K87="ok",J87,0),IF(N87="ok",M87,0),IF(Q87="ok",P87,0),IF(T87="ok",S87,0),IF(W87="ok",V87,0),IF(Z87="ok",Y87,0),IF(AC87="ok",AB87,0),IF(AF87="ok",AE87,0),IF(AI87="ok",AH87,0),IF(AL87="ok",AK87,0),IF(AO87="ok",AN87,0),IF(AR87="ok",AQ87,0))),"",CONCATENATE(" : manque ",BB87-INT(SUM(IF(K87="ok",J87,0),IF(N87="ok",M87,0),IF(Q87="ok",P87,0),IF(T87="ok",S87,0),IF(W87="ok",V87,0),IF(Z87="ok",Y87,0),IF(AC87="ok",AB87,0),IF(AF87="ok",AE87,0),IF(AI87="ok",AH87,0),IF(AL87="ok",AK87,0),IF(AO87="ok",AN87,0),IF(AR87="ok",AQ87,0)))," €")))) -> de l'objectif annuel atteint (0 € / 146) : manque 146 € | G88: Les retraits du mois -> | AY88: Somme totale des retraits -> | BB88: =SUM(MAX(I88,J88),MAX(L88,M88),MAX(O88,P88),MAX(R88,S88),MAX(U88,V88),MAX(X88,Y88),MAX(AA88,AB88),MAX(AD88,AE88),MAX(AG88,AH88),MAX(AJ88,AK88),MAX(AM88,AN88),MAX(AP88,AQ88)) -> 0 | BD88: épargnés/mois
E89: - compte d'épargne à saisir - | I89: =D89+IF(I87>J87,I87,J87)-IF(J88<I88,I88,J88) -> 36.5 | L89: =I89+IF(L87>M87,L87,M87)-IF(M88<L88,L88,M88) -> 73 | O89: =L89+IF(O87>P87,O87,P87)-IF(P88<O88,O88,P88) -> 109.5 | R89: =O89+IF(R87>S87,R87,S87)-IF(S88<R88,R88,S88) -> 146 | U89: =R89+IF(U87>V87,U87,V87)-IF(V88<U88,U88,V88) -> 146 | X89: =U89+IF(X87>Y87,X87,Y87)-IF(Y88<X88,X88,Y88) -> 146 | AA89: =X89+IF(AA87>AB87,AA87,AB87)-IF(AB88<AA88,AA88,AB88) -> 146 | AD89: =AA89+IF(AD87>AE87,AD87,AE87)-IF(AE88<AD88,AD88,AE88) -> 146 | AG89: =AD89+IF(AG87>AH87,AG87,AH87)-IF(AH88<AG88,AG88,AH88) -> 146 | AJ89: =AG89+IF(AJ87>AK87,AJ87,AK87)-IF(AK88<AJ88,AJ88,AK88) -> 146 | AM89: =AJ89+IF(AM87>AN87,AM87,AN87)-IF(AN88<AM88,AM88,AN88) -> 146 | AP89: =AM89+IF(AP87>AQ87,AP87,AQ87)-IF(AQ88<AP88,AP88,AQ88) -> 146 | AT89: =AP89+BB87 -> 292 | AU89: =AP89+BB87*4 -> 730 | AY89: =IF(E89="","",E89) -> - compte d'épargne à saisir - | BB89: =AP89 -> 146
D90: =1+D87 -> 13 | E90: Indiquer le nom du projet à financer | AT90: =CONCATENATE("Moy. de ",INT(BB90/12)," €/mois") -> Moy. de 0 €/mois | AU90: =CONCATENATE("Moy. de ",INT(BB90/12)," €/mois") -> Moy. de 0 €/mois | AY90: =IF(E90="","",E90) -> Indiquer le nom du projet à financer | BB90: =SUM(MAX(I90,J90),MAX(L90,M90),MAX(O90,P90),MAX(R90,S90),MAX(U90,V90),MAX(X90,Y90),MAX(AA90,AB90),MAX(AD90,AE90),MAX(AG90,AH90),MAX(AJ90,AK90),MAX(AM90,AN90),MAX(AP90,AQ90)) -> 0 | BD90: =BB90/12 -> 0
D91: ExtraP Off | E91: =IF(BB90=0,"",INT(SUM(IF(K90="ok",J90,0),IF(N90="ok",M90,0),IF(Q90="ok",P90,0),IF(T90="ok",S90,0),IF(W90="ok",V90,0),IF(Z90="ok",Y90,0),IF(AC90="ok",AB90,0),IF(AF90="ok",AE90,0),IF(AI90="ok",AH90,0),IF(AL90="ok",AK90,0),IF(AO90="ok",AN90,0),IF(AR90="ok",AQ90,0))*100/BB90)/100) | F91: =IF(BB90=0,"",CONCATENATE("de l'objectif annuel atteint ","(",INT(SUM(IF(K90="ok",J90,0),IF(N90="ok",M90,0),IF(Q90="ok",P90,0),IF(T90="ok",S90,0),IF(W90="ok",V90,0),IF(Z90="ok",Y90,0),IF(AC90="ok",AB90,0),IF(AF90="ok",AE90,0),IF(AI90="ok",AH90,0),IF(AL90="ok",AK90,0),IF(AO90="ok",AN90,0),IF(AR90="ok",AQ90,0)))," € / ",BB90,")",IF(BB90=INT(SUM(IF(K90="ok",J90,0),IF(N90="ok",M90,0),IF(Q90="ok",P90,0),IF(T90="ok",S90,0),IF(W90="ok",V90,0),IF(Z90="ok",Y90,0),IF(AC90="ok",AB90,0),IF(AF90="ok",AE90,0),IF(AI90="ok",AH90,0),IF(AL90="ok",AK90,0),IF(AO90="ok",AN90,0),IF(AR90="ok",AQ90,0))),"",CONCATENATE(" : manque ",BB90-INT(SUM(IF(K90="ok",J90,0),IF(N90="ok",M90,0),IF(Q90="ok",P90,0),IF(T90="ok",S90,0),IF(W90="ok",V90,0),IF(Z90="ok",Y90,0),IF(AC90="ok",AB90,0),IF(AF90="ok",AE90,0),IF(AI90="ok",AH90,0),IF(AL90="ok",AK90,0),IF(AO90="ok",AN90,0),IF(AR90="ok",AQ90,0)))," €")))) | G91: Les retraits du mois -> | AY91: Somme totale des retraits -> | BB91: =SUM(MAX(I91,J91),MAX(L91,M91),MAX(O91,P91),MAX(R91,S91),MAX(U91,V91),MAX(X91,Y91),MAX(AA91,AB91),MAX(AD91,AE91),MAX(AG91,AH91),MAX(AJ91,AK91),MAX(AM91,AN91),MAX(AP91,AQ91)) -> 0 | BD91: épargnés/mois
E92: - compte d'épargne à saisir - | I92: =D92+IF(I90>J90,I90,J90)-IF(J91<I91,I91,J91) -> 0 | L92: =I92+IF(L90>M90,L90,M90)-IF(M91<L91,L91,M91) -> 0 | O92: =L92+IF(O90>P90,O90,P90)-IF(P91<O91,O91,P91) -> 0 | R92: =O92+IF(R90>S90,R90,S90)-IF(S91<R91,R91,S91) -> 0 | U92: =R92+IF(U90>V90,U90,V90)-IF(V91<U91,U91,V91) -> 0 | X92: =U92+IF(X90>Y90,X90,Y90)-IF(Y91<X91,X91,Y91) -> 0 | AA92: =X92+IF(AA90>AB90,AA90,AB90)-IF(AB91<AA91,AA91,AB91) -> 0 | AD92: =AA92+IF(AD90>AE90,AD90,AE90)-IF(AE91<AD91,AD91,AE91) -> 0 | AG92: =AD92+IF(AG90>AH90,AG90,AH90)-IF(AH91<AG91,AG91,AH91) -> 0 | AJ92: =AG92+IF(AJ90>AK90,AJ90,AK90)-IF(AK91<AJ91,AJ91,AK91) -> 0 | AM92: =AJ92+IF(AM90>AN90,AM90,AN90)-IF(AN91<AM91,AM91,AN91) -> 0 | AP92: =AM92+IF(AP90>AQ90,AP90,AQ90)-IF(AQ91<AP91,AP91,AQ91) -> 0 | AT92: =AP92+BB90 -> 0 | AU92: =AP92+BB90*4 -> 0 | AY92: =IF(E92="","",E92) -> - compte d'épargne à saisir - | BB92: =AP92 -> 0
D93: =1+D90 -> 14 | E93: Indiquer le nom du projet à financer | AT93: =CONCATENATE("Moy. de ",INT(BB93/12)," €/mois") -> Moy. de 0 €/mois | AU93: =CONCATENATE("Moy. de ",INT(BB93/12)," €/mois") -> Moy. de 0 €/mois | AY93: =IF(E93="","",E93) -> Indiquer le nom du projet à financer | BB93: =SUM(MAX(I93,J93),MAX(L93,M93),MAX(O93,P93),MAX(R93,S93),MAX(U93,V93),MAX(X93,Y93),MAX(AA93,AB93),MAX(AD93,AE93),MAX(AG93,AH93),MAX(AJ93,AK93),MAX(AM93,AN93),MAX(AP93,AQ93)) -> 0 | BD93: =BB93/12 -> 0
D94: ExtraP Off | E94: =IF(BB93=0,"",INT(SUM(IF(K93="ok",J93,0),IF(N93="ok",M93,0),IF(Q93="ok",P93,0),IF(T93="ok",S93,0),IF(W93="ok",V93,0),IF(Z93="ok",Y93,0),IF(AC93="ok",AB93,0),IF(AF93="ok",AE93,0),IF(AI93="ok",AH93,0),IF(AL93="ok",AK93,0),IF(AO93="ok",AN93,0),IF(AR93="ok",AQ93,0))*100/BB93)/100) | F94: =IF(BB93=0,"",CONCATENATE("de l'objectif annuel atteint ","(",INT(SUM(IF(K93="ok",J93,0),IF(N93="ok",M93,0),IF(Q93="ok",P93,0),IF(T93="ok",S93,0),IF(W93="ok",V93,0),IF(Z93="ok",Y93,0),IF(AC93="ok",AB93,0),IF(AF93="ok",AE93,0),IF(AI93="ok",AH93,0),IF(AL93="ok",AK93,0),IF(AO93="ok",AN93,0),IF(AR93="ok",AQ93,0)))," € / ",BB93,")",IF(BB93=INT(SUM(IF(K93="ok",J93,0),IF(N93="ok",M93,0),IF(Q93="ok",P93,0),IF(T93="ok",S93,0),IF(W93="ok",V93,0),IF(Z93="ok",Y93,0),IF(AC93="ok",AB93,0),IF(AF93="ok",AE93,0),IF(AI93="ok",AH93,0),IF(AL93="ok",AK93,0),IF(AO93="ok",AN93,0),IF(AR93="ok",AQ93,0))),"",CONCATENATE(" : manque ",BB93-INT(SUM(IF(K93="ok",J93,0),IF(N93="ok",M93,0),IF(Q93="ok",P93,0),IF(T93="ok",S93,0),IF(W93="ok",V93,0),IF(Z93="ok",Y93,0),IF(AC93="ok",AB93,0),IF(AF93="ok",AE93,0),IF(AI93="ok",AH93,0),IF(AL93="ok",AK93,0),IF(AO93="ok",AN93,0),IF(AR93="ok",AQ93,0)))," €")))) | G94: Les retraits du mois -> | AY94: Somme totale des retraits -> | BB94: =SUM(MAX(I94,J94),MAX(L94,M94),MAX(O94,P94),MAX(R94,S94),MAX(U94,V94),MAX(X94,Y94),MAX(AA94,AB94),MAX(AD94,AE94),MAX(AG94,AH94),MAX(AJ94,AK94),MAX(AM94,AN94),MAX(AP94,AQ94)) -> 0 | BD94: épargnés/mois
E95: - compte d'épargne à saisir - | I95: =D95+IF(I93>J93,I93,J93)-IF(J94<I94,I94,J94) -> 0 | L95: =I95+IF(L93>M93,L93,M93)-IF(M94<L94,L94,M94) -> 0 | O95: =L95+IF(O93>P93,O93,P93)-IF(P94<O94,O94,P94) -> 0 | R95: =O95+IF(R93>S93,R93,S93)-IF(S94<R94,R94,S94) -> 0 | U95: =R95+IF(U93>V93,U93,V93)-IF(V94<U94,U94,V94) -> 0 | X95: =U95+IF(X93>Y93,X93,Y93)-IF(Y94<X94,X94,Y94) -> 0 | AA95: =X95+IF(AA93>AB93,AA93,AB93)-IF(AB94<AA94,AA94,AB94) -> 0 | AD95: =AA95+IF(AD93>AE93,AD93,AE93)-IF(AE94<AD94,AD94,AE94) -> 0 | AG95: =AD95+IF(AG93>AH93,AG93,AH93)-IF(AH94<AG94,AG94,AH94) -> 0 | AJ95: =AG95+IF(AJ93>AK93,AJ93,AK93)-IF(AK94<AJ94,AJ94,AK94) -> 0 | AM95: =AJ95+IF(AM93>AN93,AM93,AN93)-IF(AN94<AM94,AM94,AN94) -> 0 | AP95: =AM95+IF(AP93>AQ93,AP93,AQ93)-IF(AQ94<AP94,AP94,AQ94) -> 0 | AT95: =AP95+BB93 -> 0 | AU95: =AP95+BB93*4 -> 0 | AY95: =IF(E95="","",E95) -> - compte d'épargne à saisir - | BB95: =AP95 -> 0
D96: =1+D93 -> 15 | E96: Indiquer le nom du projet à financer | AT96: =CONCATENATE("Moy. de ",INT(BB96/12)," €/mois") -> Moy. de 0 €/mois | AU96: =CONCATENATE("Moy. de ",INT(BB96/12)," €/mois") -> Moy. de 0 €/mois | AY96: =IF(E96="","",E96) -> Indiquer le nom du projet à financer | BB96: =SUM(MAX(I96,J96),MAX(L96,M96),MAX(O96,P96),MAX(R96,S96),MAX(U96,V96),MAX(X96,Y96),MAX(AA96,AB96),MAX(AD96,AE96),MAX(AG96,AH96),MAX(AJ96,AK96),MAX(AM96,AN96),MAX(AP96,AQ96)) -> 0 | BD96: =BB96/12 -> 0
D97: ExtraP Off | E97: =IF(BB96=0,"",INT(SUM(IF(K96="ok",J96,0),IF(N96="ok",M96,0),IF(Q96="ok",P96,0),IF(T96="ok",S96,0),IF(W96="ok",V96,0),IF(Z96="ok",Y96,0),IF(AC96="ok",AB96,0),IF(AF96="ok",AE96,0),IF(AI96="ok",AH96,0),IF(AL96="ok",AK96,0),IF(AO96="ok",AN96,0),IF(AR96="ok",AQ96,0))*100/BB96)/100) | F97: =IF(BB96=0,"",CONCATENATE("de l'objectif annuel atteint ","(",INT(SUM(IF(K96="ok",J96,0),IF(N96="ok",M96,0),IF(Q96="ok",P96,0),IF(T96="ok",S96,0),IF(W96="ok",V96,0),IF(Z96="ok",Y96,0),IF(AC96="ok",AB96,0),IF(AF96="ok",AE96,0),IF(AI96="ok",AH96,0),IF(AL96="ok",AK96,0),IF(AO96="ok",AN96,0),IF(AR96="ok",AQ96,0)))," € / ",BB96,")",IF(BB96=INT(SUM(IF(K96="ok",J96,0),IF(N96="ok",M96,0),IF(Q96="ok",P96,0),IF(T96="ok",S96,0),IF(W96="ok",V96,0),IF(Z96="ok",Y96,0),IF(AC96="ok",AB96,0),IF(AF96="ok",AE96,0),IF(AI96="ok",AH96,0),IF(AL96="ok",AK96,0),IF(AO96="ok",AN96,0),IF(AR96="ok",AQ96,0))),"",CONCATENATE(" : manque ",BB96-INT(SUM(IF(K96="ok",J96,0),IF(N96="ok",M96,0),IF(Q96="ok",P96,0),IF(T96="ok",S96,0),IF(W96="ok",V96,0),IF(Z96="ok",Y96,0),IF(AC96="ok",AB96,0),IF(AF96="ok",AE96,0),IF(AI96="ok",AH96,0),IF(AL96="ok",AK96,0),IF(AO96="ok",AN96,0),IF(AR96="ok",AQ96,0)))," €")))) | G97: Les retraits du mois -> | AY97: Somme totale des retraits -> | BB97: =SUM(MAX(I97,J97),MAX(L97,M97),MAX(O97,P97),MAX(R97,S97),MAX(U97,V97),MAX(X97,Y97),MAX(AA97,AB97),MAX(AD97,AE97),MAX(AG97,AH97),MAX(AJ97,AK97),MAX(AM97,AN97),MAX(AP97,AQ97)) -> 0 | BD97: épargnés/mois
E98: - compte d'épargne à saisir - | I98: =D98+IF(I96>J96,I96,J96)-IF(J97<I97,I97,J97) -> 0 | L98: =I98+IF(L96>M96,L96,M96)-IF(M97<L97,L97,M97) -> 0 | O98: =L98+IF(O96>P96,O96,P96)-IF(P97<O97,O97,P97) -> 0 | R98: =O98+IF(R96>S96,R96,S96)-IF(S97<R97,R97,S97) -> 0 | U98: =R98+IF(U96>V96,U96,V96)-IF(V97<U97,U97,V97) -> 0 | X98: =U98+IF(X96>Y96,X96,Y96)-IF(Y97<X97,X97,Y97) -> 0 | AA98: =X98+IF(AA96>AB96,AA96,AB96)-IF(AB97<AA97,AA97,AB97) -> 0 | AD98: =AA98+IF(AD96>AE96,AD96,AE96)-IF(AE97<AD97,AD97,AE97) -> 0 | AG98: =AD98+IF(AG96>AH96,AG96,AH96)-IF(AH97<AG97,AG97,AH97) -> 0 | AJ98: =AG98+IF(AJ96>AK96,AJ96,AK96)-IF(AK97<AJ97,AJ97,AK97) -> 0 | AM98: =AJ98+IF(AM96>AN96,AM96,AN96)-IF(AN97<AM97,AM97,AN97) -> 0 | AP98: =AM98+IF(AP96>AQ96,AP96,AQ96)-IF(AQ97<AP97,AP97,AQ97) -> 0 | AT98: =AP98+BB96 -> 0 | AU98: =AP98+BB96*4 -> 0 | AY98: =IF(E98="","",E98) -> - compte d'épargne à saisir - | BB98: =AP98 -> 0
D99: =1+D96 -> 16 | E99: Indiquer le nom du projet à financer | AT99: =CONCATENATE("Moy. de ",INT(BB99/12)," €/mois") -> Moy. de 0 €/mois | AU99: =CONCATENATE("Moy. de ",INT(BB99/12)," €/mois") -> Moy. de 0 €/mois | AY99: =IF(E99="","",E99) -> Indiquer le nom du projet à financer | BB99: =SUM(MAX(I99,J99),MAX(L99,M99),MAX(O99,P99),MAX(R99,S99),MAX(U99,V99),MAX(X99,Y99),MAX(AA99,AB99),MAX(AD99,AE99),MAX(AG99,AH99),MAX(AJ99,AK99),MAX(AM99,AN99),MAX(AP99,AQ99)) -> 0 | BD99: =BB99/12 -> 0
D100: ExtraP Off | E100: =IF(BB99=0,"",INT(SUM(IF(K99="ok",J99,0),IF(N99="ok",M99,0),IF(Q99="ok",P99,0),IF(T99="ok",S99,0),IF(W99="ok",V99,0),IF(Z99="ok",Y99,0),IF(AC99="ok",AB99,0),IF(AF99="ok",AE99,0),IF(AI99="ok",AH99,0),IF(AL99="ok",AK99,0),IF(AO99="ok",AN99,0),IF(AR99="ok",AQ99,0))*100/BB99)/100) | F100: =IF(BB99=0,"",CONCATENATE("de l'objectif annuel atteint ","(",INT(SUM(IF(K99="ok",J99,0),IF(N99="ok",M99,0),IF(Q99="ok",P99,0),IF(T99="ok",S99,0),IF(W99="ok",V99,0),IF(Z99="ok",Y99,0),IF(AC99="ok",AB99,0),IF(AF99="ok",AE99,0),IF(AI99="ok",AH99,0),IF(AL99="ok",AK99,0),IF(AO99="ok",AN99,0),IF(AR99="ok",AQ99,0)))," € / ",BB99,")",IF(BB99=INT(SUM(IF(K99="ok",J99,0),IF(N99="ok",M99,0),IF(Q99="ok",P99,0),IF(T99="ok",S99,0),IF(W99="ok",V99,0),IF(Z99="ok",Y99,0),IF(AC99="ok",AB99,0),IF(AF99="ok",AE99,0),IF(AI99="ok",AH99,0),IF(AL99="ok",AK99,0),IF(AO99="ok",AN99,0),IF(AR99="ok",AQ99,0))),"",CONCATENATE(" : manque ",BB99-INT(SUM(IF(K99="ok",J99,0),IF(N99="ok",M99,0),IF(Q99="ok",P99,0),IF(T99="ok",S99,0),IF(W99="ok",V99,0),IF(Z99="ok",Y99,0),IF(AC99="ok",AB99,0),IF(AF99="ok",AE99,0),IF(AI99="ok",AH99,0),IF(AL99="ok",AK99,0),IF(AO99="ok",AN99,0),IF(AR99="ok",AQ99,0)))," €")))) | G100: Les retraits du mois -> | AY100: Somme totale des retraits -> | BB100: =SUM(MAX(I100,J100),MAX(L100,M100),MAX(O100,P100),MAX(R100,S100),MAX(U100,V100),MAX(X100,Y100),MAX(AA100,AB100),MAX(AD100,AE100),MAX(AG100,AH100),MAX(AJ100,AK100),MAX(AM100,AN100),MAX(AP100,AQ100)) -> 0 | BD100: épargnés/mois
E101: - compte d'épargne à saisir - | I101: =D101+IF(I99>J99,I99,J99)-IF(J100<I100,I100,J100) -> 0 | L101: =I101+IF(L99>M99,L99,M99)-IF(M100<L100,L100,M100) -> 0 | O101: =L101+IF(O99>P99,O99,P99)-IF(P100<O100,O100,P100) -> 0 | R101: =O101+IF(R99>S99,R99,S99)-IF(S100<R100,R100,S100) -> 0 | U101: =R101+IF(U99>V99,U99,V99)-IF(V100<U100,U100,V100) -> 0 | X101: =U101+IF(X99>Y99,X99,Y99)-IF(Y100<X100,X100,Y100) -> 0 | AA101: =X101+IF(AA99>AB99,AA99,AB99)-IF(AB100<AA100,AA100,AB100) -> 0 | AD101: =AA101+IF(AD99>AE99,AD99,AE99)-IF(AE100<AD100,AD100,AE100) -> 0 | AG101: =AD101+IF(AG99>AH99,AG99,AH99)-IF(AH100<AG100,AG100,AH100) -> 0 | AJ101: =AG101+IF(AJ99>AK99,AJ99,AK99)-IF(AK100<AJ100,AJ100,AK100) -> 0 | AM101: =AJ101+IF(AM99>AN99,AM99,AN99)-IF(AN100<AM100,AM100,AN100) -> 0 | AP101: =AM101+IF(AP99>AQ99,AP99,AQ99)-IF(AQ100<AP100,AP100,AQ100) -> 0 | AT101: =AP101+BB99 -> 0 | AU101: =AP101+BB99*4 -> 0 | AY101: =IF(E101="","",E101) -> - compte d'épargne à saisir - | BB101: =AP101 -> 0
D102: =1+D99 -> 17 | E102: Indiquer le nom du projet à financer | AT102: =CONCATENATE("Moy. de ",INT(BB102/12)," €/mois") -> Moy. de 0 €/mois | AU102: =CONCATENATE("Moy. de ",INT(BB102/12)," €/mois") -> Moy. de 0 €/mois | AY102: =IF(E102="","",E102) -> Indiquer le nom du projet à financer | BB102: =SUM(MAX(I102,J102),MAX(L102,M102),MAX(O102,P102),MAX(R102,S102),MAX(U102,V102),MAX(X102,Y102),MAX(AA102,AB102),MAX(AD102,AE102),MAX(AG102,AH102),MAX(AJ102,AK102),MAX(AM102,AN102),MAX(AP102,AQ102)) -> 0 | BD102: =BB102/12 -> 0
D103: ExtraP Off | E103: =IF(BB102=0,"",INT(SUM(IF(K102="ok",J102,0),IF(N102="ok",M102,0),IF(Q102="ok",P102,0),IF(T102="ok",S102,0),IF(W102="ok",V102,0),IF(Z102="ok",Y102,0),IF(AC102="ok",AB102,0),IF(AF102="ok",AE102,0),IF(AI102="ok",AH102,0),IF(AL102="ok",AK102,0),IF(AO102="ok",AN102,0),IF(AR102="ok",AQ102,0))*100/BB102)/100) | F103: =IF(BB102=0,"",CONCATENATE("de l'objectif annuel atteint ","(",INT(SUM(IF(K102="ok",J102,0),IF(N102="ok",M102,0),IF(Q102="ok",P102,0),IF(T102="ok",S102,0),IF(W102="ok",V102,0),IF(Z102="ok",Y102,0),IF(AC102="ok",AB102,0),IF(AF102="ok",AE102,0),IF(AI102="ok",AH102,0),IF(AL102="ok",AK102,0),IF(AO102="ok",AN102,0),IF(AR102="ok",AQ102,0)))," € / ",BB102,")",IF(BB102=INT(SUM(IF(K102="ok",J102,0),IF(N102="ok",M102,0),IF(Q102="ok",P102,0),IF(T102="ok",S102,0),IF(W102="ok",V102,0),IF(Z102="ok",Y102,0),IF(AC102="ok",AB102,0),IF(AF102="ok",AE102,0),IF(AI102="ok",AH102,0),IF(AL102="ok",AK102,0),IF(AO102="ok",AN102,0),IF(AR102="ok",AQ102,0))),"",CONCATENATE(" : manque ",BB102-INT(SUM(IF(K102="ok",J102,0),IF(N102="ok",M102,0),IF(Q102="ok",P102,0),IF(T102="ok",S102,0),IF(W102="ok",V102,0),IF(Z102="ok",Y102,0),IF(AC102="ok",AB102,0),IF(AF102="ok",AE102,0),IF(AI102="ok",AH102,0),IF(AL102="ok",AK102,0),IF(AO102="ok",AN102,0),IF(AR102="ok",AQ102,0)))," €")))) | G103: Les retraits du mois -> | AY103: Somme totale des retraits -> | BB103: =SUM(MAX(I103,J103),MAX(L103,M103),MAX(O103,P103),MAX(R103,S103),MAX(U103,V103),MAX(X103,Y103),MAX(AA103,AB103),MAX(AD103,AE103),MAX(AG103,AH103),MAX(AJ103,AK103),MAX(AM103,AN103),MAX(AP103,AQ103)) -> 0 | BD103: épargnés/mois
E104: - compte d'épargne à saisir - | I104: =D104+IF(I102>J102,I102,J102)-IF(J103<I103,I103,J103) -> 0 | L104: =I104+IF(L102>M102,L102,M102)-IF(M103<L103,L103,M103) -> 0 | O104: =L104+IF(O102>P102,O102,P102)-IF(P103<O103,O103,P103) -> 0 | R104: =O104+IF(R102>S102,R102,S102)-IF(S103<R103,R103,S103) -> 0 | U104: =R104+IF(U102>V102,U102,V102)-IF(V103<U103,U103,V103) -> 0 | X104: =U104+IF(X102>Y102,X102,Y102)-IF(Y103<X103,X103,Y103) -> 0 | AA104: =X104+IF(AA102>AB102,AA102,AB102)-IF(AB103<AA103,AA103,AB103) -> 0 | AD104: =AA104+IF(AD102>AE102,AD102,AE102)-IF(AE103<AD103,AD103,AE103) -> 0 | AG104: =AD104+IF(AG102>AH102,AG102,AH102)-IF(AH103<AG103,AG103,AH103) -> 0 | AJ104: =AG104+IF(AJ102>AK102,AJ102,AK102)-IF(AK103<AJ103,AJ103,AK103) -> 0 | AM104: =AJ104+IF(AM102>AN102,AM102,AN102)-IF(AN103<AM103,AM103,AN103) -> 0 | AP104: =AM104+IF(AP102>AQ102,AP102,AQ102)-IF(AQ103<AP103,AP103,AQ103) -> 0 | AT104: =AP104+BB102 -> 0 | AU104: =AP104+BB102*4 -> 0 | AY104: =IF(E104="","",E104) -> - compte d'épargne à saisir - | BB104: =AP104 -> 0
D105: =1+D102 -> 18 | E105: Indiquer le nom du projet à financer | AT105: =CONCATENATE("Moy. de ",INT(BB105/12)," €/mois") -> Moy. de 0 €/mois | AU105: =CONCATENATE("Moy. de ",INT(BB105/12)," €/mois") -> Moy. de 0 €/mois | AY105: =IF(E105="","",E105) -> Indiquer le nom du projet à financer | BB105: =SUM(MAX(I105,J105),MAX(L105,M105),MAX(O105,P105),MAX(R105,S105),MAX(U105,V105),MAX(X105,Y105),MAX(AA105,AB105),MAX(AD105,AE105),MAX(AG105,AH105),MAX(AJ105,AK105),MAX(AM105,AN105),MAX(AP105,AQ105)) -> 0 | BD105: =BB105/12 -> 0
D106: ExtraP Off | E106: =IF(BB105=0,"",INT(SUM(IF(K105="ok",J105,0),IF(N105="ok",M105,0),IF(Q105="ok",P105,0),IF(T105="ok",S105,0),IF(W105="ok",V105,0),IF(Z105="ok",Y105,0),IF(AC105="ok",AB105,0),IF(AF105="ok",AE105,0),IF(AI105="ok",AH105,0),IF(AL105="ok",AK105,0),IF(AO105="ok",AN105,0),IF(AR105="ok",AQ105,0))*100/BB105)/100) | F106: =IF(BB105=0,"",CONCATENATE("de l'objectif annuel atteint ","(",INT(SUM(IF(K105="ok",J105,0),IF(N105="ok",M105,0),IF(Q105="ok",P105,0),IF(T105="ok",S105,0),IF(W105="ok",V105,0),IF(Z105="ok",Y105,0),IF(AC105="ok",AB105,0),IF(AF105="ok",AE105,0),IF(AI105="ok",AH105,0),IF(AL105="ok",AK105,0),IF(AO105="ok",AN105,0),IF(AR105="ok",AQ105,0)))," € / ",BB105,")",IF(BB105=INT(SUM(IF(K105="ok",J105,0),IF(N105="ok",M105,0),IF(Q105="ok",P105,0),IF(T105="ok",S105,0),IF(W105="ok",V105,0),IF(Z105="ok",Y105,0),IF(AC105="ok",AB105,0),IF(AF105="ok",AE105,0),IF(AI105="ok",AH105,0),IF(AL105="ok",AK105,0),IF(AO105="ok",AN105,0),IF(AR105="ok",AQ105,0))),"",CONCATENATE(" : manque ",BB105-INT(SUM(IF(K105="ok",J105,0),IF(N105="ok",M105,0),IF(Q105="ok",P105,0),IF(T105="ok",S105,0),IF(W105="ok",V105,0),IF(Z105="ok",Y105,0),IF(AC105="ok",AB105,0),IF(AF105="ok",AE105,0),IF(AI105="ok",AH105,0),IF(AL105="ok",AK105,0),IF(AO105="ok",AN105,0),IF(AR105="ok",AQ105,0)))," €")))) | G106: Les retraits du mois -> | AY106: Somme totale des retraits -> | BB106: =SUM(MAX(I106,J106),MAX(L106,M106),MAX(O106,P106),MAX(R106,S106),MAX(U106,V106),MAX(X106,Y106),MAX(AA106,AB106),MAX(AD106,AE106),MAX(AG106,AH106),MAX(AJ106,AK106),MAX(AM106,AN106),MAX(AP106,AQ106)) -> 0 | BD106: épargnés/mois
E107: - compte d'épargne à saisir - | I107: =D107+IF(I105>J105,I105,J105)-IF(J106<I106,I106,J106) -> 0 | L107: =I107+IF(L105>M105,L105,M105)-IF(M106<L106,L106,M106) -> 0 | O107: =L107+IF(O105>P105,O105,P105)-IF(P106<O106,O106,P106) -> 0 | R107: =O107+IF(R105>S105,R105,S105)-IF(S106<R106,R106,S106) -> 0 | U107: =R107+IF(U105>V105,U105,V105)-IF(V106<U106,U106,V106) -> 0 | X107: =U107+IF(X105>Y105,X105,Y105)-IF(Y106<X106,X106,Y106) -> 0 | AA107: =X107+IF(AA105>AB105,AA105,AB105)-IF(AB106<AA106,AA106,AB106) -> 0 | AD107: =AA107+IF(AD105>AE105,AD105,AE105)-IF(AE106<AD106,AD106,AE106) -> 0 | AG107: =AD107+IF(AG105>AH105,AG105,AH105)-IF(AH106<AG106,AG106,AH106) -> 0 | AJ107: =AG107+IF(AJ105>AK105,AJ105,AK105)-IF(AK106<AJ106,AJ106,AK106) -> 0 | AM107: =AJ107+IF(AM105>AN105,AM105,AN105)-IF(AN106<AM106,AM106,AN106) -> 0 | AP107: =AM107+IF(AP105>AQ105,AP105,AQ105)-IF(AQ106<AP106,AP106,AQ106) -> 0 | AT107: =AP107+BB105 -> 0 | AU107: =AP107+BB105*4 -> 0 | AY107: =IF(E107="","",E107) -> - compte d'épargne à saisir - | BB107: =AP107 -> 0
D108: =1+D105 -> 19 | E108: Indiquer le nom du projet à financer | AT108: =CONCATENATE("Moy. de ",INT(BB108/12)," €/mois") -> Moy. de 0 €/mois | AU108: =CONCATENATE("Moy. de ",INT(BB108/12)," €/mois") -> Moy. de 0 €/mois | AY108: =IF(E108="","",E108) -> Indiquer le nom du projet à financer | BB108: =SUM(MAX(I108,J108),MAX(L108,M108),MAX(O108,P108),MAX(R108,S108),MAX(U108,V108),MAX(X108,Y108),MAX(AA108,AB108),MAX(AD108,AE108),MAX(AG108,AH108),MAX(AJ108,AK108),MAX(AM108,AN108),MAX(AP108,AQ108)) -> 0 | BD108: =BB108/12 -> 0
D109: ExtraP Off | E109: =IF(BB108=0,"",INT(SUM(IF(K108="ok",J108,0),IF(N108="ok",M108,0),IF(Q108="ok",P108,0),IF(T108="ok",S108,0),IF(W108="ok",V108,0),IF(Z108="ok",Y108,0),IF(AC108="ok",AB108,0),IF(AF108="ok",AE108,0),IF(AI108="ok",AH108,0),IF(AL108="ok",AK108,0),IF(AO108="ok",AN108,0),IF(AR108="ok",AQ108,0))*100/BB108)/100) | F109: =IF(BB108=0,"",CONCATENATE("de l'objectif annuel atteint ","(",INT(SUM(IF(K108="ok",J108,0),IF(N108="ok",M108,0),IF(Q108="ok",P108,0),IF(T108="ok",S108,0),IF(W108="ok",V108,0),IF(Z108="ok",Y108,0),IF(AC108="ok",AB108,0),IF(AF108="ok",AE108,0),IF(AI108="ok",AH108,0),IF(AL108="ok",AK108,0),IF(AO108="ok",AN108,0),IF(AR108="ok",AQ108,0)))," € / ",BB108,")",IF(BB108=INT(SUM(IF(K108="ok",J108,0),IF(N108="ok",M108,0),IF(Q108="ok",P108,0),IF(T108="ok",S108,0),IF(W108="ok",V108,0),IF(Z108="ok",Y108,0),IF(AC108="ok",AB108,0),IF(AF108="ok",AE108,0),IF(AI108="ok",AH108,0),IF(AL108="ok",AK108,0),IF(AO108="ok",AN108,0),IF(AR108="ok",AQ108,0))),"",CONCATENATE(" : manque ",BB108-INT(SUM(IF(K108="ok",J108,0),IF(N108="ok",M108,0),IF(Q108="ok",P108,0),IF(T108="ok",S108,0),IF(W108="ok",V108,0),IF(Z108="ok",Y108,0),IF(AC108="ok",AB108,0),IF(AF108="ok",AE108,0),IF(AI108="ok",AH108,0),IF(AL108="ok",AK108,0),IF(AO108="ok",AN108,0),IF(AR108="ok",AQ108,0)))," €")))) | G109: Les retraits du mois -> | AY109: Somme totale des retraits -> | BB109: =SUM(MAX(I109,J109),MAX(L109,M109),MAX(O109,P109),MAX(R109,S109),MAX(U109,V109),MAX(X109,Y109),MAX(AA109,AB109),MAX(AD109,AE109),MAX(AG109,AH109),MAX(AJ109,AK109),MAX(AM109,AN109),MAX(AP109,AQ109)) -> 0 | BD109: épargnés/mois
E110: - compte d'épargne à saisir - | I110: =D110+IF(I108>J108,I108,J108)-IF(J109<I109,I109,J109) -> 0 | L110: =I110+IF(L108>M108,L108,M108)-IF(M109<L109,L109,M109) -> 0 | O110: =L110+IF(O108>P108,O108,P108)-IF(P109<O109,O109,P109) -> 0 | R110: =O110+IF(R108>S108,R108,S108)-IF(S109<R109,R109,S109) -> 0 | U110: =R110+IF(U108>V108,U108,V108)-IF(V109<U109,U109,V109) -> 0 | X110: =U110+IF(X108>Y108,X108,Y108)-IF(Y109<X109,X109,Y109) -> 0 | AA110: =X110+IF(AA108>AB108,AA108,AB108)-IF(AB109<AA109,AA109,AB109) -> 0 | AD110: =AA110+IF(AD108>AE108,AD108,AE108)-IF(AE109<AD109,AD109,AE109) -> 0 | AG110: =AD110+IF(AG108>AH108,AG108,AH108)-IF(AH109<AG109,AG109,AH109) -> 0 | AJ110: =AG110+IF(AJ108>AK108,AJ108,AK108)-IF(AK109<AJ109,AJ109,AK109) -> 0 | AM110: =AJ110+IF(AM108>AN108,AM108,AN108)-IF(AN109<AM109,AM109,AN109) -> 0 | AP110: =AM110+IF(AP108>AQ108,AP108,AQ108)-IF(AQ109<AP109,AP109,AQ109) -> 0 | AT110: =AP110+BB108 -> 0 | AU110: =AP110+BB108*4 -> 0 | AY110: =IF(E110="","",E110) -> - compte d'épargne à saisir - | BB110: =AP110 -> 0
D111: =1+D108 -> 20 | E111: Indiquer le nom du projet à financer | AT111: =CONCATENATE("Moy. de ",INT(BB111/12)," €/mois") -> Moy. de 0 €/mois | AU111: =CONCATENATE("Moy. de ",INT(BB111/12)," €/mois") -> Moy. de 0 €/mois | AY111: =IF(E111="","",E111) -> Indiquer le nom du projet à financer | BB111: =SUM(MAX(I111,J111),MAX(L111,M111),MAX(O111,P111),MAX(R111,S111),MAX(U111,V111),MAX(X111,Y111),MAX(AA111,AB111),MAX(AD111,AE111),MAX(AG111,AH111),MAX(AJ111,AK111),MAX(AM111,AN111),MAX(AP111,AQ111)) -> 0 | BD111: =BB111/12 -> 0
D112: ExtraP Off | E112: =IF(BB111=0,"",INT(SUM(IF(K111="ok",J111,0),IF(N111="ok",M111,0),IF(Q111="ok",P111,0),IF(T111="ok",S111,0),IF(W111="ok",V111,0),IF(Z111="ok",Y111,0),IF(AC111="ok",AB111,0),IF(AF111="ok",AE111,0),IF(AI111="ok",AH111,0),IF(AL111="ok",AK111,0),IF(AO111="ok",AN111,0),IF(AR111="ok",AQ111,0))*100/BB111)/100) | F112: =IF(BB111=0,"",CONCATENATE("de l'objectif annuel atteint ","(",INT(SUM(IF(K111="ok",J111,0),IF(N111="ok",M111,0),IF(Q111="ok",P111,0),IF(T111="ok",S111,0),IF(W111="ok",V111,0),IF(Z111="ok",Y111,0),IF(AC111="ok",AB111,0),IF(AF111="ok",AE111,0),IF(AI111="ok",AH111,0),IF(AL111="ok",AK111,0),IF(AO111="ok",AN111,0),IF(AR111="ok",AQ111,0)))," € / ",BB111,")",IF(BB111=INT(SUM(IF(K111="ok",J111,0),IF(N111="ok",M111,0),IF(Q111="ok",P111,0),IF(T111="ok",S111,0),IF(W111="ok",V111,0),IF(Z111="ok",Y111,0),IF(AC111="ok",AB111,0),IF(AF111="ok",AE111,0),IF(AI111="ok",AH111,0),IF(AL111="ok",AK111,0),IF(AO111="ok",AN111,0),IF(AR111="ok",AQ111,0))),"",CONCATENATE(" : manque ",BB111-INT(SUM(IF(K111="ok",J111,0),IF(N111="ok",M111,0),IF(Q111="ok",P111,0),IF(T111="ok",S111,0),IF(W111="ok",V111,0),IF(Z111="ok",Y111,0),IF(AC111="ok",AB111,0),IF(AF111="ok",AE111,0),IF(AI111="ok",AH111,0),IF(AL111="ok",AK111,0),IF(AO111="ok",AN111,0),IF(AR111="ok",AQ111,0)))," €")))) | G112: Les retraits du mois -> | AY112: Somme totale des retraits -> | BB112: =SUM(MAX(I112,J112),MAX(L112,M112),MAX(O112,P112),MAX(R112,S112),MAX(U112,V112),MAX(X112,Y112),MAX(AA112,AB112),MAX(AD112,AE112),MAX(AG112,AH112),MAX(AJ112,AK112),MAX(AM112,AN112),MAX(AP112,AQ112)) -> 0 | BD112: épargnés/mois
E113: - compte d'épargne à saisir - | I113: =D113+IF(I111>J111,I111,J111)-IF(J112<I112,I112,J112) -> 0 | L113: =I113+IF(L111>M111,L111,M111)-IF(M112<L112,L112,M112) -> 0 | O113: =L113+IF(O111>P111,O111,P111)-IF(P112<O112,O112,P112) -> 0 | R113: =O113+IF(R111>S111,R111,S111)-IF(S112<R112,R112,S112) -> 0 | U113: =R113+IF(U111>V111,U111,V111)-IF(V112<U112,U112,V112) -> 0 | X113: =U113+IF(X111>Y111,X111,Y111)-IF(Y112<X112,X112,Y112) -> 0 | AA113: =X113+IF(AA111>AB111,AA111,AB111)-IF(AB112<AA112,AA112,AB112) -> 0 | AD113: =AA113+IF(AD111>AE111,AD111,AE111)-IF(AE112<AD112,AD112,AE112) -> 0 | AG113: =AD113+IF(AG111>AH111,AG111,AH111)-IF(AH112<AG112,AG112,AH112) -> 0 | AJ113: =AG113+IF(AJ111>AK111,AJ111,AK111)-IF(AK112<AJ112,AJ112,AK112) -> 0 | AM113: =AJ113+IF(AM111>AN111,AM111,AN111)-IF(AN112<AM112,AM112,AN112) -> 0 | AP113: =AM113+IF(AP111>AQ111,AP111,AQ111)-IF(AQ112<AP112,AP112,AQ112) -> 0 | AT113: =AP113+BB111 -> 0 | AU113: =AP113+BB111*4 -> 0 | AY113: =IF(E113="","",E113) -> - compte d'épargne à saisir - | BB113: =AP113 -> 0
...

Sheet Synthèse
A2: Retour au Budget
K4: =Menu!I6 -> Version 2026 Révision VMAX EUR
C6: Synthèse des mouvements sur vos comptes d'épargne et de provisions
D10: ='Budget Gold'!I7 -> 46174 | H10: ='Budget Gold'!L7 -> 46206 | L10: ='Budget Gold'!O7 -> 46238
D14: ='Budget Gold'!R7 -> 46270 | H14: ='Budget Gold'!U7 -> 46302 | L14: ='Budget Gold'!X7 -> 46334
D18: ='Budget Gold'!AA7 -> 46366 | H18: ='Budget Gold'!AD7 -> 46398 | L18: ='Budget Gold'!AG7 -> 46430
D22: ='Budget Gold'!AJ7 -> 46462 | H22: ='Budget Gold'!AM7 -> 46494 | L22: ='Budget Gold'!AP7 -> 46526

Sheet Menu Mariage
A2: Retour au MENU
D4: < Mariage Gold > | E4: =Menu!I6 -> Version 2026 Révision VMAX EUR
D5: Pour gérer le budget de votre cérémonie de mariage
D8: Prénom de la fiancée
D10: Prénom du fiancé
D12: Mois de démarrage du budget | E12: 46023
D14: Date prévisionnelle du mariage
D16: Mois/année de la cérémonie | E16: =IF(OR(E14="",E14="jj/mm/aaaa"),"",DATE(YEAR(E14),MONTH(E14),1))
C20: Accéder à Mariage Gold

Sheet Mariage
C2: < Mariage Gold > | E2: Budget Total prévisionnel | X2: Retour | Y2: PLAN DE FINANCEMENT prévisionnel | AH2: Retour | AI2: PLAN DES DECAISSEMENTS
A3: Accès au MENU | C3: =CONCATENATE('Menu Mariage'!E8," & ",'Menu Mariage'!E10) -> & | E3: =AD5 -> 0 | T3: =SUM(IF(T9="",0,E9), IF(T10="",0,E10), IF(T11="",0,E11), IF(T12="",0,E12), IF(T13="",0,E13), IF(T14="",0,E14), IF(T15="",0,E15), IF(T16="",0,E16), IF(T17="",0,E17), IF(T18="",0,E18), IF(T20="",0,E20), IF(T21="",0,E21), IF(T22="",0,E22), IF(T23="",0,E23), IF(T24="",0,E24), IF(T25="",0,E25), IF(T26="",0,E26), IF(T30="",0,E30), IF(T31="",0,E31), IF(T32="",0,E32), IF(T33="",0,E33), IF(T34="",0,E34), IF(T35="",0,E35), IF(T36="",0,E36), IF(T37="",0,E37), IF(T38="",0,E38), IF(T39="",0,E39), IF(T40="",0,E40), IF(T44="",0,E44), IF(T45="",0,E45), IF(T46="",0,E46), IF(T47="",0,E47), IF(T48="",0,E48), IF(T49="",0,E49), IF(T50="",0,E50), IF(T51="",0,E51), IF(T52="",0,E52), IF(T53="",0,E53), IF(T54="",0,E54), IF(T58="",0,E58), IF(T59="",0,E59), IF(T60="",0,E60), IF(T61="",0,E61), IF(T62="",0,E62), IF(T63="",0,E63), IF(T64="",0,E64), IF(T68="",0,E68), IF(T69="",0,E69), IF(T70="",0,E70)) -> 0 | V3: <--- Budget à financer (avec les prix courants et les priorités) | AF3: Différence
A5: Accès au Budget | C5: =IF(OR('Menu Mariage'!E14="",'Menu Mariage'!E14="jj/mm/aaaa"),"",CONCATENATE("Le ",DAY('Menu Mariage'!E14),"/",MONTH('Menu Mariage'!E14),"/",YEAR('Menu Mariage'!E14))) | E5: =E27+E41+E55+E65+E71 -> 0 | G5: =G27+G41+G55+G65+G71 -> 0 | L5: =Menu!I6 -> Version 2026 Révision VMAX EUR | Q5: Priorités | T5: =SUM(IF(T9="",0,G9), IF(T10="",0,G10), IF(T11="",0,G11), IF(T12="",0,G12), IF(T13="",0,G13), IF(T14="",0,G14), IF(T15="",0,G15), IF(T16="",0,G16), IF(T17="",0,G17), IF(T18="",0,G18), IF(T20="",0,G20), IF(T21="",0,G21), IF(T22="",0,G22), IF(T23="",0,G23), IF(T24="",0,G24), IF(T25="",0,G25), IF(T26="",0,G26), IF(T30="",0,G30), IF(T31="",0,G31), IF(T32="",0,G32), IF(T33="",0,G33), IF(T34="",0,G34), IF(T35="",0,G35), IF(T36="",0,G36), IF(T37="",0,G37), IF(T38="",0,G38), IF(T39="",0,G39), IF(T40="",0,G40), IF(T44="",0,G44), IF(T45="",0,G45), IF(T46="",0,G46), IF(T47="",0,G47), IF(T48="",0,G48), IF(T49="",0,G49), IF(T50="",0,G50), IF(T51="",0,G51), IF(T52="",0,G52), IF(T53="",0,G53), IF(T54="",0,G54), IF(T58="",0,G58), IF(T59="",0,G59), IF(T60="",0,G60), IF(T61="",0,G61), IF(T62="",0,G62), IF(T63="",0,G63), IF(T64="",0,G64), IF(T68="",0,G68), IF(T69="",0,G69), IF(T70="",0,G70)) -> 0 | V5: <--- Budget Réel à financer (avec les devis retenus et les priorités) | Y5: Remplir les lignes les unes après les autres sans sauter de ligne | AD5: =MAX(AD8:AD157) -> 0 | AE5: =MAX(AE8:AE157) -> 0 | AF5: =AE5-AD5 -> 0 | AJ5: Total de tous les paiements prévisionnels | AL5: Budget restant à couvrir pour effectuer tous les paiements | AM5: Total des paiements déjà réalisés | AN5: Budget Réel disponible (à ce jour)
A6: Simulateur d'épargne | E6: Frais à financer (Prix courants) | G6: Frais Réels à financer (avec les devis retenus) | Q6: =CONCATENATE(COUNTIF(Q9:Q70,"1 (indispensable)")," prio1, ",COUNTIF(Q9:Q70,"2 (essentiel)")," prio2 et ",COUNTIF(Q9:Q70," 3 (souhaitable)")," prio3") -> 0 prio1, 0 prio2 et 0 prio3 | R6: =CONCATENATE(COUNTIF(R9:R70,"1 (indispensable)")," prio1, ",COUNTIF(R9:R70,"2 (essentiel)")," prio2 et ",COUNTIF(R9:R70," 3 (souhaitable)")," prio3") -> 0 prio1, 0 prio2 et 0 prio3 | T6: Priorités combinées | Y6: Date | Z6: Montant de l'apport | AA6: Etat | AB6: Provenance (Qui apporte ?) | AC6: Type | AD6: Budget Total (prévisionnelles) | AE6: Budget Total (réelles)
C7: Préparation des mariés | J7: Devis 1 | L7: Devis 2 | N7: Devis 3 | Q7: =IF('Menu Mariage'!E8="","Priorités de la fiancée",CONCATENATE("Priorités de ",'Menu Mariage'!E8)) -> Priorités de la fiancée | R7: =IF('Menu Mariage'!E10="","Priorités du fiancé",CONCATENATE("Priorités de ",'Menu Mariage'!E10)) -> Priorités du fiancé | V7: Remarques/commentaires | AJ7: =0-SUM(AJ11:AJ160) -> 0 | AL7: =IF((0-AJ7)-AE5<0,0,(0-AJ7)-AE5) -> 0 | AM7: =SUM(AN11:AN160) -> 0 | AN7: =AE5-AM7 -> 0
A8: Configurer Mariage Gold | C8: Préparation de la mariée | X8: 1 | Y8: jj-mm-aaaa | AA8: Non effectué | AD8: =IF(Z8="","",Z8) | AE8: =IF(AA8="Non effectué","",Z8)
C9: Robe de la mariée | G9: =IF(H9="",IF(E9="","",E9),IF(H9="Devis 1",J9,IF(H9="Devis 2",L9,N9))) | K9: Voir | M9: Voir | O9: Voir | T9: =IF(OR(Q9="1 (indispensable)",R9="1 (indispensable)"),"1 (indispensable)",IF(AND(Q9="2 (essentiel)",R9="2 (essentiel)"),"2 (essentiel)","")) | X9: =1+X8 -> 2 | Y9: jj-mm-aaaa | AA9: Non effectué | AD9: =IF(Z9="","",Z9+AD8) | AE9: =IF(Z9="","",IF(AA9="Non effectué",IF(AE8="","",AE8),IF(AE8="",Z9,Z9+AE8))) | AI9: Date | AJ9: Montant du paiement | AK9: Etat | AL9: Prestations | AM9: Prestataires | AN9: Paiements réalisés
C10: Coiffure | G10: =IF(H10="",IF(E10="","",E10),IF(H10="Devis 1",J10,IF(H10="Devis 2",L10,N10))) | K10: Voir | M10: Voir | O10: Voir | T10: =IF(OR(Q10="1 (indispensable)",R10="1 (indispensable)"),"1 (indispensable)",IF(AND(Q10="2 (essentiel)",R10="2 (essentiel)"),"2 (essentiel)","")) | X10: =1+X9 -> 3 | Y10: jj-mm-aaaa | AA10: Non effectué | AD10: =IF(Z10="","",Z10+AD9) | AE10: =IF(Z10="","",IF(AA10="Non effectué",IF(AE9="","",AE9),IF(AE9="",Z10,Z10+AE9)))
A11: Plan de financement | C11: Maquillage | G11: =IF(H11="",IF(E11="","",E11),IF(H11="Devis 1",J11,IF(H11="Devis 2",L11,N11))) | K11: Voir | M11: Voir | O11: Voir | T11: =IF(OR(Q11="1 (indispensable)",R11="1 (indispensable)"),"1 (indispensable)",IF(AND(Q11="2 (essentiel)",R11="2 (essentiel)"),"2 (essentiel)","")) | X11: =1+X10 -> 4 | Y11: jj-mm-aaaa | AA11: Non effectué | AD11: =IF(Z11="","",Z11+AD10) | AE11: =IF(Z11="","",IF(AA11="Non effectué",IF(AE10="","",AE10),IF(AE10="",Z11,Z11+AE10))) | AH11: 1 | AI11: jj-mm-aaaa | AK11: Non effectué | AL11: Ex: Acompte salle de réception | AM11: EVENT-LOCATION | AN11: =IF(AK11="Non effectué","",AJ11)
C12: Esthéticienne/Pédicure | G12: =IF(H12="",IF(E12="","",E12),IF(H12="Devis 1",J12,IF(H12="Devis 2",L12,N12))) | K12: Voir | M12: Voir | O12: Voir | T12: =IF(OR(Q12="1 (indispensable)",R12="1 (indispensable)"),"1 (indispensable)",IF(AND(Q12="2 (essentiel)",R12="2 (essentiel)"),"2 (essentiel)","")) | X12: =1+X11 -> 5 | Y12: jj-mm-aaaa | AA12: Non effectué | AD12: =IF(Z12="","",Z12+AD11) | AE12: =IF(Z12="","",IF(AA12="Non effectué",IF(AE11="","",AE11),IF(AE11="",Z12,Z12+AE11))) | AH12: =1+AH11 -> 2 | AI12: jj-mm-aaaa | AK12: Non effectué | AN12: =IF(AK12="Non effectué","",AJ12)
A13: Plan de décaissement | C13: Bouquet de la mariée | G13: =IF(H13="",IF(E13="","",E13),IF(H13="Devis 1",J13,IF(H13="Devis 2",L13,N13))) | K13: Voir | M13: Voir | O13: Voir | T13: =IF(OR(Q13="1 (indispensable)",R13="1 (indispensable)"),"1 (indispensable)",IF(AND(Q13="2 (essentiel)",R13="2 (essentiel)"),"2 (essentiel)","")) | X13: =1+X12 -> 6 | Y13: jj-mm-aaaa | AA13: Non effectué | AD13: =IF(Z13="","",Z13+AD12) | AE13: =IF(Z13="","",IF(AA13="Non effectué",IF(AE12="","",AE12),IF(AE12="",Z13,Z13+AE12))) | AH13: =1+AH12 -> 3 | AI13: jj-mm-aaaa | AK13: Non effectué | AN13: =IF(AK13="Non effectué","",AJ13)
C14: Accessoires de la mariée | G14: =IF(H14="",IF(E14="","",E14),IF(H14="Devis 1",J14,IF(H14="Devis 2",L14,N14))) | K14: Voir | M14: Voir | O14: Voir | T14: =IF(OR(Q14="1 (indispensable)",R14="1 (indispensable)"),"1 (indispensable)",IF(AND(Q14="2 (essentiel)",R14="2 (essentiel)"),"2 (essentiel)","")) | X14: =1+X13 -> 7 | Y14: jj-mm-aaaa | AA14: Non effectué | AD14: =IF(Z14="","",Z14+AD13) | AE14: =IF(Z14="","",IF(AA14="Non effectué",IF(AE13="","",AE13),IF(AE13="",Z14,Z14+AE13))) | AH14: =1+AH13 -> 4 | AI14: jj-mm-aaaa | AK14: Non effectué | AN14: =IF(AK14="Non effectué","",AJ14)
C15: Tenue de soirée | G15: =IF(H15="",IF(E15="","",E15),IF(H15="Devis 1",J15,IF(H15="Devis 2",L15,N15))) | K15: Voir | M15: Voir | O15: Voir | T15: =IF(OR(Q15="1 (indispensable)",R15="1 (indispensable)"),"1 (indispensable)",IF(AND(Q15="2 (essentiel)",R15="2 (essentiel)"),"2 (essentiel)","")) | X15: =1+X14 -> 8 | Y15: jj-mm-aaaa | AA15: Non effectué | AD15: =IF(Z15="","",Z15+AD14) | AE15: =IF(Z15="","",IF(AA15="Non effectué",IF(AE14="","",AE14),IF(AE14="",Z15,Z15+AE14))) | AH15: =1+AH14 -> 5 | AI15: jj-mm-aaaa | AK15: Non effectué | AN15: =IF(AK15="Non effectué","",AJ15)
C16: Autre (1) | G16: =IF(H16="",IF(E16="","",E16),IF(H16="Devis 1",J16,IF(H16="Devis 2",L16,N16))) | K16: Voir | M16: Voir | O16: Voir | T16: =IF(OR(Q16="1 (indispensable)",R16="1 (indispensable)"),"1 (indispensable)",IF(AND(Q16="2 (essentiel)",R16="2 (essentiel)"),"2 (essentiel)","")) | X16: =1+X15 -> 9 | Y16: jj-mm-aaaa | AA16: Non effectué | AD16: =IF(Z16="","",Z16+AD15) | AE16: =IF(Z16="","",IF(AA16="Non effectué",IF(AE15="","",AE15),IF(AE15="",Z16,Z16+AE15))) | AH16: =1+AH15 -> 6 | AI16: jj-mm-aaaa | AK16: Non effectué | AN16: =IF(AK16="Non effectué","",AJ16)
C17: Autre (2) | G17: =IF(H17="",IF(E17="","",E17),IF(H17="Devis 1",J17,IF(H17="Devis 2",L17,N17))) | K17: Voir | M17: Voir | O17: Voir | T17: =IF(OR(Q17="1 (indispensable)",R17="1 (indispensable)"),"1 (indispensable)",IF(AND(Q17="2 (essentiel)",R17="2 (essentiel)"),"2 (essentiel)","")) | X17: =1+X16 -> 10 | Y17: jj-mm-aaaa | AA17: Non effectué | AD17: =IF(Z17="","",Z17+AD16) | AE17: =IF(Z17="","",IF(AA17="Non effectué",IF(AE16="","",AE16),IF(AE16="",Z17,Z17+AE16))) | AH17: =1+AH16 -> 7 | AI17: jj-mm-aaaa | AK17: Non effectué | AN17: =IF(AK17="Non effectué","",AJ17)
C18: Autre (3) | G18: =IF(H18="",IF(E18="","",E18),IF(H18="Devis 1",J18,IF(H18="Devis 2",L18,N18))) | K18: Voir | M18: Voir | O18: Voir | T18: =IF(OR(Q18="1 (indispensable)",R18="1 (indispensable)"),"1 (indispensable)",IF(AND(Q18="2 (essentiel)",R18="2 (essentiel)"),"2 (essentiel)","")) | X18: =1+X17 -> 11 | Y18: jj-mm-aaaa | AA18: Non effectué | AD18: =IF(Z18="","",Z18+AD17) | AE18: =IF(Z18="","",IF(AA18="Non effectué",IF(AE17="","",AE17),IF(AE17="",Z18,Z18+AE17))) | AH18: =1+AH17 -> 8 | AI18: jj-mm-aaaa | AK18: Non effectué | AN18: =IF(AK18="Non effectué","",AJ18)
C19: Préparation du marié | X19: =1+X18 -> 12 | Y19: jj-mm-aaaa | AA19: Non effectué | AD19: =IF(Z19="","",Z19+AD18) | AE19: =IF(Z19="","",IF(AA19="Non effectué",IF(AE18="","",AE18),IF(AE18="",Z19,Z19+AE18))) | AH19: =1+AH18 -> 9 | AI19: jj-mm-aaaa | AK19: Non effectué | AN19: =IF(AK19="Non effectué","",AJ19)
C20: Tenue du marié | G20: =IF(H20="",IF(E20="","",E20),IF(H20="Devis 1",J20,IF(H20="Devis 2",L20,N20))) | K20: Voir | M20: Voir | O20: Voir | T20: =IF(OR(Q20="1 (indispensable)",R20="1 (indispensable)"),"1 (indispensable)",IF(AND(Q20="2 (essentiel)",R20="2 (essentiel)"),"2 (essentiel)","")) | X20: =1+X19 -> 13 | Y20: jj-mm-aaaa | AA20: Non effectué | AD20: =IF(Z20="","",Z20+AD19) | AE20: =IF(Z20="","",IF(AA20="Non effectué",IF(AE19="","",AE19),IF(AE19="",Z20,Z20+AE19))) | AH20: =1+AH19 -> 10 | AI20: jj-mm-aaaa | AK20: Non effectué | AN20: =IF(AK20="Non effectué","",AJ20)
C21: Accessoires du marié | G21: =IF(H21="",IF(E21="","",E21),IF(H21="Devis 1",J21,IF(H21="Devis 2",L21,N21))) | K21: Voir | M21: Voir | O21: Voir | T21: =IF(OR(Q21="1 (indispensable)",R21="1 (indispensable)"),"1 (indispensable)",IF(AND(Q21="2 (essentiel)",R21="2 (essentiel)"),"2 (essentiel)","")) | X21: =1+X20 -> 14 | Y21: jj-mm-aaaa | AA21: Non effectué | AD21: =IF(Z21="","",Z21+AD20) | AE21: =IF(Z21="","",IF(AA21="Non effectué",IF(AE20="","",AE20),IF(AE20="",Z21,Z21+AE20))) | AH21: =1+AH20 -> 11 | AI21: jj-mm-aaaa | AK21: Non effectué | AN21: =IF(AK21="Non effectué","",AJ21)
C22: Coiffure | G22: =IF(H22="",IF(E22="","",E22),IF(H22="Devis 1",J22,IF(H22="Devis 2",L22,N22))) | K22: Voir | M22: Voir | O22: Voir | T22: =IF(OR(Q22="1 (indispensable)",R22="1 (indispensable)"),"1 (indispensable)",IF(AND(Q22="2 (essentiel)",R22="2 (essentiel)"),"2 (essentiel)","")) | X22: =1+X21 -> 15 | Y22: jj-mm-aaaa | AA22: Non effectué | AD22: =IF(Z22="","",Z22+AD21) | AE22: =IF(Z22="","",IF(AA22="Non effectué",IF(AE21="","",AE21),IF(AE21="",Z22,Z22+AE21))) | AH22: =1+AH21 -> 12 | AI22: jj-mm-aaaa | AK22: Non effectué | AN22: =IF(AK22="Non effectué","",AJ22)
C23: Tenue de soirée | G23: =IF(H23="",IF(E23="","",E23),IF(H23="Devis 1",J23,IF(H23="Devis 2",L23,N23))) | K23: Voir | M23: Voir | O23: Voir | T23: =IF(OR(Q23="1 (indispensable)",R23="1 (indispensable)"),"1 (indispensable)",IF(AND(Q23="2 (essentiel)",R23="2 (essentiel)"),"2 (essentiel)","")) | X23: =1+X22 -> 16 | Y23: jj-mm-aaaa | AA23: Non effectué | AD23: =IF(Z23="","",Z23+AD22) | AE23: =IF(Z23="","",IF(AA23="Non effectué",IF(AE22="","",AE22),IF(AE22="",Z23,Z23+AE22))) | AH23: =1+AH22 -> 13 | AI23: jj-mm-aaaa | AK23: Non effectué | AN23: =IF(AK23="Non effectué","",AJ23)
C24: Autre (1) | G24: =IF(H24="",IF(E24="","",E24),IF(H24="Devis 1",J24,IF(H24="Devis 2",L24,N24))) | K24: Voir | M24: Voir | O24: Voir | T24: =IF(OR(Q24="1 (indispensable)",R24="1 (indispensable)"),"1 (indispensable)",IF(AND(Q24="2 (essentiel)",R24="2 (essentiel)"),"2 (essentiel)","")) | X24: =1+X23 -> 17 | Y24: jj-mm-aaaa | AA24: Non effectué | AD24: =IF(Z24="","",Z24+AD23) | AE24: =IF(Z24="","",IF(AA24="Non effectué",IF(AE23="","",AE23),IF(AE23="",Z24,Z24+AE23))) | AH24: =1+AH23 -> 14 | AI24: jj-mm-aaaa | AK24: Non effectué | AN24: =IF(AK24="Non effectué","",AJ24)
C25: Autre (2) | G25: =IF(H25="",IF(E25="","",E25),IF(H25="Devis 1",J25,IF(H25="Devis 2",L25,N25))) | K25: Voir | M25: Voir | O25: Voir | T25: =IF(OR(Q25="1 (indispensable)",R25="1 (indispensable)"),"1 (indispensable)",IF(AND(Q25="2 (essentiel)",R25="2 (essentiel)"),"2 (essentiel)","")) | X25: =1+X24 -> 18 | Y25: jj-mm-aaaa | AA25: Non effectué | AD25: =IF(Z25="","",Z25+AD24) | AE25: =IF(Z25="","",IF(AA25="Non effectué",IF(AE24="","",AE24),IF(AE24="",Z25,Z25+AE24))) | AH25: =1+AH24 -> 15 | AI25: jj-mm-aaaa | AK25: Non effectué | AN25: =IF(AK25="Non effectué","",AJ25)
C26: Autre (3) | G26: =IF(H26="",IF(E26="","",E26),IF(H26="Devis 1",J26,IF(H26="Devis 2",L26,N26))) | K26: Voir | M26: Voir | O26: Voir | T26: =IF(OR(Q26="1 (indispensable)",R26="1 (indispensable)"),"1 (indispensable)",IF(AND(Q26="2 (essentiel)",R26="2 (essentiel)"),"2 (essentiel)","")) | X26: =1+X25 -> 19 | Y26: jj-mm-aaaa | AA26: Non effectué | AD26: =IF(Z26="","",Z26+AD25) | AE26: =IF(Z26="","",IF(AA26="Non effectué",IF(AE25="","",AE25),IF(AE25="",Z26,Z26+AE25))) | AH26: =1+AH25 -> 16 | AI26: jj-mm-aaaa | AK26: Non effectué | AN26: =IF(AK26="Non effectué","",AJ26)
C27: sous-total = | E27: =SUM(E9:E26) -> 0 | G27: =SUM(G9:G26) -> 0 | J27: =SUM(J9:J26) -> 0 | L27: =SUM(L9:L26) -> 0 | N27: =SUM(N9:N26) -> 0 | X27: =1+X26 -> 20 | Y27: jj-mm-aaaa | AA27: Non effectué | AD27: =IF(Z27="","",Z27+AD26) | AE27: =IF(Z27="","",IF(AA27="Non effectué",IF(AE26="","",AE26),IF(AE26="",Z27,Z27+AE26))) | AH27: =1+AH26 -> 17 | AI27: jj-mm-aaaa | AK27: Non effectué | AN27: =IF(AK27="Non effectué","",AJ27)
X28: =1+X27 -> 21 | Y28: jj-mm-aaaa | AA28: Non effectué | AD28: =IF(Z28="","",Z28+AD27) | AE28: =IF(Z28="","",IF(AA28="Non effectué",IF(AE27="","",AE27),IF(AE27="",Z28,Z28+AE27))) | AH28: =1+AH27 -> 18 | AI28: jj-mm-aaaa | AK28: Non effectué | AN28: =IF(AK28="Non effectué","",AJ28)
C29: Cérémonies | E29: Frais à financer | G29: Frais réels à financer | J29: Devis 1 | L29: Devis 2 | N29: Devis 3 | Q29: =Q7 -> Priorités de la fiancée | R29: =R7 -> Priorités du fiancé | T29: Priorités combinées | V29: Remarques/commentaires | X29: =1+X28 -> 22 | Y29: jj-mm-aaaa | AA29: Non effectué | AD29: =IF(Z29="","",Z29+AD28) | AE29: =IF(Z29="","",IF(AA29="Non effectué",IF(AE28="","",AE28),IF(AE28="",Z29,Z29+AE28))) | AH29: =1+AH28 -> 19 | AI29: jj-mm-aaaa | AK29: Non effectué | AN29: =IF(AK29="Non effectué","",AJ29)
C30: Alliances | G30: =IF(H30="",IF(E30="","",E30),IF(H30="Devis 1",J30,IF(H30="Devis 2",L30,N30))) | K30: Voir | M30: Voir | O30: Voir | T30: =IF(OR(Q30="1 (indispensable)",R30="1 (indispensable)"),"1 (indispensable)",IF(AND(Q30="2 (essentiel)",R30="2 (essentiel)"),"2 (essentiel)","")) | X30: =1+X29 -> 23 | Y30: jj-mm-aaaa | AA30: Non effectué | AD30: =IF(Z30="","",Z30+AD29) | AE30: =IF(Z30="","",IF(AA30="Non effectué",IF(AE29="","",AE29),IF(AE29="",Z30,Z30+AE29))) | AH30: =1+AH29 -> 20 | AI30: jj-mm-aaaa | AK30: Non effectué | AN30: =IF(AK30="Non effectué","",AJ30)
C31: Décoration Eglise | G31: =IF(H31="",IF(E31="","",E31),IF(H31="Devis 1",J31,IF(H31="Devis 2",L31,N31))) | K31: Voir | M31: Voir | O31: Voir | T31: =IF(OR(Q31="1 (indispensable)",R31="1 (indispensable)"),"1 (indispensable)",IF(AND(Q31="2 (essentiel)",R31="2 (essentiel)"),"2 (essentiel)","")) | X31: =1+X30 -> 24 | Y31: jj-mm-aaaa | AA31: Non effectué | AD31: =IF(Z31="","",Z31+AD30) | AE31: =IF(Z31="","",IF(AA31="Non effectué",IF(AE30="","",AE30),IF(AE30="",Z31,Z31+AE30))) | AH31: =1+AH30 -> 21 | AI31: jj-mm-aaaa | AK31: Non effectué | AN31: =IF(AK31="Non effectué","",AJ31)
C32: Animation de la sortie (riz, pétales, confettis..) | G32: =IF(H32="",IF(E32="","",E32),IF(H32="Devis 1",J32,IF(H32="Devis 2",L32,N32))) | K32: Voir | M32: Voir | O32: Voir | T32: =IF(OR(Q32="1 (indispensable)",R32="1 (indispensable)"),"1 (indispensable)",IF(AND(Q32="2 (essentiel)",R32="2 (essentiel)"),"2 (essentiel)","")) | X32: =1+X31 -> 25 | Y32: jj-mm-aaaa | AA32: Non effectué | AD32: =IF(Z32="","",Z32+AD31) | AE32: =IF(Z32="","",IF(AA32="Non effectué",IF(AE31="","",AE31),IF(AE31="",Z32,Z32+AE31))) | AH32: =1+AH31 -> 22 | AI32: jj-mm-aaaa | AK32: Non effectué | AN32: =IF(AK32="Non effectué","",AJ32)
C33: Offrande (église) | G33: =IF(H33="",IF(E33="","",E33),IF(H33="Devis 1",J33,IF(H33="Devis 2",L33,N33))) | K33: Voir | M33: Voir | O33: Voir | T33: =IF(OR(Q33="1 (indispensable)",R33="1 (indispensable)"),"1 (indispensable)",IF(AND(Q33="2 (essentiel)",R33="2 (essentiel)"),"2 (essentiel)","")) | X33: =1+X32 -> 26 | Y33: jj-mm-aaaa | AA33: Non effectué | AD33: =IF(Z33="","",Z33+AD32) | AE33: =IF(Z33="","",IF(AA33="Non effectué",IF(AE32="","",AE32),IF(AE32="",Z33,Z33+AE32))) | AH33: =1+AH32 -> 23 | AI33: jj-mm-aaaa | AK33: Non effectué | AN33: =IF(AK33="Non effectué","",AJ33)
C34: Location de la voiture des mariés | G34: =IF(H34="",IF(E34="","",E34),IF(H34="Devis 1",J34,IF(H34="Devis 2",L34,N34))) | K34: Voir | M34: Voir | O34: Voir | T34: =IF(OR(Q34="1 (indispensable)",R34="1 (indispensable)"),"1 (indispensable)",IF(AND(Q34="2 (essentiel)",R34="2 (essentiel)"),"2 (essentiel)","")) | X34: =1+X33 -> 27 | Y34: jj-mm-aaaa | AA34: Non effectué | AD34: =IF(Z34="","",Z34+AD33) | AE34: =IF(Z34="","",IF(AA34="Non effectué",IF(AE33="","",AE33),IF(AE33="",Z34,Z34+AE33))) | AH34: =1+AH33 -> 24 | AI34: jj-mm-aaaa | AK34: Non effectué | AN34: =IF(AK34="Non effectué","",AJ34)
C35: Location autres véhicules | G35: =IF(H35="",IF(E35="","",E35),IF(H35="Devis 1",J35,IF(H35="Devis 2",L35,N35))) | K35: Voir | M35: Voir | O35: Voir | T35: =IF(OR(Q35="1 (indispensable)",R35="1 (indispensable)"),"1 (indispensable)",IF(AND(Q35="2 (essentiel)",R35="2 (essentiel)"),"2 (essentiel)","")) | X35: =1+X34 -> 28 | Y35: jj-mm-aaaa | AA35: Non effectué | AD35: =IF(Z35="","",Z35+AD34) | AE35: =IF(Z35="","",IF(AA35="Non effectué",IF(AE34="","",AE34),IF(AE34="",Z35,Z35+AE34))) | AH35: =1+AH34 -> 25 | AI35: jj-mm-aaaa | AK35: Non effectué | AN35: =IF(AK35="Non effectué","",AJ35)
C36: Photographe | G36: =IF(H36="",IF(E36="","",E36),IF(H36="Devis 1",J36,IF(H36="Devis 2",L36,N36))) | K36: Voir | M36: Voir | O36: Voir | T36: =IF(OR(Q36="1 (indispensable)",R36="1 (indispensable)"),"1 (indispensable)",IF(AND(Q36="2 (essentiel)",R36="2 (essentiel)"),"2 (essentiel)","")) | X36: =1+X35 -> 29 | Y36: jj-mm-aaaa | AA36: Non effectué | AD36: =IF(Z36="","",Z36+AD35) | AE36: =IF(Z36="","",IF(AA36="Non effectué",IF(AE35="","",AE35),IF(AE35="",Z36,Z36+AE35))) | AH36: =1+AH35 -> 26 | AI36: jj-mm-aaaa | AK36: Non effectué | AN36: =IF(AK36="Non effectué","",AJ36)
C37: Caméraman | G37: =IF(H37="",IF(E37="","",E37),IF(H37="Devis 1",J37,IF(H37="Devis 2",L37,N37))) | K37: Voir | M37: Voir | O37: Voir | T37: =IF(OR(Q37="1 (indispensable)",R37="1 (indispensable)"),"1 (indispensable)",IF(AND(Q37="2 (essentiel)",R37="2 (essentiel)"),"2 (essentiel)","")) | X37: =1+X36 -> 30 | Y37: jj-mm-aaaa | AA37: Non effectué | AD37: =IF(Z37="","",Z37+AD36) | AE37: =IF(Z37="","",IF(AA37="Non effectué",IF(AE36="","",AE36),IF(AE36="",Z37,Z37+AE36))) | AH37: =1+AH36 -> 27 | AI37: jj-mm-aaaa | AK37: Non effectué | AN37: =IF(AK37="Non effectué","",AJ37)
C38: Autre (1) | G38: =IF(H38="",IF(E38="","",E38),IF(H38="Devis 1",J38,IF(H38="Devis 2",L38,N38))) | K38: Voir | M38: Voir | O38: Voir | T38: =IF(OR(Q38="1 (indispensable)",R38="1 (indispensable)"),"1 (indispensable)",IF(AND(Q38="2 (essentiel)",R38="2 (essentiel)"),"2 (essentiel)","")) | X38: =1+X37 -> 31 | Y38: jj-mm-aaaa | AA38: Non effectué | AD38: =IF(Z38="","",Z38+AD37) | AE38: =IF(Z38="","",IF(AA38="Non effectué",IF(AE37="","",AE37),IF(AE37="",Z38,Z38+AE37))) | AH38: =1+AH37 -> 28 | AI38: jj-mm-aaaa | AK38: Non effectué | AN38: =IF(AK38="Non effectué","",AJ38)
C39: Autre (2) | G39: =IF(H39="",IF(E39="","",E39),IF(H39="Devis 1",J39,IF(H39="Devis 2",L39,N39))) | K39: Voir | M39: Voir | O39: Voir | T39: =IF(OR(Q39="1 (indispensable)",R39="1 (indispensable)"),"1 (indispensable)",IF(AND(Q39="2 (essentiel)",R39="2 (essentiel)"),"2 (essentiel)","")) | X39: =1+X38 -> 32 | Y39: jj-mm-aaaa | AA39: Non effectué | AD39: =IF(Z39="","",Z39+AD38) | AE39: =IF(Z39="","",IF(AA39="Non effectué",IF(AE38="","",AE38),IF(AE38="",Z39,Z39+AE38))) | AH39: =1+AH38 -> 29 | AI39: jj-mm-aaaa | AK39: Non effectué | AN39: =IF(AK39="Non effectué","",AJ39)
C40: Autre (3) | G40: =IF(H40="",IF(E40="","",E40),IF(H40="Devis 1",J40,IF(H40="Devis 2",L40,N40))) | K40: Voir | M40: Voir | O40: Voir | T40: =IF(OR(Q40="1 (indispensable)",R40="1 (indispensable)"),"1 (indispensable)",IF(AND(Q40="2 (essentiel)",R40="2 (essentiel)"),"2 (essentiel)","")) | X40: =1+X39 -> 33 | Y40: jj-mm-aaaa | AA40: Non effectué | AD40: =IF(Z40="","",Z40+AD39) | AE40: =IF(Z40="","",IF(AA40="Non effectué",IF(AE39="","",AE39),IF(AE39="",Z40,Z40+AE39))) | AH40: =1+AH39 -> 30 | AI40: jj-mm-aaaa | AK40: Non effectué | AN40: =IF(AK40="Non effectué","",AJ40)
C41: sous-total = | E41: =SUM(E30:E40) -> 0 | G41: =SUM(G30:G40) -> 0 | J41: =SUM(J30:J40) -> 0 | L41: =SUM(L30:L40) -> 0 | N41: =SUM(N30:N40) -> 0 | X41: =1+X40 -> 34 | Y41: jj-mm-aaaa | AA41: Non effectué | AD41: =IF(Z41="","",Z41+AD40) | AE41: =IF(Z41="","",IF(AA41="Non effectué",IF(AE40="","",AE40),IF(AE40="",Z41,Z41+AE40))) | AH41: =1+AH40 -> 31 | AI41: jj-mm-aaaa | AK41: Non effectué | AN41: =IF(AK41="Non effectué","",AJ41)
X42: =1+X41 -> 35 | Y42: jj-mm-aaaa | AA42: Non effectué | AD42: =IF(Z42="","",Z42+AD41) | AE42: =IF(Z42="","",IF(AA42="Non effectué",IF(AE41="","",AE41),IF(AE41="",Z42,Z42+AE41))) | AH42: =1+AH41 -> 32 | AI42: jj-mm-aaaa | AK42: Non effectué | AN42: =IF(AK42="Non effectué","",AJ42)
C43: Réceptions | E43: Frais à financer | G43: Frais réels à financer | J43: Devis 1 | L43: Devis 2 | N43: Devis 3 | Q43: =Q29 -> Priorités de la fiancée | R43: =R29 -> Priorités du fiancé | T43: =T29 -> Priorités combinées | V43: Remarques/commentaires | X43: =1+X42 -> 36 | Y43: jj-mm-aaaa | AA43: Non effectué | AD43: =IF(Z43="","",Z43+AD42) | AE43: =IF(Z43="","",IF(AA43="Non effectué",IF(AE42="","",AE42),IF(AE42="",Z43,Z43+AE42))) | AH43: =1+AH42 -> 33 | AI43: jj-mm-aaaa | AK43: Non effectué | AN43: =IF(AK43="Non effectué","",AJ43)
C44: Frais de papeterie (faire-parts, etc…) | G44: =IF(H44="",IF(E44="","",E44),IF(H44="Devis 1",J44,IF(H44="Devis 2",L44,N44))) | K44: Voir | M44: Voir | O44: Voir | T44: =IF(OR(Q44="1 (indispensable)",R44="1 (indispensable)"),"1 (indispensable)",IF(AND(Q44="2 (essentiel)",R44="2 (essentiel)"),"2 (essentiel)","")) | X44: =1+X43 -> 37 | Y44: jj-mm-aaaa | AA44: Non effectué | AD44: =IF(Z44="","",Z44+AD43) | AE44: =IF(Z44="","",IF(AA44="Non effectué",IF(AE43="","",AE43),IF(AE43="",Z44,Z44+AE43))) | AH44: =1+AH43 -> 34 | AI44: jj-mm-aaaa | AK44: Non effectué | AN44: =IF(AK44="Non effectué","",AJ44)
C45: Location de la salle et du matériel | G45: =IF(H45="",IF(E45="","",E45),IF(H45="Devis 1",J45,IF(H45="Devis 2",L45,N45))) | K45: Voir | M45: Voir | O45: Voir | T45: =IF(OR(Q45="1 (indispensable)",R45="1 (indispensable)"),"1 (indispensable)",IF(AND(Q45="2 (essentiel)",R45="2 (essentiel)"),"2 (essentiel)","")) | X45: =1+X44 -> 38 | Y45: jj-mm-aaaa | AA45: Non effectué | AD45: =IF(Z45="","",Z45+AD44) | AE45: =IF(Z45="","",IF(AA45="Non effectué",IF(AE44="","",AE44),IF(AE44="",Z45,Z45+AE44))) | AH45: =1+AH44 -> 35 | AI45: jj-mm-aaaa | AK45: Non effectué | AN45: =IF(AK45="Non effectué","",AJ45)
C46: Repas, Vin d'honneur | G46: =IF(H46="",IF(E46="","",E46),IF(H46="Devis 1",J46,IF(H46="Devis 2",L46,N46))) | K46: Voir | M46: Voir | O46: Voir | T46: =IF(OR(Q46="1 (indispensable)",R46="1 (indispensable)"),"1 (indispensable)",IF(AND(Q46="2 (essentiel)",R46="2 (essentiel)"),"2 (essentiel)","")) | X46: =1+X45 -> 39 | Y46: jj-mm-aaaa | AA46: Non effectué | AD46: =IF(Z46="","",Z46+AD45) | AE46: =IF(Z46="","",IF(AA46="Non effectué",IF(AE45="","",AE45),IF(AE45="",Z46,Z46+AE45))) | AH46: =1+AH45 -> 36 | AI46: jj-mm-aaaa | AK46: Non effectué | AN46: =IF(AK46="Non effectué","",AJ46)
C47: Gâteau / pièce montée | G47: =IF(H47="",IF(E47="","",E47),IF(H47="Devis 1",J47,IF(H47="Devis 2",L47,N47))) | K47: Voir | M47: Voir | O47: Voir | T47: =IF(OR(Q47="1 (indispensable)",R47="1 (indispensable)"),"1 (indispensable)",IF(AND(Q47="2 (essentiel)",R47="2 (essentiel)"),"2 (essentiel)","")) | X47: =1+X46 -> 40 | Y47: jj-mm-aaaa | AA47: Non effectué | AD47: =IF(Z47="","",Z47+AD46) | AE47: =IF(Z47="","",IF(AA47="Non effectué",IF(AE46="","",AE46),IF(AE46="",Z47,Z47+AE46))) | AH47: =1+AH46 -> 37 | AI47: jj-mm-aaaa | AK47: Non effectué | AN47: =IF(AK47="Non effectué","",AJ47)
C48: Décoration - Salle de réception | G48: =IF(H48="",IF(E48="","",E48),IF(H48="Devis 1",J48,IF(H48="Devis 2",L48,N48))) | K48: Voir | M48: Voir | O48: Voir | T48: =IF(OR(Q48="1 (indispensable)",R48="1 (indispensable)"),"1 (indispensable)",IF(AND(Q48="2 (essentiel)",R48="2 (essentiel)"),"2 (essentiel)","")) | X48: =1+X47 -> 41 | Y48: jj-mm-aaaa | AA48: Non effectué | AD48: =IF(Z48="","",Z48+AD47) | AE48: =IF(Z48="","",IF(AA48="Non effectué",IF(AE47="","",AE47),IF(AE47="",Z48,Z48+AE47))) | AH48: =1+AH47 -> 38 | AI48: jj-mm-aaaa | AK48: Non effectué | AN48: =IF(AK48="Non effectué","",AJ48)
C49: Cadeaux symboliques pour les parents | G49: =IF(H49="",IF(E49="","",E49),IF(H49="Devis 1",J49,IF(H49="Devis 2",L49,N49))) | K49: Voir | M49: Voir | O49: Voir | T49: =IF(OR(Q49="1 (indispensable)",R49="1 (indispensable)"),"1 (indispensable)",IF(AND(Q49="2 (essentiel)",R49="2 (essentiel)"),"2 (essentiel)","")) | X49: =1+X48 -> 42 | Y49: jj-mm-aaaa | AA49: Non effectué | AD49: =IF(Z49="","",Z49+AD48) | AE49: =IF(Z49="","",IF(AA49="Non effectué",IF(AE48="","",AE48),IF(AE48="",Z49,Z49+AE48))) | AH49: =1+AH48 -> 39 | AI49: jj-mm-aaaa | AK49: Non effectué | AN49: =IF(AK49="Non effectué","",AJ49)
C50: Dragées | G50: =IF(H50="",IF(E50="","",E50),IF(H50="Devis 1",J50,IF(H50="Devis 2",L50,N50))) | K50: Voir | M50: Voir | O50: Voir | T50: =IF(OR(Q50="1 (indispensable)",R50="1 (indispensable)"),"1 (indispensable)",IF(AND(Q50="2 (essentiel)",R50="2 (essentiel)"),"2 (essentiel)","")) | X50: =1+X49 -> 43 | Y50: jj-mm-aaaa | AA50: Non effectué | AD50: =IF(Z50="","",Z50+AD49) | AE50: =IF(Z50="","",IF(AA50="Non effectué",IF(AE49="","",AE49),IF(AE49="",Z50,Z50+AE49))) | AH50: =1+AH49 -> 40 | AI50: jj-mm-aaaa | AK50: Non effectué | AN50: =IF(AK50="Non effectué","",AJ50)
C51: Disk-jokey (DJ) Animation musicale | G51: =IF(H51="",IF(E51="","",E51),IF(H51="Devis 1",J51,IF(H51="Devis 2",L51,N51))) | K51: Voir | M51: Voir | O51: Voir | T51: =IF(OR(Q51="1 (indispensable)",R51="1 (indispensable)"),"1 (indispensable)",IF(AND(Q51="2 (essentiel)",R51="2 (essentiel)"),"2 (essentiel)","")) | X51: =1+X50 -> 44 | Y51: jj-mm-aaaa | AA51: Non effectué | AD51: =IF(Z51="","",Z51+AD50) | AE51: =IF(Z51="","",IF(AA51="Non effectué",IF(AE50="","",AE50),IF(AE50="",Z51,Z51+AE50))) | AH51: =1+AH50 -> 41 | AI51: jj-mm-aaaa | AK51: Non effectué | AN51: =IF(AK51="Non effectué","",AJ51)
C52: Autre (1) | G52: =IF(H52="",IF(E52="","",E52),IF(H52="Devis 1",J52,IF(H52="Devis 2",L52,N52))) | K52: Voir | M52: Voir | O52: Voir | T52: =IF(OR(Q52="1 (indispensable)",R52="1 (indispensable)"),"1 (indispensable)",IF(AND(Q52="2 (essentiel)",R52="2 (essentiel)"),"2 (essentiel)","")) | X52: =1+X51 -> 45 | Y52: jj-mm-aaaa | AA52: Non effectué | AD52: =IF(Z52="","",Z52+AD51) | AE52: =IF(Z52="","",IF(AA52="Non effectué",IF(AE51="","",AE51),IF(AE51="",Z52,Z52+AE51))) | AH52: =1+AH51 -> 42 | AI52: jj-mm-aaaa | AK52: Non effectué | AN52: =IF(AK52="Non effectué","",AJ52)
C53: Autre (2) | G53: =IF(H53="",IF(E53="","",E53),IF(H53="Devis 1",J53,IF(H53="Devis 2",L53,N53))) | K53: Voir | M53: Voir | O53: Voir | T53: =IF(OR(Q53="1 (indispensable)",R53="1 (indispensable)"),"1 (indispensable)",IF(AND(Q53="2 (essentiel)",R53="2 (essentiel)"),"2 (essentiel)","")) | X53: =1+X52 -> 46 | Y53: jj-mm-aaaa | AA53: Non effectué | AD53: =IF(Z53="","",Z53+AD52) | AE53: =IF(Z53="","",IF(AA53="Non effectué",IF(AE52="","",AE52),IF(AE52="",Z53,Z53+AE52))) | AH53: =1+AH52 -> 43 | AI53: jj-mm-aaaa | AK53: Non effectué | AN53: =IF(AK53="Non effectué","",AJ53)
C54: Autre (3) | G54: =IF(H54="",IF(E54="","",E54),IF(H54="Devis 1",J54,IF(H54="Devis 2",L54,N54))) | K54: Voir | M54: Voir | O54: Voir | T54: =IF(OR(Q54="1 (indispensable)",R54="1 (indispensable)"),"1 (indispensable)",IF(AND(Q54="2 (essentiel)",R54="2 (essentiel)"),"2 (essentiel)","")) | X54: =1+X53 -> 47 | Y54: jj-mm-aaaa | AA54: Non effectué | AD54: =IF(Z54="","",Z54+AD53) | AE54: =IF(Z54="","",IF(AA54="Non effectué",IF(AE53="","",AE53),IF(AE53="",Z54,Z54+AE53))) | AH54: =1+AH53 -> 44 | AI54: jj-mm-aaaa | AK54: Non effectué | AN54: =IF(AK54="Non effectué","",AJ54)
C55: sous-total = | E55: =SUM(E44:E54) -> 0 | G55: =SUM(G44:G54) -> 0 | J55: =SUM(J44:J54) -> 0 | L55: =SUM(L44:L54) -> 0 | N55: =SUM(N44:N54) -> 0 | X55: =1+X54 -> 48 | Y55: jj-mm-aaaa | AA55: Non effectué | AD55: =IF(Z55="","",Z55+AD54) | AE55: =IF(Z55="","",IF(AA55="Non effectué",IF(AE54="","",AE54),IF(AE54="",Z55,Z55+AE54))) | AH55: =1+AH54 -> 45 | AI55: jj-mm-aaaa | AK55: Non effectué | AN55: =IF(AK55="Non effectué","",AJ55)
X56: =1+X55 -> 49 | Y56: jj-mm-aaaa | AA56: Non effectué | AD56: =IF(Z56="","",Z56+AD55) | AE56: =IF(Z56="","",IF(AA56="Non effectué",IF(AE55="","",AE55),IF(AE55="",Z56,Z56+AE55))) | AH56: =1+AH55 -> 46 | AI56: jj-mm-aaaa | AK56: Non effectué | AN56: =IF(AK56="Non effectué","",AJ56)
C57: Noces - Lune de miel | E57: Frais à financer | G57: Frais réels à financer | J57: Devis 1 | L57: Devis 2 | N57: Devis 3 | Q57: =Q43 -> Priorités de la fiancée | R57: =R43 -> Priorités du fiancé | T57: =T43 -> Priorités combinées | V57: Remarques/commentaires | X57: =1+X56 -> 50 | Y57: jj-mm-aaaa | AA57: Non effectué | AD57: =IF(Z57="","",Z57+AD56) | AE57: =IF(Z57="","",IF(AA57="Non effectué",IF(AE56="","",AE56),IF(AE56="",Z57,Z57+AE56))) | AH57: =1+AH56 -> 47 | AI57: jj-mm-aaaa | AK57: Non effectué | AN57: =IF(AK57="Non effectué","",AJ57)
C58: Hôtel | G58: =IF(H58="",IF(E58="","",E58),IF(H58="Devis 1",J58,IF(H58="Devis 2",L58,N58))) | K58: Voir | M58: Voir | O58: Voir | T58: =IF(OR(Q58="1 (indispensable)",R58="1 (indispensable)"),"1 (indispensable)",IF(AND(Q58="2 (essentiel)",R58="2 (essentiel)"),"2 (essentiel)","")) | X58: =1+X57 -> 51 | Y58: jj-mm-aaaa | AA58: Non effectué | AD58: =IF(Z58="","",Z58+AD57) | AE58: =IF(Z58="","",IF(AA58="Non effectué",IF(AE57="","",AE57),IF(AE57="",Z58,Z58+AE57))) | AH58: =1+AH57 -> 48 | AI58: jj-mm-aaaa | AK58: Non effectué | AN58: =IF(AK58="Non effectué","",AJ58)
C59: Voyage de noces | G59: =IF(H59="",IF(E59="","",E59),IF(H59="Devis 1",J59,IF(H59="Devis 2",L59,N59))) | K59: Voir | M59: Voir | O59: Voir | T59: =IF(OR(Q59="1 (indispensable)",R59="1 (indispensable)"),"1 (indispensable)",IF(AND(Q59="2 (essentiel)",R59="2 (essentiel)"),"2 (essentiel)","")) | X59: =1+X58 -> 52 | Y59: jj-mm-aaaa | AA59: Non effectué | AD59: =IF(Z59="","",Z59+AD58) | AE59: =IF(Z59="","",IF(AA59="Non effectué",IF(AE58="","",AE58),IF(AE58="",Z59,Z59+AE58))) | AH59: =1+AH58 -> 49 | AI59: jj-mm-aaaa | AK59: Non effectué | AN59: =IF(AK59="Non effectué","",AJ59)
C60: Frais de visa | G60: =IF(H60="",IF(E60="","",E60),IF(H60="Devis 1",J60,IF(H60="Devis 2",L60,N60))) | K60: Voir | M60: Voir | O60: Voir | T60: =IF(OR(Q60="1 (indispensable)",R60="1 (indispensable)"),"1 (indispensable)",IF(AND(Q60="2 (essentiel)",R60="2 (essentiel)"),"2 (essentiel)","")) | X60: =1+X59 -> 53 | Y60: jj-mm-aaaa | AA60: Non effectué | AD60: =IF(Z60="","",Z60+AD59) | AE60: =IF(Z60="","",IF(AA60="Non effectué",IF(AE59="","",AE59),IF(AE59="",Z60,Z60+AE59))) | AH60: =1+AH59 -> 50 | AI60: jj-mm-aaaa | AK60: Non effectué | AN60: =IF(AK60="Non effectué","",AJ60)
C61: Argent de poche - voyage | G61: =IF(H61="",IF(E61="","",E61),IF(H61="Devis 1",J61,IF(H61="Devis 2",L61,N61))) | K61: Voir | M61: Voir | O61: Voir | T61: =IF(OR(Q61="1 (indispensable)",R61="1 (indispensable)"),"1 (indispensable)",IF(AND(Q61="2 (essentiel)",R61="2 (essentiel)"),"2 (essentiel)","")) | X61: =1+X60 -> 54 | Y61: jj-mm-aaaa | AA61: Non effectué | AD61: =IF(Z61="","",Z61+AD60) | AE61: =IF(Z61="","",IF(AA61="Non effectué",IF(AE60="","",AE60),IF(AE60="",Z61,Z61+AE60))) | AH61: =1+AH60 -> 51 | AI61: jj-mm-aaaa | AK61: Non effectué | AN61: =IF(AK61="Non effectué","",AJ61)
C62: Autre (1) | G62: =IF(H62="",IF(E62="","",E62),IF(H62="Devis 1",J62,IF(H62="Devis 2",L62,N62))) | K62: Voir | M62: Voir | O62: Voir | T62: =IF(OR(Q62="1 (indispensable)",R62="1 (indispensable)"),"1 (indispensable)",IF(AND(Q62="2 (essentiel)",R62="2 (essentiel)"),"2 (essentiel)","")) | X62: =1+X61 -> 55 | Y62: jj-mm-aaaa | AA62: Non effectué | AD62: =IF(Z62="","",Z62+AD61) | AE62: =IF(Z62="","",IF(AA62="Non effectué",IF(AE61="","",AE61),IF(AE61="",Z62,Z62+AE61))) | AH62: =1+AH61 -> 52 | AI62: jj-mm-aaaa | AK62: Non effectué | AN62: =IF(AK62="Non effectué","",AJ62)
C63: Autre (2) | G63: =IF(H63="",IF(E63="","",E63),IF(H63="Devis 1",J63,IF(H63="Devis 2",L63,N63))) | K63: Voir | M63: Voir | O63: Voir | T63: =IF(OR(Q63="1 (indispensable)",R63="1 (indispensable)"),"1 (indispensable)",IF(AND(Q63="2 (essentiel)",R63="2 (essentiel)"),"2 (essentiel)","")) | X63: =1+X62 -> 56 | Y63: jj-mm-aaaa | AA63: Non effectué | AD63: =IF(Z63="","",Z63+AD62) | AE63: =IF(Z63="","",IF(AA63="Non effectué",IF(AE62="","",AE62),IF(AE62="",Z63,Z63+AE62))) | AH63: =1+AH62 -> 53 | AI63: jj-mm-aaaa | AK63: Non effectué | AN63: =IF(AK63="Non effectué","",AJ63)
C64: Autre (3) | G64: =IF(H64="",IF(E64="","",E64),IF(H64="Devis 1",J64,IF(H64="Devis 2",L64,N64))) | K64: Voir | M64: Voir | O64: Voir | T64: =IF(OR(Q64="1 (indispensable)",R64="1 (indispensable)"),"1 (indispensable)",IF(AND(Q64="2 (essentiel)",R64="2 (essentiel)"),"2 (essentiel)","")) | X64: =1+X63 -> 57 | Y64: jj-mm-aaaa | AA64: Non effectué | AD64: =IF(Z64="","",Z64+AD63) | AE64: =IF(Z64="","",IF(AA64="Non effectué",IF(AE63="","",AE63),IF(AE63="",Z64,Z64+AE63))) | AH64: =1+AH63 -> 54 | AI64: jj-mm-aaaa | AK64: Non effectué | AN64: =IF(AK64="Non effectué","",AJ64)
C65: sous-total = | E65: =SUM(E58:E64) -> 0 | G65: =SUM(G58:G64) -> 0 | J65: =SUM(J58:J64) -> 0 | L65: =SUM(L58:L64) -> 0 | N65: =SUM(N58:N64) -> 0 | X65: =1+X64 -> 58 | Y65: jj-mm-aaaa | AA65: Non effectué | AD65: =IF(Z65="","",Z65+AD64) | AE65: =IF(Z65="","",IF(AA65="Non effectué",IF(AE64="","",AE64),IF(AE64="",Z65,Z65+AE64))) | AH65: =1+AH64 -> 55 | AI65: jj-mm-aaaa | AK65: Non effectué | AN65: =IF(AK65="Non effectué","",AJ65)
X66: =1+X65 -> 59 | Y66: jj-mm-aaaa | AA66: Non effectué | AD66: =IF(Z66="","",Z66+AD65) | AE66: =IF(Z66="","",IF(AA66="Non effectué",IF(AE65="","",AE65),IF(AE65="",Z66,Z66+AE65))) | AH66: =1+AH65 -> 56 | AI66: jj-mm-aaaa | AK66: Non effectué | AN66: =IF(AK66="Non effectué","",AJ66)
C67: Divers | E67: Frais à financer | G67: Frais réels à financer | J67: Devis 1 | L67: Devis 2 | N67: Devis 3 | Q67: =Q57 -> Priorités de la fiancée | R67: =R57 -> Priorités du fiancé | T67: =T57 -> Priorités combinées | V67: Remarques/commentaires | X67: =1+X66 -> 60 | Y67: jj-mm-aaaa | AA67: Non effectué | AD67: =IF(Z67="","",Z67+AD66) | AE67: =IF(Z67="","",IF(AA67="Non effectué",IF(AE66="","",AE66),IF(AE66="",Z67,Z67+AE66))) | AH67: =1+AH66 -> 57 | AI67: jj-mm-aaaa | AK67: Non effectué | AN67: =IF(AK67="Non effectué","",AJ67)
C68: Divers (1) | G68: =IF(H68="",IF(E68="","",E68),IF(H68="Devis 1",J68,IF(H68="Devis 2",L68,N68))) | K68: Voir | M68: Voir | O68: Voir | T68: =IF(OR(Q68="1 (indispensable)",R68="1 (indispensable)"),"1 (indispensable)",IF(AND(Q68="2 (essentiel)",R68="2 (essentiel)"),"2 (essentiel)","")) | X68: =1+X67 -> 61 | Y68: jj-mm-aaaa | AA68: Non effectué | AD68: =IF(Z68="","",Z68+AD67) | AE68: =IF(Z68="","",IF(AA68="Non effectué",IF(AE67="","",AE67),IF(AE67="",Z68,Z68+AE67))) | AH68: =1+AH67 -> 58 | AI68: jj-mm-aaaa | AK68: Non effectué | AN68: =IF(AK68="Non effectué","",AJ68)
C69: Divers (2) | G69: =IF(H69="",IF(E69="","",E69),IF(H69="Devis 1",J69,IF(H69="Devis 2",L69,N69))) | K69: Voir | M69: Voir | O69: Voir | T69: =IF(OR(Q69="1 (indispensable)",R69="1 (indispensable)"),"1 (indispensable)",IF(AND(Q69="2 (essentiel)",R69="2 (essentiel)"),"2 (essentiel)","")) | X69: =1+X68 -> 62 | Y69: jj-mm-aaaa | AA69: Non effectué | AD69: =IF(Z69="","",Z69+AD68) | AE69: =IF(Z69="","",IF(AA69="Non effectué",IF(AE68="","",AE68),IF(AE68="",Z69,Z69+AE68))) | AH69: =1+AH68 -> 59 | AI69: jj-mm-aaaa | AK69: Non effectué | AN69: =IF(AK69="Non effectué","",AJ69)
C70: Divers (3) | G70: =IF(H70="",IF(E70="","",E70),IF(H70="Devis 1",J70,IF(H70="Devis 2",L70,N70))) | K70: Voir | M70: Voir | O70: Voir | T70: =IF(OR(Q70="1 (indispensable)",R70="1 (indispensable)"),"1 (indispensable)",IF(AND(Q70="2 (essentiel)",R70="2 (essentiel)"),"2 (essentiel)","")) | X70: =1+X69 -> 63 | Y70: jj-mm-aaaa | AA70: Non effectué | AD70: =IF(Z70="","",Z70+AD69) | AE70: =IF(Z70="","",IF(AA70="Non effectué",IF(AE69="","",AE69),IF(AE69="",Z70,Z70+AE69))) | AH70: =1+AH69 -> 60 | AI70: jj-mm-aaaa | AK70: Non effectué | AN70: =IF(AK70="Non effectué","",AJ70)
C71: sous-total = | E71: =SUM(E68:E70) -> 0 | G71: =SUM(G68:G70) -> 0 | J71: =SUM(J68:J70) -> 0 | L71: =SUM(L68:L70) -> 0 | N71: =SUM(N68:N70) -> 0 | X71: =1+X70 -> 64 | Y71: jj-mm-aaaa | AA71: Non effectué | AD71: =IF(Z71="","",Z71+AD70) | AE71: =IF(Z71="","",IF(AA71="Non effectué",IF(AE70="","",AE70),IF(AE70="",Z71,Z71+AE70))) | AH71: =1+AH70 -> 61 | AI71: jj-mm-aaaa | AK71: Non effectué | AN71: =IF(AK71="Non effectué","",AJ71)
X72: =1+X71 -> 65 | Y72: jj-mm-aaaa | AA72: Non effectué | AD72: =IF(Z72="","",Z72+AD71) | AE72: =IF(Z72="","",IF(AA72="Non effectué",IF(AE71="","",AE71),IF(AE71="",Z72,Z72+AE71))) | AH72: =1+AH71 -> 62 | AI72: jj-mm-aaaa | AK72: Non effectué | AN72: =IF(AK72="Non effectué","",AJ72)
C73: TOTAL = | E73: =E5 -> 0 | G73: =G5 -> 0 | X73: =1+X72 -> 66 | Y73: jj-mm-aaaa | AA73: Non effectué | AD73: =IF(Z73="","",Z73+AD72) | AE73: =IF(Z73="","",IF(AA73="Non effectué",IF(AE72="","",AE72),IF(AE72="",Z73,Z73+AE72))) | AH73: =1+AH72 -> 63 | AI73: jj-mm-aaaa | AK73: Non effectué | AN73: =IF(AK73="Non effectué","",AJ73)
E74: Frais à financer (Prix courants) | G74: Frais Réels à financer (avec les devis retenus) | X74: =1+X73 -> 67 | Y74: jj-mm-aaaa | AA74: Non effectué | AD74: =IF(Z74="","",Z74+AD73) | AE74: =IF(Z74="","",IF(AA74="Non effectué",IF(AE73="","",AE73),IF(AE73="",Z74,Z74+AE73))) | AH74: =1+AH73 -> 64 | AI74: jj-mm-aaaa | AK74: Non effectué | AN74: =IF(AK74="Non effectué","",AJ74)
X75: =1+X74 -> 68 | Y75: jj-mm-aaaa | AA75: Non effectué | AD75: =IF(Z75="","",Z75+AD74) | AE75: =IF(Z75="","",IF(AA75="Non effectué",IF(AE74="","",AE74),IF(AE74="",Z75,Z75+AE74))) | AH75: =1+AH74 -> 65 | AI75: jj-mm-aaaa | AK75: Non effectué | AN75: =IF(AK75="Non effectué","",AJ75)
X76: =1+X75 -> 69 | Y76: jj-mm-aaaa | AA76: Non effectué | AD76: =IF(Z76="","",Z76+AD75) | AE76: =IF(Z76="","",IF(AA76="Non effectué",IF(AE75="","",AE75),IF(AE75="",Z76,Z76+AE75))) | AH76: =1+AH75 -> 66 | AI76: jj-mm-aaaa | AK76: Non effectué | AN76: =IF(AK76="Non effectué","",AJ76)
X77: =1+X76 -> 70 | Y77: jj-mm-aaaa | AA77: Non effectué | AD77: =IF(Z77="","",Z77+AD76) | AE77: =IF(Z77="","",IF(AA77="Non effectué",IF(AE76="","",AE76),IF(AE76="",Z77,Z77+AE76))) | AH77: =1+AH76 -> 67 | AI77: jj-mm-aaaa | AK77: Non effectué | AN77: =IF(AK77="Non effectué","",AJ77)
X78: =1+X77 -> 71 | Y78: jj-mm-aaaa | AA78: Non effectué | AD78: =IF(Z78="","",Z78+AD77) | AE78: =IF(Z78="","",IF(AA78="Non effectué",IF(AE77="","",AE77),IF(AE77="",Z78,Z78+AE77))) | AH78: =1+AH77 -> 68 | AI78: jj-mm-aaaa | AK78: Non effectué | AN78: =IF(AK78="Non effectué","",AJ78)
X79: =1+X78 -> 72 | Y79: jj-mm-aaaa | AA79: Non effectué | AD79: =IF(Z79="","",Z79+AD78) | AE79: =IF(Z79="","",IF(AA79="Non effectué",IF(AE78="","",AE78),IF(AE78="",Z79,Z79+AE78))) | AH79: =1+AH78 -> 69 | AI79: jj-mm-aaaa | AK79: Non effectué | AN79: =IF(AK79="Non effectué","",AJ79)
X80: =1+X79 -> 73 | Y80: jj-mm-aaaa | AA80: Non effectué | AD80: =IF(Z80="","",Z80+AD79) | AE80: =IF(Z80="","",IF(AA80="Non effectué",IF(AE79="","",AE79),IF(AE79="",Z80,Z80+AE79))) | AH80: =1+AH79 -> 70 | AI80: jj-mm-aaaa | AK80: Non effectué | AN80: =IF(AK80="Non effectué","",AJ80)
X81: =1+X80 -> 74 | Y81: jj-mm-aaaa | AA81: Non effectué | AD81: =IF(Z81="","",Z81+AD80) | AE81: =IF(Z81="","",IF(AA81="Non effectué",IF(AE80="","",AE80),IF(AE80="",Z81,Z81+AE80))) | AH81: =1+AH80 -> 71 | AI81: jj-mm-aaaa | AK81: Non effectué | AN81: =IF(AK81="Non effectué","",AJ81)
X82: =1+X81 -> 75 | Y82: jj-mm-aaaa | AA82: Non effectué | AD82: =IF(Z82="","",Z82+AD81) | AE82: =IF(Z82="","",IF(AA82="Non effectué",IF(AE81="","",AE81),IF(AE81="",Z82,Z82+AE81))) | AH82: =1+AH81 -> 72 | AI82: jj-mm-aaaa | AK82: Non effectué | AN82: =IF(AK82="Non effectué","",AJ82)
X83: =1+X82 -> 76 | Y83: jj-mm-aaaa | AA83: Non effectué | AD83: =IF(Z83="","",Z83+AD82) | AE83: =IF(Z83="","",IF(AA83="Non effectué",IF(AE82="","",AE82),IF(AE82="",Z83,Z83+AE82))) | AH83: =1+AH82 -> 73 | AI83: jj-mm-aaaa | AK83: Non effectué | AN83: =IF(AK83="Non effectué","",AJ83)
X84: =1+X83 -> 77 | Y84: jj-mm-aaaa | AA84: Non effectué | AD84: =IF(Z84="","",Z84+AD83) | AE84: =IF(Z84="","",IF(AA84="Non effectué",IF(AE83="","",AE83),IF(AE83="",Z84,Z84+AE83))) | AH84: =1+AH83 -> 74 | AI84: jj-mm-aaaa | AK84: Non effectué | AN84: =IF(AK84="Non effectué","",AJ84)
X85: =1+X84 -> 78 | Y85: jj-mm-aaaa | AA85: Non effectué | AD85: =IF(Z85="","",Z85+AD84) | AE85: =IF(Z85="","",IF(AA85="Non effectué",IF(AE84="","",AE84),IF(AE84="",Z85,Z85+AE84))) | AH85: =1+AH84 -> 75 | AI85: jj-mm-aaaa | AK85: Non effectué | AN85: =IF(AK85="Non effectué","",AJ85)
X86: =1+X85 -> 79 | Y86: jj-mm-aaaa | AA86: Non effectué | AD86: =IF(Z86="","",Z86+AD85) | AE86: =IF(Z86="","",IF(AA86="Non effectué",IF(AE85="","",AE85),IF(AE85="",Z86,Z86+AE85))) | AH86: =1+AH85 -> 76 | AI86: jj-mm-aaaa | AK86: Non effectué | AN86: =IF(AK86="Non effectué","",AJ86)
... X157: =1+X156 -> 150 | Y157: jj-mm-aaaa | AA157: Non effectué | AD157: =IF(Z157="","",Z157+AD156) | AE157: =IF(Z157="","",IF(AA157="Non effectué",IF(AE156="","",AE156),IF(AE156="",Z157,Z157+AE156))) | AH157: =1+AH156 -> 147 | AI157: jj-mm-aaaa | AK157: Non effectué | AN157: =IF(AK157="Non effectué","",AJ157)
AH158: =1+AH157 -> 148 | AI158: jj-mm-aaaa | AK158: Non effectué | AN158: =IF(AK158="Non effectué","",AJ158)
AH159: =1+AH158 -> 149 | AI159: jj-mm-aaaa | AK159: Non effectué | AN159: =IF(AK159="Non effectué","",AJ159)
AH160: =1+AH159 -> 150 | AI160: jj-mm-aaaa | AK160: Non effectué | AN160: =IF(AK160="Non effectué","",AJ160)

Sheet Simulateur
A2: Retour au Budget | C2: Simulateur d'épargne
G5: =Menu!I6 -> Version 2026 Révision VMAX EUR
B6: Epargne mensuelle | D6: Rentabilité brute moyenne (%) | E6: Apport initial
B7: 100 | D7: 3 | E7: 0 | F7: <- Les champs modifiables sont en JAUNE
D9: En Euros (€)
C10: Années | D10: Valeur acquise | E10: Epargne cumulée | F10: Gain brut
C11: 1 | D11: =(12*$B$7+E7)*(1+$D$7/100) -> 1236 | E11: =12*$B$7+E7 -> 1200 | F11: =D11-E11 -> 36
C12: 2 | D12: =(((12*$B$7)+D11)*(1+$D$7/100)) -> 2509.08 | E12: =E11+(12*$B$7) -> 2400 | F12: =D12-E12 -> 109.08
C13: 3 | D13: =(((12*$B$7)+D12)*(1+$D$7/100)) -> 3820.3524 | E13: =E12+(12*$B$7) -> 3600 | F13: =D13-E13 -> 220.3524
C14: 4 | D14: =(((12*$B$7)+D13)*(1+$D$7/100)) -> 5170.963 | E14: =E13+(12*$B$7) -> 4800 | F14: =D14-E14 -> 370.96297
C15: 5 | D15: =(((12*$B$7)+D14)*(1+$D$7/100)) -> 6562.0919 | E15: =E14+(12*$B$7) -> 6000 | F15: =D15-E15 -> 562.09186
C16: 6 | D16: =(((12*$B$7)+D15)*(1+$D$7/100)) -> 7994.9546 | E16: =E15+(12*$B$7) -> 7200 | F16: =D16-E16 -> 794.95462
C17: 7 | D17: =(((12*$B$7)+D16)*(1+$D$7/100)) -> 9470.8033 | E17: =E16+(12*$B$7) -> 8400 | F17: =D17-E17 -> 1070.8033
C18: 8 | D18: =(((12*$B$7)+D17)*(1+$D$7/100)) -> 10990.927 | E18: =E17+(12*$B$7) -> 9600 | F18: =D18-E18 -> 1390.9274
C19: 9 | D19: =(((12*$B$7)+D18)*(1+$D$7/100)) -> 12556.655 | E19: =E18+(12*$B$7) -> 10800 | F19: =D19-E19 -> 1756.6552
C20: 10 | D20: =(((12*$B$7)+D19)*(1+$D$7/100)) -> 14169.355 | E20: =E19+(12*$B$7) -> 12000 | F20: =D20-E20 -> 2169.3548
C21: 11 | D21: =(((12*$B$7)+D20)*(1+$D$7/100)) -> 15830.435 | E21: =E20+(12*$B$7) -> 13200 | F21: =D21-E21 -> 2630.4355
C22: 12 | D22: =(((12*$B$7)+D21)*(1+$D$7/100)) -> 17541.349 | E22: =E21+(12*$B$7) -> 14400 | F22: =D22-E22 -> 3141.3485
C23: 13 | D23: =(((12*$B$7)+D22)*(1+$D$7/100)) -> 19303.589 | E23: =E22+(12*$B$7) -> 15600 | F23: =D23-E23 -> 3703.589
... C30: 20 | D30: =(((12*$B$7)+D29)*(1+$D$7/100)) -> 33211.783 | E30: =E29+(12*$B$7) -> 24000 | F30: =D30-E30 -> 9211.7829
C31: =1+C30 -> 21 | D31: =(((12*$B$7)+D30)*(1+$D$7/100)) -> 35444.136 | E31: =E30+(12*$B$7) -> 25200 | F31: =D31-E31 -> 10244.136
C32: =1+C31 -> 22 | D32: =(((12*$B$7)+D31)*(1+$D$7/100)) -> 37743.46 | E32: =E31+(12*$B$7) -> 26400 | F32: =D32-E32 -> 11343.46
C33: =1+C32 -> 23 | D33: =(((12*$B$7)+D32)*(1+$D$7/100)) -> 40111.764 | E33: =E32+(12*$B$7) -> 27600 | F33: =D33-E33 -> 12511.764
C34: =1+C33 -> 24 | D34: =(((12*$B$7)+D33)*(1+$D$7/100)) -> 42551.117 | E34: =E33+(12*$B$7) -> 28800 | F34: =D34-E34 -> 13751.117
C35: =1+C34 -> 25 | D35: =(((12*$B$7)+D34)*(1+$D$7/100)) -> 45063.651 | E35: =E34+(12*$B$7) -> 30000 | F35: =D35-E35 -> 15063.651
C36: =1+C35 -> 26 | D36: =(((12*$B$7)+D35)*(1+$D$7/100)) -> 47651.56 | E36: =E35+(12*$B$7) -> 31200 | F36: =D36-E36 -> 16451.56
C37: =1+C36 -> 27 | D37: =(((12*$B$7)+D36)*(1+$D$7/100)) -> 50317.107 | E37: =E36+(12*$B$7) -> 32400 | F37: =D37-E37 -> 17917.107
C38: =1+C37 -> 28 | D38: =(((12*$B$7)+D37)*(1+$D$7/100)) -> 53062.62 | E38: =E37+(12*$B$7) -> 33600 | F38: =D38-E38 -> 19462.62
C39: =1+C38 -> 29 | D39: =(((12*$B$7)+D38)*(1+$D$7/100)) -> 55890.499 | E39: =E38+(12*$B$7) -> 34800 | F39: =D39-E39 -> 21090.499
C40: =1+C39 -> 30 | D40: =(((12*$B$7)+D39)*(1+$D$7/100)) -> 58803.214 | E40: =E39+(12*$B$7) -> 36000 | F40: =D40-E40 -> 22803.214
C41: Années | D41: Valeur acquise | E41: Epargne cumulée | F41: Gain brut
D42: En Euros (€)

Sheet ImmoView 1
A2: Accès au MENU | C2: < ImmoView > | D2: Bien n° 1 | AP2: < ImmoView >
A3: Accès au Budget
A4: Simulateur d'épargne | C4: Désignation du bien | J4: =Menu!I6 -> Version 2026 Révision VMAX EUR
C5: Adresse
C6: Code postal - VILLE
C8: ENTREES | D8: =Menu!F22 -> 46174 | G8: =D8+32 -> 46206 | J8: =G8+32 -> 46238 | M8: =J8+32 -> 46270 | P8: =M8+32 -> 46302 | S8: =P8+32 -> 46334 | V8: =S8+32 -> 46366 | Y8: =V8+32 -> 46398 | AB8: =Y8+32 -> 46430 | AE8: =AB8+32 -> 46462 | AH8: =AE8+32 -> 46494 | AK8: =AH8+32 -> 46526 | AP8: ENTREES | AQ8: BILAN ANNUEL
D9: Suivi | E9: Budget | G9: Suivi | H9: Budget | J9: Suivi | K9: Budget | M9: Suivi | N9: Budget | P9: Suivi | Q9: Budget | S9: Suivi | T9: Budget | V9: Suivi | W9: Budget | Y9: Suivi | Z9: Budget | AB9: Suivi | AC9: Budget | AE9: Suivi | AF9: Budget | AH9: Suivi | AI9: Budget | AK9: Suivi | AL9: Budget
C10: Loyers | AP10: =C10 -> Loyers | AQ10: =SUM(MAX(D10:E10),MAX(G10:H10),MAX(J10:K10),MAX(M10,N10),MAX(P10:Q10),MAX(S10:T10),MAX(V10:W10),MAX(Y10:Z10),MAX(AB10:AC10),MAX(AE10,AF10),MAX(AH10:AI10),MAX(AK10:AL10)) -> 0
C11: Provisions pour charges | AP11: =C11 -> Provisions pour charges | AQ11: =SUM(MAX(D11:E11),MAX(G11:H11),MAX(J11:K11),MAX(M11,N11),MAX(P11:Q11),MAX(S11:T11),MAX(V11:W11),MAX(Y11:Z11),MAX(AB11:AC11),MAX(AE11,AF11),MAX(AH11:AI11),MAX(AK11:AL11)) -> 0
C12: Dépots de garantie | AP12: =C12 -> Dépots de garantie | AQ12: =SUM(MAX(D12:E12),MAX(G12:H12),MAX(J12:K12),MAX(M12,N12),MAX(P12:Q12),MAX(S12:T12),MAX(V12:W12),MAX(Y12:Z12),MAX(AB12:AC12),MAX(AE12,AF12),MAX(AH12:AI12),MAX(AK12:AL12)) -> 0
C13: Apports personnels | AP13: =C13 -> Apports personnels | AQ13: =SUM(MAX(D13:E13),MAX(G13:H13),MAX(J13:K13),MAX(M13,N13),MAX(P13:Q13),MAX(S13:T13),MAX(V13:W13),MAX(Y13:Z13),MAX(AB13:AC13),MAX(AE13,AF13),MAX(AH13:AI13),MAX(AK13:AL13)) -> 0
C14: Financement | AP14: =C14 -> Financement | AQ14: =SUM(MAX(D14:E14),MAX(G14:H14),MAX(J14:K14),MAX(M14,N14),MAX(P14:Q14),MAX(S14:T14),MAX(V14:W14),MAX(Y14:Z14),MAX(AB14:AC14),MAX(AE14,AF14),MAX(AH14:AI14),MAX(AK14:AL14)) -> 0
C15: Subventions | AP15: =C15 -> Subventions | AQ15: =SUM(MAX(D15:E15),MAX(G15:H15),MAX(J15:K15),MAX(M15,N15),MAX(P15:Q15),MAX(S15:T15),MAX(V15:W15),MAX(Y15:Z15),MAX(AB15:AC15),MAX(AE15,AF15),MAX(AH15:AI15),MAX(AK15:AL15)) -> 0
C16: Autres | AP16: =C16 -> Autres | AQ16: =SUM(MAX(D16:E16),MAX(G16:H16),MAX(J16:K16),MAX(M16,N16),MAX(P16:Q16),MAX(S16:T16),MAX(V16:W16),MAX(Y16:Z16),MAX(AB16:AC16),MAX(AE16,AF16),MAX(AH16:AI16),MAX(AK16:AL16)) -> 0
C17: Total des Entrées | D17: =IF(SUM(D10:D16)=0,"",SUM(D10:D16)) | E17: =SUM(E10:E16) -> 0 | G17: =IF(SUM(G10:G16)=0,"",SUM(G10:G16)) | H17: =SUM(H10:H16) -> 0 | J17: =IF(SUM(J10:J16)=0,"",SUM(J10:J16)) | K17: =SUM(K10:K16) -> 0 | M17: =IF(SUM(M10:M16)=0,"",SUM(M10:M16)) | N17: =SUM(N10:N16) -> 0 | P17: =IF(SUM(P10:P16)=0,"",SUM(P10:P16)) | Q17: =SUM(Q10:Q16) -> 0 | S17: =IF(SUM(S10:S16)=0,"",SUM(S10:S16)) | T17: =SUM(T10:T16) -> 0 | V17: =IF(SUM(V10:V16)=0,"",SUM(V10:V16)) | W17: =SUM(W10:W16) -> 0 | Y17: =IF(SUM(Y10:Y16)=0,"",SUM(Y10:Y16)) | Z17: =SUM(Z10:Z16) -> 0 | AB17: =IF(SUM(AB10:AB16)=0,"",SUM(AB10:AB16)) | AC17: =SUM(AC10:AC16) -> 0 | AE17: =IF(SUM(AE10:AE16)=0,"",SUM(AE10:AE16)) | AF17: =SUM(AF10:AF16) -> 0 | AH17: =IF(SUM(AH10:AH16)=0,"",SUM(AH10:AH16)) | AI17: =SUM(AI10:AI16) -> 0 | AK17: =IF(SUM(AK10:AK16)=0,"",SUM(AK10:AK16)) | AL17: =SUM(AL10:AL16) -> 0 | AP17: Total des Entrées annuelles | AQ17: =SUM(AQ10:AS16) -> 0
C18: Différence | D18: =IF(D17="","",D17-E17) | G18: =IF(G17="","",G17-H17) | J18: =IF(J17="","",J17-K17) | M18: =IF(M17="","",M17-N17) | P18: =IF(P17="","",P17-Q17) | S18: =IF(S17="","",S17-T17) | V18: =IF(V17="","",V17-W17) | Y18: =IF(Y17="","",Y17-Z17) | AB18: =IF(AB17="","",AB17-AC17) | AE18: =IF(AE17="","",AE17-AF17) | AH18: =IF(AH17="","",AH17-AI17) | AK18: =IF(AK17="","",AK17-AL17)
C20: SORTIES | D20: =Menu!F22 -> 46174 | G20: =32+D20 -> 46206 | J20: =32+G20 -> 46238 | M20: =32+J20 -> 46270 | P20: =32+M20 -> 46302 | S20: =32+P20 -> 46334 | V20: =32+S20 -> 46366 | Y20: =32+V20 -> 46398 | AB20: =32+Y20 -> 46430 | AE20: =32+AB20 -> 46462 | AH20: =32+AE20 -> 46494 | AK20: =32+AH20 -> 46526 | AP20: SORTIES
D21: Suivi | E21: Budget | G21: Suivi | H21: Budget | J21: Suivi | K21: Budget | M21: Suivi | N21: Budget | P21: Suivi | Q21: Budget | S21: Suivi | T21: Budget | V21: Suivi | W21: Budget | Y21: Suivi | Z21: Budget | AB21: Suivi | AC21: Budget | AE21: Suivi | AF21: Budget | AH21: Suivi | AI21: Budget | AK21: Suivi | AL21: Budget
C22: Frais de gérance | AP22: =C22 -> Frais de gérance | AQ22: =SUM(MAX(D22:E22),MAX(G22:H22),MAX(J22:K22),MAX(M22,N22),MAX(P22:Q22),MAX(S22:T22),MAX(V22:W22),MAX(Y22:Z22),MAX(AB22:AC22),MAX(AE22,AF22),MAX(AH22:AI22),MAX(AK22:AL22)) -> 0
C23: Assurances | AP23: =C23 -> Assurances | AQ23: =SUM(MAX(D23:E23),MAX(G23:H23),MAX(J23:K23),MAX(M23,N23),MAX(P23:Q23),MAX(S23:T23),MAX(V23:W23),MAX(Y23:Z23),MAX(AB23:AC23),MAX(AE23,AF23),MAX(AH23:AI23),MAX(AK23:AL23)) -> 0
C24: Eau | AP24: =C24 -> Eau | AQ24: =SUM(MAX(D24:E24),MAX(G24:H24),MAX(J24:K24),MAX(M24,N24),MAX(P24:Q24),MAX(S24:T24),MAX(V24:W24),MAX(Y24:Z24),MAX(AB24:AC24),MAX(AE24,AF24),MAX(AH24:AI24),MAX(AK24:AL24)) -> 0
C25: Electricité/Gaz | AP25: =C25 -> Electricité/Gaz | AQ25: =SUM(MAX(D25:E25),MAX(G25:H25),MAX(J25:K25),MAX(M25,N25),MAX(P25:Q25),MAX(S25:T25),MAX(V25:W25),MAX(Y25:Z25),MAX(AB25:AC25),MAX(AE25,AF25),MAX(AH25:AI25),MAX(AK25:AL25)) -> 0
C26: Crédit immobilier principal | AP26: =C26 -> Crédit immobilier principal | AQ26: =SUM(MAX(D26:E26),MAX(G26:H26),MAX(J26:K26),MAX(M26,N26),MAX(P26:Q26),MAX(S26:T26),MAX(V26:W26),MAX(Y26:Z26),MAX(AB26:AC26),MAX(AE26,AF26),MAX(AH26:AI26),MAX(AK26:AL26)) -> 0
C27: Crédit secondaire | AP27: =C27 -> Crédit secondaire | AQ27: =SUM(MAX(D27:E27),MAX(G27:H27),MAX(J27:K27),MAX(M27,N27),MAX(P27:Q27),MAX(S27:T27),MAX(V27:W27),MAX(Y27:Z27),MAX(AB27:AC27),MAX(AE27,AF27),MAX(AH27:AI27),MAX(AK27:AL27)) -> 0
C28: Frais bancaires | AP28: =C28 -> Frais bancaires | AQ28: =SUM(MAX(D28:E28),MAX(G28:H28),MAX(J28:K28),MAX(M28,N28),MAX(P28:Q28),MAX(S28:T28),MAX(V28:W28),MAX(Y28:Z28),MAX(AB28:AC28),MAX(AE28,AF28),MAX(AH28:AI28),MAX(AK28:AL28)) -> 0
C29: Taxe foncière | AP29: =C29 -> Taxe foncière | AQ29: =SUM(MAX(D29:E29),MAX(G29:H29),MAX(J29:K29),MAX(M29,N29),MAX(P29:Q29),MAX(S29:T29),MAX(V29:W29),MAX(Y29:Z29),MAX(AB29:AC29),MAX(AE29,AF29),MAX(AH29:AI29),MAX(AK29:AL29)) -> 0
C30: Divers (travaux etc.) | AP30: =C30 -> Divers (travaux etc.) | AQ30: =SUM(MAX(D30:E30),MAX(G30:H30),MAX(J30:K30),MAX(M30,N30),MAX(P30:Q30),MAX(S30:T30),MAX(V30:W30),MAX(Y30:Z30),MAX(AB30:AC30),MAX(AE30,AF30),MAX(AH30:AI30),MAX(AK30:AL30)) -> 0
C31: Entretien / Nettoyage | AP31: =C31 -> Entretien / Nettoyage | AQ31: =SUM(MAX(D31:E31),MAX(G31:H31),MAX(J31:K31),MAX(M31,N31),MAX(P31:Q31),MAX(S31:T31),MAX(V31:W31),MAX(Y31:Z31),MAX(AB31:AC31),MAX(AE31,AF31),MAX(AH31:AI31),MAX(AK31:AL31)) -> 0
C32: Retraits ponctuels | AP32: =C32 -> Retraits ponctuels | AQ32: =SUM(MAX(D32:E32),MAX(G32:H32),MAX(J32:K32),MAX(M32,N32),MAX(P32:Q32),MAX(S32:T32),MAX(V32:W32),MAX(Y32:Z32),MAX(AB32:AC32),MAX(AE32,AF32),MAX(AH32:AI32),MAX(AK32:AL32)) -> 0
C33: Autres | AP33: =C33 -> Autres | AQ33: =SUM(MAX(D33:E33),MAX(G33:H33),MAX(J33:K33),MAX(M33,N33),MAX(P33:Q33),MAX(S33:T33),MAX(V33:W33),MAX(Y33:Z33),MAX(AB33:AC33),MAX(AE33,AF33),MAX(AH33:AI33),MAX(AK33:AL33)) -> 0
C34: Total des sorties | D34: =IF(SUM(D22:D33)=0,"",SUM(D22:D33)) | E34: =SUM(E22:E33) -> 0 | G34: =IF(SUM(G22:G33)=0,"",SUM(G22:G33)) | H34: =SUM(H22:H33) -> 0 | J34: =IF(SUM(J22:J33)=0,"",SUM(J22:J33)) | K34: =SUM(K22:K33) -> 0 | M34: =IF(SUM(M22:M33)=0,"",SUM(M22:M33)) | N34: =SUM(N22:N33) -> 0 | P34: =IF(SUM(P22:P33)=0,"",SUM(P22:P33)) | Q34: =SUM(Q22:Q33) -> 0 | S34: =IF(SUM(S22:S33)=0,"",SUM(S22:S33)) | T34: =SUM(T22:T33) -> 0 | V34: =IF(SUM(V22:V33)=0,"",SUM(V22:V33)) | W34: =SUM(W22:W33) -> 0 | Y34: =IF(SUM(Y22:Y33)=0,"",SUM(Y22:Y33)) | Z34: =SUM(Z22:Z33) -> 0 | AB34: =IF(SUM(AB22:AB33)=0,"",SUM(AB22:AB33)) | AC34: =SUM(AC22:AC33) -> 0 | AE34: =IF(SUM(AE22:AE33)=0,"",SUM(AE22:AE33)) | AF34: =SUM(AF22:AF33) -> 0 | AH34: =IF(SUM(AH22:AH33)=0,"",SUM(AH22:AH33)) | AI34: =SUM(AI22:AI33) -> 0 | AK34: =IF(SUM(AK22:AK33)=0,"",SUM(AK22:AK33)) | AL34: =SUM(AL22:AL33) -> 0 | AP34: Total des sorties annuelles | AQ34: =SUM(AQ22:AS33) -> 0
C35: Différence | D35: =IF(D34="","",E34-D34) | G35: =IF(G34="","",H34-G34) | J35: =IF(J34="","",K34-J34) | M35: =IF(M34="","",N34-M34) | P35: =IF(P34="","",Q34-P34) | S35: =IF(S34="","",T34-S34) | V35: =IF(V34="","",W34-V34) | Y35: =IF(Y34="","",Z34-Y34) | AB35: =IF(AB34="","",AC34-AB34) | AE35: =IF(AE34="","",AF34-AE34) | AH35: =IF(AH34="","",AI34-AH34) | AK35: =IF(AK34="","",AL34-AK34)
D37: =Menu!F22 -> 46174 | G37: =D37+32 -> 46206 | J37: =G37+32 -> 46238 | M37: =J37+32 -> 46270 | P37: =M37+32 -> 46302 | S37: =P37+32 -> 46334 | V37: =S37+32 -> 46366 | Y37: =V37+32 -> 46398 | AB37: =Y37+32 -> 46430 | AE37: =AB37+32 -> 46462 | AH37: =AE37+32 -> 46494 | AK37: =AH37+32 -> 46526
D38: Suivi | E38: Budget | G38: Suivi | H38: Budget | J38: Suivi | K38: Budget | M38: Suivi | N38: Budget | P38: Suivi | Q38: Budget | S38: Suivi | T38: Budget | V38: Suivi | W38: Budget | Y38: Suivi | Z38: Budget | AB38: Suivi | AC38: Budget | AE38: Suivi | AF38: Budget | AH38: Suivi | AI38: Budget | AK38: Suivi | AL38: Budget
C39: BALANCE MENSUELLE DE TRESORERIE -> | D39: =IF(OR(D17="",D34=""),"",D17-D34) | E39: =E17-E34 -> 0 | G39: =IF(OR(G17="",G34=""),"",G17-G34) | H39: =H17-H34 -> 0 | J39: =IF(OR(J17="",J34=""),"",J17-J34) | K39: =K17-K34 -> 0 | M39: =IF(OR(M17="",M34=""),"",M17-M34) | N39: =N17-N34 -> 0 | P39: =IF(OR(P17="",P34=""),"",P17-P34) | Q39: =Q17-Q34 -> 0 | S39: =IF(OR(S17="",S34=""),"",S17-S34) | T39: =T17-T34 -> 0 | V39: =IF(OR(V17="",V34=""),"",V17-V34) | W39: =W17-W34 -> 0 | Y39: =IF(OR(Y17="",Y34=""),"",Y17-Y34) | Z39: =Z17-Z34 -> 0 | AB39: =IF(OR(AB17="",AB34=""),"",AB17-AB34) | AC39: =AC17-AC34 -> 0 | AE39: =IF(OR(AE17="",AE34=""),"",AE17-AE34) | AF39: =AF17-AF34 -> 0 | AH39: =IF(OR(AH17="",AH34=""),"",AH17-AH34) | AI39: =AI17-AI34 -> 0 | AK39: =IF(OR(AK17="",AK34=""),"",AK17-AK34) | AL39: =AL17-AL34 -> 0 | AP39: BALANCE ANNUELLE DE TRESORERIE -> | AQ39: =AQ17-AQ34 -> 0
A42: Trésorerie initiale | C42: CUMUL DE TRESORERIE -> | D42: =A43+E39 -> 0 | G42: =D42+H39 -> 0 | J42: =G42+K39 -> 0 | M42: =J42+N39 -> 0 | P42: =M42+Q39 -> 0 | S42: =P42+T39 -> 0 | V42: =S42+W39 -> 0 | Y42: =V42+Z39 -> 0 | AB42: =Y42+AC39 -> 0 | AE42: =AB42+AF39 -> 0 | AH42: =AE42+AI39 -> 0 | AK42: =AH42+AL39 -> 0 | AP42: CUMUL GENERAL DE TRESORERIE -> | AQ42: =AK42 -> 0
A43: 0
C45: INFORMATIONS UTILES :
C47: LOCATAIRE(S) :
C48: Nom
C49: Prénom
C50: Téléphone
C51: Email
C52: Autres informations utiles
C54: ASSURANCES :
C55: Entreprise
C56: Adresse
C57: Téléphone
C58: Email
... C92: Autres informations utiles

Sheet ImmoView 2
A2: Accès au MENU | C2: < ImmoView > | D2: Bien n° 2 | AP2: < ImmoView >
A3: Accès au Budget
A4: Simulateur d'épargne | C4: Désignation du bien | J4: =Menu!I6 -> Version 2026 Révision VMAX EUR
C5: Adresse
C6: Code postal - VILLE
C8: ENTREES | D8: =Menu!F22 -> 46174 | G8: =D8+32 -> 46206 | J8: =G8+32 -> 46238 | M8: =J8+32 -> 46270 | P8: =M8+32 -> 46302 | S8: =P8+32 -> 46334 | V8: =S8+32 -> 46366 | Y8: =V8+32 -> 46398 | AB8: =Y8+32 -> 46430 | AE8: =AB8+32 -> 46462 | AH8: =AE8+32 -> 46494 | AK8: =AH8+32 -> 46526 | AP8: ENTREES | AQ8: BILAN ANNUEL
D9: Suivi | E9: Budget | G9: Suivi | H9: Budget | J9: Suivi | K9: Budget | M9: Suivi | N9: Budget | P9: Suivi | Q9: Budget | S9: Suivi | T9: Budget | V9: Suivi | W9: Budget | Y9: Suivi | Z9: Budget | AB9: Suivi | AC9: Budget | AE9: Suivi | AF9: Budget | AH9: Suivi | AI9: Budget | AK9: Suivi | AL9: Budget
C10: Loyers | AP10: =C10 -> Loyers | AQ10: =SUM(MAX(D10:E10),MAX(G10:H10),MAX(J10:K10),MAX(M10,N10),MAX(P10:Q10),MAX(S10:T10),MAX(V10:W10),MAX(Y10:Z10),MAX(AB10:AC10),MAX(AE10,AF10),MAX(AH10:AI10),MAX(AK10:AL10)) -> 0
C11: Provisions pour charges | AP11: =C11 -> Provisions pour charges | AQ11: =SUM(MAX(D11:E11),MAX(G11:H11),MAX(J11:K11),MAX(M11,N11),MAX(P11:Q11),MAX(S11:T11),MAX(V11:W11),MAX(Y11:Z11),MAX(AB11:AC11),MAX(AE11,AF11),MAX(AH11:AI11),MAX(AK11:AL11)) -> 0
C12: Dépots de garantie | AP12: =C12 -> Dépots de garantie | AQ12: =SUM(MAX(D12:E12),MAX(G12:H12),MAX(J12:K12),MAX(M12,N12),MAX(P12:Q12),MAX(S12:T12),MAX(V12:W12),MAX(Y12:Z12),MAX(AB12:AC12),MAX(AE12,AF12),MAX(AH12:AI12),MAX(AK12:AL12)) -> 0
C13: Apports personnels | AP13: =C13 -> Apports personnels | AQ13: =SUM(MAX(D13:E13),MAX(G13:H13),MAX(J13:K13),MAX(M13,N13),MAX(P13:Q13),MAX(S13:T13),MAX(V13:W13),MAX(Y13:Z13),MAX(AB13:AC13),MAX(AE13,AF13),MAX(AH13:AI13),MAX(AK13:AL13)) -> 0
C14: Financement | AP14: =C14 -> Financement | AQ14: =SUM(MAX(D14:E14),MAX(G14:H14),MAX(J14:K14),MAX(M14,N14),MAX(P14:Q14),MAX(S14:T14),MAX(V14:W14),MAX(Y14:Z14),MAX(AB14:AC14),MAX(AE14,AF14),MAX(AH14:AI14),MAX(AK14:AL14)) -> 0
C15: Subventions | AP15: =C15 -> Subventions | AQ15: =SUM(MAX(D15:E15),MAX(G15:H15),MAX(J15:K15),MAX(M15,N15),MAX(P15:Q15),MAX(S15:T15),MAX(V15:W15),MAX(Y15:Z15),MAX(AB15:AC15),MAX(AE15,AF15),MAX(AH15:AI15),MAX(AK15:AL15)) -> 0
C16: Autres | AP16: =C16 -> Autres | AQ16: =SUM(MAX(D16:E16),MAX(G16:H16),MAX(J16:K16),MAX(M16,N16),MAX(P16:Q16),MAX(S16:T16),MAX(V16:W16),MAX(Y16:Z16),MAX(AB16:AC16),MAX(AE16,AF16),MAX(AH16:AI16),MAX(AK16:AL16)) -> 0
C17: Total des Entrées | D17: =IF(SUM(D10:D16)=0,"",SUM(D10:D16)) | E17: =SUM(E10:E16) -> 0 | G17: =IF(SUM(G10:G16)=0,"",SUM(G10:G16)) | H17: =SUM(H10:H16) -> 0 | J17: =IF(SUM(J10:J16)=0,"",SUM(J10:J16)) | K17: =SUM(K10:K16) -> 0 | M17: =IF(SUM(M10:M16)=0,"",SUM(M10:M16)) | N17: =SUM(N10:N16) -> 0 | P17: =IF(SUM(P10:P16)=0,"",SUM(P10:P16)) | Q17: =SUM(Q10:Q16) -> 0 | S17: =IF(SUM(S10:S16)=0,"",SUM(S10:S16)) | T17: =SUM(T10:T16) -> 0 | V17: =IF(SUM(V10:V16)=0,"",SUM(V10:V16)) | W17: =SUM(W10:W16) -> 0 | Y17: =IF(SUM(Y10:Y16)=0,"",SUM(Y10:Y16)) | Z17: =SUM(Z10:Z16) -> 0 | AB17: =IF(SUM(AB10:AB16)=0,"",SUM(AB10:AB16)) | AC17: =SUM(AC10:AC16) -> 0 | AE17: =IF(SUM(AE10:AE16)=0,"",SUM(AE10:AE16)) | AF17: =SUM(AF10:AF16) -> 0 | AH17: =IF(SUM(AH10:AH16)=0,"",SUM(AH10:AH16)) | AI17: =SUM(AI10:AI16) -> 0 | AK17: =IF(SUM(AK10:AK16)=0,"",SUM(AK10:AK16)) | AL17: =SUM(AL10:AL16) -> 0 | AP17: Total des Entrées annuelles | AQ17: =SUM(AQ10:AS16) -> 0
C18: Différence | D18: =IF(D17="","",D17-E17) | G18: =IF(G17="","",G17-H17) | J18: =IF(J17="","",J17-K17) | M18: =IF(M17="","",M17-N17) | P18: =IF(P17="","",P17-Q17) | S18: =IF(S17="","",S17-T17) | V18: =IF(V17="","",V17-W17) | Y18: =IF(Y17="","",Y17-Z17) | AB18: =IF(AB17="","",AB17-AC17) | AE18: =IF(AE17="","",AE17-AF17) | AH18: =IF(AH17="","",AH17-AI17) | AK18: =IF(AK17="","",AK17-AL17)
C20: SORTIES | D20: =Menu!F22 -> 46174 | G20: =32+D20 -> 46206 | J20: =32+G20 -> 46238 | M20: =32+J20 -> 46270 | P20: =32+M20 -> 46302 | S20: =32+P20 -> 46334 | V20: =32+S20 -> 46366 | Y20: =32+V20 -> 46398 | AB20: =32+Y20 -> 46430 | AE20: =32+AB20 -> 46462 | AH20: =32+AE20 -> 46494 | AK20: =32+AH20 -> 46526 | AP20: SORTIES
D21: Suivi | E21: Budget | G21: Suivi | H21: Budget | J21: Suivi | K21: Budget | M21: Suivi | N21: Budget | P21: Suivi | Q21: Budget | S21: Suivi | T21: Budget | V21: Suivi | W21: Budget | Y21: Suivi | Z21: Budget | AB21: Suivi | AC21: Budget | AE21: Suivi | AF21: Budget | AH21: Suivi | AI21: Budget | AK21: Suivi | AL21: Budget
C22: Frais de gérance | AP22: =C22 -> Frais de gérance | AQ22: =SUM(MAX(D22:E22),MAX(G22:H22),MAX(J22:K22),MAX(M22,N22),MAX(P22:Q22),MAX(S22:T22),MAX(V22:W22),MAX(Y22:Z22),MAX(AB22:AC22),MAX(AE22,AF22),MAX(AH22:AI22),MAX(AK22:AL22)) -> 0
C23: Assurances | AP23: =C23 -> Assurances | AQ23: =SUM(MAX(D23:E23),MAX(G23:H23),MAX(J23:K23),MAX(M23,N23),MAX(P23:Q23),MAX(S23:T23),MAX(V23:W23),MAX(Y23:Z23),MAX(AB23:AC23),MAX(AE23,AF23),MAX(AH23:AI23),MAX(AK23:AL23)) -> 0
C24: Eau | AP24: =C24 -> Eau | AQ24: =SUM(MAX(D24:E24),MAX(G24:H24),MAX(J24:K24),MAX(M24,N24),MAX(P24:Q24),MAX(S24:T24),MAX(V24:W24),MAX(Y24:Z24),MAX(AB24:AC24),MAX(AE24,AF24),MAX(AH24:AI24),MAX(AK24:AL24)) -> 0
C25: Electricité/Gaz | AP25: =C25 -> Electricité/Gaz | AQ25: =SUM(MAX(D25:E25),MAX(G25:H25),MAX(J25:K25),MAX(M25,N25),MAX(P25:Q25),MAX(S25:T25),MAX(V25:W25),MAX(Y25:Z25),MAX(AB25:AC25),MAX(AE25,AF25),MAX(AH25:AI25),MAX(AK25:AL25)) -> 0
C26: Crédit immobilier principal | AP26: =C26 -> Crédit immobilier principal | AQ26: =SUM(MAX(D26:E26),MAX(G26:H26),MAX(J26:K26),MAX(M26,N26),MAX(P26:Q26),MAX(S26:T26),MAX(V26:W26),MAX(Y26:Z26),MAX(AB26:AC26),MAX(AE26,AF26),MAX(AH26:AI26),MAX(AK26:AL26)) -> 0
C27: Crédit secondaire | AP27: =C27 -> Crédit secondaire | AQ27: =SUM(MAX(D27:E27),MAX(G27:H27),MAX(J27:K27),MAX(M27,N27),MAX(P27:Q27),MAX(S27:T27),MAX(V27:W27),MAX(Y27:Z27),MAX(AB27:AC27),MAX(AE27,AF27),MAX(AH27:AI27),MAX(AK27:AL27)) -> 0
C28: Frais bancaires | AP28: =C28 -> Frais bancaires | AQ28: =SUM(MAX(D28:E28),MAX(G28:H28),MAX(J28:K28),MAX(M28,N28),MAX(P28:Q28),MAX(S28:T28),MAX(V28:W28),MAX(Y28:Z28),MAX(AB28:AC28),MAX(AE28,AF28),MAX(AH28:AI28),MAX(AK28:AL28)) -> 0
C29: Taxe foncière | AP29: =C29 -> Taxe foncière | AQ29: =SUM(MAX(D29:E29),MAX(G29:H29),MAX(J29:K29),MAX(M29,N29),MAX(P29:Q29),MAX(S29:T29),MAX(V29:W29),MAX(Y29:Z29),MAX(AB29:AC29),MAX(AE29,AF29),MAX(AH29:AI29),MAX(AK29:AL29)) -> 0
C30: Divers (travaux etc.) | AP30: =C30 -> Divers (travaux etc.) | AQ30: =SUM(MAX(D30:E30),MAX(G30:H30),MAX(J30:K30),MAX(M30,N30),MAX(P30:Q30),MAX(S30:T30),MAX(V30:W30),MAX(Y30:Z30),MAX(AB30:AC30),MAX(AE30,AF30),MAX(AH30:AI30),MAX(AK30:AL30)) -> 0
C31: Entretien / Nettoyage | AP31: =C31 -> Entretien / Nettoyage | AQ31: =SUM(MAX(D31:E31),MAX(G31:H31),MAX(J31:K31),MAX(M31,N31),MAX(P31:Q31),MAX(S31:T31),MAX(V31:W31),MAX(Y31:Z31),MAX(AB31:AC31),MAX(AE31,AF31),MAX(AH31:AI31),MAX(AK31:AL31)) -> 0
C32: Retraits ponctuels | AP32: =C32 -> Retraits ponctuels | AQ32: =SUM(MAX(D32:E32),MAX(G32:H32),MAX(J32:K32),MAX(M32,N32),MAX(P32:Q32),MAX(S32:T32),MAX(V32:W32),MAX(Y32:Z32),MAX(AB32:AC32),MAX(AE32,AF32),MAX(AH32:AI32),MAX(AK32:AL32)) -> 0
C33: Autres | AP33: =C33 -> Autres | AQ33: =SUM(MAX(D33:E33),MAX(G33:H33),MAX(J33:K33),MAX(M33,N33),MAX(P33:Q33),MAX(S33:T33),MAX(V33:W33),MAX(Y33:Z33),MAX(AB33:AC33),MAX(AE33,AF33),MAX(AH33:AI33),MAX(AK33:AL33)) -> 0
C34: Total des sorties | D34: =IF(SUM(D22:D33)=0,"",SUM(D22:D33)) | E34: =SUM(E22:E33) -> 0 | G34: =IF(SUM(G22:G33)=0,"",SUM(G22:G33)) | H34: =SUM(H22:H33) -> 0 | J34: =IF(SUM(J22:J33)=0,"",SUM(J22:J33)) | K34: =SUM(K22:K33) -> 0 | M34: =IF(SUM(M22:M33)=0,"",SUM(M22:M33)) | N34: =SUM(N22:N33) -> 0 | P34: =IF(SUM(P22:P33)=0,"",SUM(P22:P33)) | Q34: =SUM(Q22:Q33) -> 0 | S34: =IF(SUM(S22:S33)=0,"",SUM(S22:S33)) | T34: =SUM(T22:T33) -> 0 | V34: =IF(SUM(V22:V33)=0,"",SUM(V22:V33)) | W34: =SUM(W22:W33) -> 0 | Y34: =IF(SUM(Y22:Y33)=0,"",SUM(Y22:Y33)) | Z34: =SUM(Z22:Z33) -> 0 | AB34: =IF(SUM(AB22:AB33)=0,"",SUM(AB22:AB33)) | AC34: =SUM(AC22:AC33) -> 0 | AE34: =IF(SUM(AE22:AE33)=0,"",SUM(AE22:AE33)) | AF34: =SUM(AF22:AF33) -> 0 | AH34: =IF(SUM(AH22:AH33)=0,"",SUM(AH22:AH33)) | AI34: =SUM(AI22:AI33) -> 0 | AK34: =IF(SUM(AK22:AK33)=0,"",SUM(AK22:AK33)) | AL34: =SUM(AL22:AL33) -> 0 | AP34: Total des sorties annuelles | AQ34: =SUM(AQ22:AS33) -> 0
C35: Différence | D35: =IF(D34="","",E34-D34) | G35: =IF(G34="","",H34-G34) | J35: =IF(J34="","",K34-J34) | M35: =IF(M34="","",N34-M34) | P35: =IF(P34="","",Q34-P34) | S35: =IF(S34="","",T34-S34) | V35: =IF(V34="","",W34-V34) | Y35: =IF(Y34="","",Z34-Y34) | AB35: =IF(AB34="","",AC34-AB34) | AE35: =IF(AE34="","",AF34-AE34) | AH35: =IF(AH34="","",AI34-AH34) | AK35: =IF(AK34="","",AL34-AK34)
D37: =Menu!F22 -> 46174 | G37: =D37+32 -> 46206 | J37: =G37+32 -> 46238 | M37: =J37+32 -> 46270 | P37: =M37+32 -> 46302 | S37: =P37+32 -> 46334 | V37: =S37+32 -> 46366 | Y37: =V37+32 -> 46398 | AB37: =Y37+32 -> 46430 | AE37: =AB37+32 -> 46462 | AH37: =AE37+32 -> 46494 | AK37: =AH37+32 -> 46526
D38: Suivi | E38: Budget | G38: Suivi | H38: Budget | J38: Suivi | K38: Budget | M38: Suivi | N38: Budget | P38: Suivi | Q38: Budget | S38: Suivi | T38: Budget | V38: Suivi | W38: Budget | Y38: Suivi | Z38: Budget | AB38: Suivi | AC38: Budget | AE38: Suivi | AF38: Budget | AH38: Suivi | AI38: Budget | AK38: Suivi | AL38: Budget
C39: BALANCE MENSUELLE DE TRESORERIE -> | D39: =IF(OR(D17="",D34=""),"",D17-D34) | E39: =E17-E34 -> 0 | G39: =IF(OR(G17="",G34=""),"",G17-G34) | H39: =H17-H34 -> 0 | J39: =IF(OR(J17="",J34=""),"",J17-J34) | K39: =K17-K34 -> 0 | M39: =IF(OR(M17="",M34=""),"",M17-M34) | N39: =N17-N34 -> 0 | P39: =IF(OR(P17="",P34=""),"",P17-P34) | Q39: =Q17-Q34 -> 0 | S39: =IF(OR(S17="",S34=""),"",S17-S34) | T39: =T17-T34 -> 0 | V39: =IF(OR(V17="",V34=""),"",V17-V34) | W39: =W17-W34 -> 0 | Y39: =IF(OR(Y17="",Y34=""),"",Y17-Y34) | Z39: =Z17-Z34 -> 0 | AB39: =IF(OR(AB17="",AB34=""),"",AB17-AB34) | AC39: =AC17-AC34 -> 0 | AE39: =IF(OR(AE17="",AE34=""),"",AE17-AE34) | AF39: =AF17-AF34 -> 0 | AH39: =IF(OR(AH17="",AH34=""),"",AH17-AH34) | AI39: =AI17-AI34 -> 0 | AK39: =IF(OR(AK17="",AK34=""),"",AK17-AK34) | AL39: =AL17-AL34 -> 0 | AP39: BALANCE ANNUELLE DE TRESORERIE -> | AQ39: =AQ17-AQ34 -> 0
A42: Trésorerie initiale | C42: CUMUL DE TRESORERIE -> | D42: =A43+E39 -> 0 | G42: =D42+H39 -> 0 | J42: =G42+K39 -> 0 | M42: =J42+N39 -> 0 | P42: =M42+Q39 -> 0 | S42: =P42+T39 -> 0 | V42: =S42+W39 -> 0 | Y42: =V42+Z39 -> 0 | AB42: =Y42+AC39 -> 0 | AE42: =AB42+AF39 -> 0 | AH42: =AE42+AI39 -> 0 | AK42: =AH42+AL39 -> 0 | AP42: CUMUL GENERAL DE TRESORERIE -> | AQ42: =AK42 -> 0
A43: 0
C45: INFORMATIONS UTILES :
C47: LOCATAIRE(S) :
C48: Nom
C49: Prénom
C50: Téléphone
C51: Email
C52: Autres informations utiles
C54: ASSURANCES :
C55: Entreprise
C56: Adresse
C57: Téléphone
C58: Email
... C92: Autres informations utiles

Sheet ImmoView 3
A2: Accès au MENU | C2: < ImmoView > | D2: Bien n° 3 | AP2: < ImmoView >
A3: Accès au Budget
A4: Simulateur d'épargne | C4: Désignation du bien | J4: =Menu!I6 -> Version 2026 Révision VMAX EUR
C5: Adresse
C6: Code postal - VILLE
C8: ENTREES | D8: =Menu!F22 -> 46174 | G8: =D8+32 -> 46206 | J8: =G8+32 -> 46238 | M8: =J8+32 -> 46270 | P8: =M8+32 -> 46302 | S8: =P8+32 -> 46334 | V8: =S8+32 -> 46366 | Y8: =V8+32 -> 46398 | AB8: =Y8+32 -> 46430 | AE8: =AB8+32 -> 46462 | AH8: =AE8+32 -> 46494 | AK8: =AH8+32 -> 46526 | AP8: ENTREES | AQ8: BILAN ANNUEL
D9: Suivi | E9: Budget | G9: Suivi | H9: Budget | J9: Suivi | K9: Budget | M9: Suivi | N9: Budget | P9: Suivi | Q9: Budget | S9: Suivi | T9: Budget | V9: Suivi | W9: Budget | Y9: Suivi | Z9: Budget | AB9: Suivi | AC9: Budget | AE9: Suivi | AF9: Budget | AH9: Suivi | AI9: Budget | AK9: Suivi | AL9: Budget
C10: Loyers | AP10: =C10 -> Loyers | AQ10: =SUM(MAX(D10:E10),MAX(G10:H10),MAX(J10:K10),MAX(M10,N10),MAX(P10:Q10),MAX(S10:T10),MAX(V10:W10),MAX(Y10:Z10),MAX(AB10:AC10),MAX(AE10,AF10),MAX(AH10:AI10),MAX(AK10:AL10)) -> 0
C11: Provisions pour charges | AP11: =C11 -> Provisions pour charges | AQ11: =SUM(MAX(D11:E11),MAX(G11:H11),MAX(J11:K11),MAX(M11,N11),MAX(P11:Q11),MAX(S11:T11),MAX(V11:W11),MAX(Y11:Z11),MAX(AB11:AC11),MAX(AE11,AF11),MAX(AH11:AI11),MAX(AK11:AL11)) -> 0
C12: Dépots de garantie | AP12: =C12 -> Dépots de garantie | AQ12: =SUM(MAX(D12:E12),MAX(G12:H12),MAX(J12:K12),MAX(M12,N12),MAX(P12:Q12),MAX(S12:T12),MAX(V12:W12),MAX(Y12:Z12),MAX(AB12:AC12),MAX(AE12,AF12),MAX(AH12:AI12),MAX(AK12:AL12)) -> 0
C13: Apports personnels | AP13: =C13 -> Apports personnels | AQ13: =SUM(MAX(D13:E13),MAX(G13:H13),MAX(J13:K13),MAX(M13,N13),MAX(P13:Q13),MAX(S13:T13),MAX(V13:W13),MAX(Y13:Z13),MAX(AB13:AC13),MAX(AE13,AF13),MAX(AH13:AI13),MAX(AK13:AL13)) -> 0
C14: Financement | AP14: =C14 -> Financement | AQ14: =SUM(MAX(D14:E14),MAX(G14:H14),MAX(J14:K14),MAX(M14,N14),MAX(P14:Q14),MAX(S14:T14),MAX(V14:W14),MAX(Y14:Z14),MAX(AB14:AC14),MAX(AE14,AF14),MAX(AH14:AI14),MAX(AK14:AL14)) -> 0
C15: Subventions | AP15: =C15 -> Subventions | AQ15: =SUM(MAX(D15:E15),MAX(G15:H15),MAX(J15:K15),MAX(M15,N15),MAX(P15:Q15),MAX(S15:T15),MAX(V15:W15),MAX(Y15:Z15),MAX(AB15:AC15),MAX(AE15,AF15),MAX(AH15:AI15),MAX(AK15:AL15)) -> 0
C16: Autres | AP16: =C16 -> Autres | AQ16: =SUM(MAX(D16:E16),MAX(G16:H16),MAX(J16:K16),MAX(M16,N16),MAX(P16:Q16),MAX(S16:T16),MAX(V16:W16),MAX(Y16:Z16),MAX(AB16:AC16),MAX(AE16,AF16),MAX(AH16:AI16),MAX(AK16:AL16)) -> 0
C17: Total des Entrées | D17: =IF(SUM(D10:D16)=0,"",SUM(D10:D16)) | E17: =SUM(E10:E16) -> 0 | G17: =IF(SUM(G10:G16)=0,"",SUM(G10:G16)) | H17: =SUM(H10:H16) -> 0 | J17: =IF(SUM(J10:J16)=0,"",SUM(J10:J16)) | K17: =SUM(K10:K16) -> 0 | M17: =IF(SUM(M10:M16)=0,"",SUM(M10:M16)) | N17: =SUM(N10:N16) -> 0 | P17: =IF(SUM(P10:P16)=0,"",SUM(P10:P16)) | Q17: =SUM(Q10:Q16) -> 0 | S17: =IF(SUM(S10:S16)=0,"",SUM(S10:S16)) | T17: =SUM(T10:T16) -> 0 | V17: =IF(SUM(V10:V16)=0,"",SUM(V10:V16)) | W17: =SUM(W10:W16) -> 0 | Y17: =IF(SUM(Y10:Y16)=0,"",SUM(Y10:Y16)) | Z17: =SUM(Z10:Z16) -> 0 | AB17: =IF(SUM(AB10:AB16)=0,"",SUM(AB10:AB16)) | AC17: =SUM(AC10:AC16) -> 0 | AE17: =IF(SUM(AE10:AE16)=0,"",SUM(AE10:AE16)) | AF17: =SUM(AF10:AF16) -> 0 | AH17: =IF(SUM(AH10:AH16)=0,"",SUM(AH10:AH16)) | AI17: =SUM(AI10:AI16) -> 0 | AK17: =IF(SUM(AK10:AK16)=0,"",SUM(AK10:AK16)) | AL17: =SUM(AL10:AL16) -> 0 | AP17: Total des Entrées annuelles | AQ17: =SUM(AQ10:AS16) -> 0
C18: Différence | D18: =IF(D17="","",D17-E17) | G18: =IF(G17="","",G17-H17) | J18: =IF(J17="","",J17-K17) | M18: =IF(M17="","",M17-N17) | P18: =IF(P17="","",P17-Q17) | S18: =IF(S17="","",S17-T17) | V18: =IF(V17="","",V17-W17) | Y18: =IF(Y17="","",Y17-Z17) | AB18: =IF(AB17="","",AB17-AC17) | AE18: =IF(AE17="","",AE17-AF17) | AH18: =IF(AH17="","",AH17-AI17) | AK18: =IF(AK17="","",AK17-AL17)
C20: SORTIES | D20: =Menu!F22 -> 46174 | G20: =32+D20 -> 46206 | J20: =32+G20 -> 46238 | M20: =32+J20 -> 46270 | P20: =32+M20 -> 46302 | S20: =32+P20 -> 46334 | V20: =32+S20 -> 46366 | Y20: =32+V20 -> 46398 | AB20: =32+Y20 -> 46430 | AE20: =32+AB20 -> 46462 | AH20: =32+AE20 -> 46494 | AK20: =32+AH20 -> 46526 | AP20: SORTIES
D21: Suivi | E21: Budget | G21: Suivi | H21: Budget | J21: Suivi | K21: Budget | M21: Suivi | N21: Budget | P21: Suivi | Q21: Budget | S21: Suivi | T21: Budget | V21: Suivi | W21: Budget | Y21: Suivi | Z21: Budget | AB21: Suivi | AC21: Budget | AE21: Suivi | AF21: Budget | AH21: Suivi | AI21: Budget | AK21: Suivi | AL21: Budget
C22: Frais de gérance | AP22: =C22 -> Frais de gérance | AQ22: =SUM(MAX(D22:E22),MAX(G22:H22),MAX(J22:K22),MAX(M22,N22),MAX(P22:Q22),MAX(S22:T22),MAX(V22:W22),MAX(Y22:Z22),MAX(AB22:AC22),MAX(AE22,AF22),MAX(AH22:AI22),MAX(AK22:AL22)) -> 0
C23: Assurances | AP23: =C23 -> Assurances | AQ23: =SUM(MAX(D23:E23),MAX(G23:H23),MAX(J23:K23),MAX(M23,N23),MAX(P23:Q23),MAX(S23:T23),MAX(V23:W23),MAX(Y23:Z23),MAX(AB23:AC23),MAX(AE23,AF23),MAX(AH23:AI23),MAX(AK23:AL23)) -> 0
C24: Eau | AP24: =C24 -> Eau | AQ24: =SUM(MAX(D24:E24),MAX(G24:H24),MAX(J24:K24),MAX(M24,N24),MAX(P24:Q24),MAX(S24:T24),MAX(V24:W24),MAX(Y24:Z24),MAX(AB24:AC24),MAX(AE24,AF24),MAX(AH24:AI24),MAX(AK24:AL24)) -> 0
C25: Electricité/Gaz | AP25: =C25 -> Electricité/Gaz | AQ25: =SUM(MAX(D25:E25),MAX(G25:H25),MAX(J25:K25),MAX(M25,N25),MAX(P25:Q25),MAX(S25:T25),MAX(V25:W25),MAX(Y25:Z25),MAX(AB25:AC25),MAX(AE25,AF25),MAX(AH25:AI25),MAX(AK25:AL25)) -> 0
C26: Crédit immobilier principal | AP26: =C26 -> Crédit immobilier principal | AQ26: =SUM(MAX(D26:E26),MAX(G26:H26),MAX(J26:K26),MAX(M26,N26),MAX(P26:Q26),MAX(S26:T26),MAX(V26:W26),MAX(Y26:Z26),MAX(AB26:AC26),MAX(AE26,AF26),MAX(AH26:AI26),MAX(AK26:AL26)) -> 0
C27: Crédit secondaire | AP27: =C27 -> Crédit secondaire | AQ27: =SUM(MAX(D27:E27),MAX(G27:H27),MAX(J27:K27),MAX(M27,N27),MAX(P27:Q27),MAX(S27:T27),MAX(V27:W27),MAX(Y27:Z27),MAX(AB27:AC27),MAX(AE27,AF27),MAX(AH27:AI27),MAX(AK27:AL27)) -> 0
C28: Frais bancaires | AP28: =C28 -> Frais bancaires | AQ28: =SUM(MAX(D28:E28),MAX(G28:H28),MAX(J28:K28),MAX(M28,N28),MAX(P28:Q28),MAX(S28:T28),MAX(V28:W28),MAX(Y28:Z28),MAX(AB28:AC28),MAX(AE28,AF28),MAX(AH28:AI28),MAX(AK28:AL28)) -> 0
C29: Taxe foncière | AP29: =C29 -> Taxe foncière | AQ29: =SUM(MAX(D29:E29),MAX(G29:H29),MAX(J29:K29),MAX(M29,N29),MAX(P29:Q29),MAX(S29:T29),MAX(V29:W29),MAX(Y29:Z29),MAX(AB29:AC29),MAX(AE29,AF29),MAX(AH29:AI29),MAX(AK29:AL29)) -> 0
C30: Divers (travaux etc.) | AP30: =C30 -> Divers (travaux etc.) | AQ30: =SUM(MAX(D30:E30),MAX(G30:H30),MAX(J30:K30),MAX(M30,N30),MAX(P30:Q30),MAX(S30:T30),MAX(V30:W30),MAX(Y30:Z30),MAX(AB30:AC30),MAX(AE30,AF30),MAX(AH30:AI30),MAX(AK30:AL30)) -> 0
C31: Entretien / Nettoyage | AP31: =C31 -> Entretien / Nettoyage | AQ31: =SUM(MAX(D31:E31),MAX(G31:H31),MAX(J31:K31),MAX(M31,N31),MAX(P31:Q31),MAX(S31:T31),MAX(V31:W31),MAX(Y31:Z31),MAX(AB31:AC31),MAX(AE31,AF31),MAX(AH31:AI31),MAX(AK31:AL31)) -> 0
C32: Retraits ponctuels | AP32: =C32 -> Retraits ponctuels | AQ32: =SUM(MAX(D32:E32),MAX(G32:H32),MAX(J32:K32),MAX(M32,N32),MAX(P32:Q32),MAX(S32:T32),MAX(V32:W32),MAX(Y32:Z32),MAX(AB32:AC32),MAX(AE32,AF32),MAX(AH32:AI32),MAX(AK32:AL32)) -> 0
C33: Autres | AP33: =C33 -> Autres | AQ33: =SUM(MAX(D33:E33),MAX(G33:H33),MAX(J33:K33),MAX(M33,N33),MAX(P33:Q33),MAX(S33:T33),MAX(V33:W33),MAX(Y33:Z33),MAX(AB33:AC33),MAX(AE33,AF33),MAX(AH33:AI33),MAX(AK33:AL33)) -> 0
C34: Total des sorties | D34: =IF(SUM(D22:D33)=0,"",SUM(D22:D33)) | E34: =SUM(E22:E33) -> 0 | G34: =IF(SUM(G22:G33)=0,"",SUM(G22:G33)) | H34: =SUM(H22:H33) -> 0 | J34: =IF(SUM(J22:J33)=0,"",SUM(J22:J33)) | K34: =SUM(K22:K33) -> 0 | M34: =IF(SUM(M22:M33)=0,"",SUM(M22:M33)) | N34: =SUM(N22:N33) -> 0 | P34: =IF(SUM(P22:P33)=0,"",SUM(P22:P33)) | Q34: =SUM(Q22:Q33) -> 0 | S34: =IF(SUM(S22:S33)=0,"",SUM(S22:S33)) | T34: =SUM(T22:T33) -> 0 | V34: =IF(SUM(V22:V33)=0,"",SUM(V22:V33)) | W34: =SUM(W22:W33) -> 0 | Y34: =IF(SUM(Y22:Y33)=0,"",SUM(Y22:Y33)) | Z34: =SUM(Z22:Z33) -> 0 | AB34: =IF(SUM(AB22:AB33)=0,"",SUM(AB22:AB33)) | AC34: =SUM(AC22:AC33) -> 0 | AE34: =IF(SUM(AE22:AE33)=0,"",SUM(AE22:AE33)) | AF34: =SUM(AF22:AF33) -> 0 | AH34: =IF(SUM(AH22:AH33)=0,"",SUM(AH22:AH33)) | AI34: =SUM(AI22:AI33) -> 0 | AK34: =IF(SUM(AK22:AK33)=0,"",SUM(AK22:AK33)) | AL34: =SUM(AL22:AL33) -> 0 | AP34: Total des sorties annuelles | AQ34: =SUM(AQ22:AS33) -> 0
C35: Différence | D35: =IF(D34="","",E34-D34) | G35: =IF(G34="","",H34-G34) | J35: =IF(J34="","",K34-J34) | M35: =IF(M34="","",N34-M34) | P35: =IF(P34="","",Q34-P34) | S35: =IF(S34="","",T34-S34) | V35: =IF(V34="","",W34-V34) | Y35: =IF(Y34="","",Z34-Y34) | AB35: =IF(AB34="","",AC34-AB34) | AE35: =IF(AE34="","",AF34-AE34) | AH35: =IF(AH34="","",AI34-AH34) | AK35: =IF(AK34="","",AL34-AK34)
D37: =Menu!F22 -> 46174 | G37: =D37+32 -> 46206 | J37: =G37+32 -> 46238 | M37: =J37+32 -> 46270 | P37: =M37+32 -> 46302 | S37: =P37+32 -> 46334 | V37: =S37+32 -> 46366 | Y37: =V37+32 -> 46398 | AB37: =Y37+32 -> 46430 | AE37: =AB37+32 -> 46462 | AH37: =AE37+32 -> 46494 | AK37: =AH37+32 -> 46526
D38: Suivi | E38: Budget | G38: Suivi | H38: Budget | J38: Suivi | K38: Budget | M38: Suivi | N38: Budget | P38: Suivi | Q38: Budget | S38: Suivi | T38: Budget | V38: Suivi | W38: Budget | Y38: Suivi | Z38: Budget | AB38: Suivi | AC38: Budget | AE38: Suivi | AF38: Budget | AH38: Suivi | AI38: Budget | AK38: Suivi | AL38: Budget
C39: BALANCE MENSUELLE DE TRESORERIE -> | D39: =IF(OR(D17="",D34=""),"",D17-D34) | E39: =E17-E34 -> 0 | G39: =IF(OR(G17="",G34=""),"",G17-G34) | H39: =H17-H34 -> 0 | J39: =IF(OR(J17="",J34=""),"",J17-J34) | K39: =K17-K34 -> 0 | M39: =IF(OR(M17="",M34=""),"",M17-M34) | N39: =N17-N34 -> 0 | P39: =IF(OR(P17="",P34=""),"",P17-P34) | Q39: =Q17-Q34 -> 0 | S39: =IF(OR(S17="",S34=""),"",S17-S34) | T39: =T17-T34 -> 0 | V39: =IF(OR(V17="",V34=""),"",V17-V34) | W39: =W17-W34 -> 0 | Y39: =IF(OR(Y17="",Y34=""),"",Y17-Y34) | Z39: =Z17-Z34 -> 0 | AB39: =IF(OR(AB17="",AB34=""),"",AB17-AB34) | AC39: =AC17-AC34 -> 0 | AE39: =IF(OR(AE17="",AE34=""),"",AE17-AE34) | AF39: =AF17-AF34 -> 0 | AH39: =IF(OR(AH17="",AH34=""),"",AH17-AH34) | AI39: =AI17-AI34 -> 0 | AK39: =IF(OR(AK17="",AK34=""),"",AK17-AK34) | AL39: =AL17-AL34 -> 0 | AP39: BALANCE ANNUELLE DE TRESORERIE -> | AQ39: =AQ17-AQ34 -> 0
A42: Trésorerie initiale | C42: CUMUL DE TRESORERIE -> | D42: =A43+E39 -> 0 | G42: =D42+H39 -> 0 | J42: =G42+K39 -> 0 | M42: =J42+N39 -> 0 | P42: =M42+Q39 -> 0 | S42: =P42+T39 -> 0 | V42: =S42+W39 -> 0 | Y42: =V42+Z39 -> 0 | AB42: =Y42+AC39 -> 0 | AE42: =AB42+AF39 -> 0 | AH42: =AE42+AI39 -> 0 | AK42: =AH42+AL39 -> 0 | AP42: CUMUL GENERAL DE TRESORERIE -> | AQ42: =AK42 -> 0
A43: 0
C45: INFORMATIONS UTILES :
C47: LOCATAIRE(S) :
C48: Nom
C49: Prénom
C50: Téléphone
C51: Email
C52: Autres informations utiles
C54: ASSURANCES :
C55: Entreprise
C56: Adresse
C57: Téléphone
C58: Email
... C92: Autres informations utiles

Sheet Données
L2: ImmoView | N2: ImmoView | P2: Priorités | R2: Devis
B3: Menu | L3: RESSOURCES | N3: CHARGES
J4: Comptes courants | L4: Loyers bruts | N4: Frais de gérance | P4: 1 (indispensable) | R4: Devis 1
B5: Situation familiale | D5: Nombre d'enfants mineurs | F5: Nombre d'enfants majeurs | H5: Date de début du budget | J5: CPTES | L5: Provisions pour charges | N5: Assurances | P5: 2 (essentiel) | R5: Devis 2
B6: SITFA1 | D6: NBMIN1 | F6: NBMAJ1 | H6: DEBUDGET1 | J6: - sélectionner - | L6: Dépots de garantie | N6: Eau | P6: 3 (souhaitable) | R6: Devis 3
B7: - sélectionner - | D7: - sélectionner - | F7: - sélectionner - | H7: - sélectionner - | I7: 1 | J7: =IF('Menu 2'!E8="","",'Menu 2'!E8) -> Compte courant - BANXO | L7: Apports personnels | N7: Electricité
B8: en couple | D8: 0 | E8: 1 | F8: 0 | G8: 1 | H8: 46023 | I8: 2 | J8: =IF('Menu 2'!E9="","",'Menu 2'!E9) -> Compte courant - Revolut | L8: Financement | N8: Crédit principal
B9: célibataire | D9: 1 | E9: 2 | F9: 1 | G9: 2 | H9: 46054 | I9: 3 | J9: =IF('Menu 2'!E10="","",'Menu 2'!E10) | L9: Subventions | N9: Ccrédit secondaire
B10: parent seul | D10: 2 | E10: 3 | F10: 2 | G10: 3 | H10: 46082 | I10: 4 | J10: =IF('Menu 2'!E11="","",'Menu 2'!E11) | L10: Autres | N10: Frais bancaires
B11: étudiant | D11: 3 | E11: 4 | F11: 3 | G11: 4 | H11: 46113 | I11: 5 | J11: =IF('Menu 2'!E12="","",'Menu 2'!E12) | N11: Taxe foncière
B12: veuf/veuve | D12: 4 | E12: 5 | F12: 4 | G12: 5 | H12: 46143 | I12: 6 | J12: =IF('Menu 2'!E13="","",'Menu 2'!E13) | N12: Divers (travaux etc.)
B13: autre (association, société, etc.) | D13: 5 | E13: 6 | F13: 5 | G13: 6 | H13: 46174 | I13: 7 | J13: =IF('Menu 2'!E14="","",'Menu 2'!E14) | N13: ADI
D14: plus de 5 | E14: 7 | F14: plus de 5 | G14: 7 | H14: 46204 | I14: 8 | J14: =IF('Menu 2'!E15="","",'Menu 2'!E15) | N14: Retraits ponctuels
H15: 46235 | I15: 9 | J15: =IF('Menu 2'!E16="","",'Menu 2'!E16) | N15: Autres
H16: 46266 | I16: 10 | J16: =IF('Menu 2'!E17="","",'Menu 2'!E17)
H17: 46296 | I17: 11 | J17: =IF('Menu 2'!E18="","",'Menu 2'!E18)
H18: 46327 | I18: 12 | J18: =IF('Menu 2'!E19="","",'Menu 2'!E19)
H19: 46357
B21: Budget 2019
B23: Les mois | D23: Revenus | F23: Validation | H23: Epargne & Placements | J23: Epargne & Placements | L23: Crédits | N23: Prélèvements | P23: Provisions | R23: Compte Provisions | T23: Dépenses fixes | V23: Dépenses variables
D24: REV | F24: OK | H24: EPAR | J24: EPARBUT | L24: CREDIT | N24: DATE | P24: PROV | R24: CPROV | T24: DFIX | V24: DVAR
A25: 0 | B25: DECEMBRE 2018 | C25: Décembre | D25: Revenu à configurer | H25: Type d'épargne/placement | J25: Indiquer le nom du projet à financer | L25: Indiquer le crédit/prêt/dette à rembourser | N25: Indiquer la date de l'échéance | P25: Indiquer le nom de la provision à financer | R25: Indiquer le compte cible | T25: Autre dépense régulière | V25: Autre dépense variable
A26: 1 | B26: JANVIER 2019 | C26: Janvier | D26: SALAIRE | F26: ok | H26: Assurance-Vie | J26: Stratégie "RETRAITE" | L26: Crédit à la consommation - SOFINCO | N26: prélèvement le 1er du mois | P26: Provision - Impôt sur le Revenu | R26: Assurance-Vie | T26: Loyer | V26: Divertissement
A27: 2 | B27: FEVRIER 2019 | C27: Février | D27: SALAIRE 1 | F27: ec | H27: Assurance-Vie (bloquée) | J27: TRESOR FAMILIAL | L27: Crédit à la consommation - FINANCO | N27: prélèvement le 02 du mois | P27: Provision - Taxe d'Habitation + Taxe Foncière | R27: CEL - Compte d'Epargne Logement | T27: Loyer/ Remboursement Prêt Immobilier | V27: Frais Médicaux
A28: 3 | B28: MARS 2019 | C28: Mars | D28: SALAIRE 2 | F28: ea | H28: Assurance-Vie (non bloquée) | J28: Epargne pour "IMPREVUS" | L28: Crédit à la consommation - CETELEM | N28: prélèvement le 03 du mois | P28: Provision - Factures Energie | R28: LEP - Livret d'Epargne Populaire | T28: Remboursement - Prêt Résidence Principale | V28: Argent de poche
A29: 4 | B29: AVRIL 2019 | C29: Avril | D29: SALAIRE A | H29: Assurance-Vie "Multi-supports" | J29: Capital "ETUDES & VIE ACTIVE" - Enfant | L29: Crédit à la consommation - FINAREF | N29: prélèvement le 04 du mois | P29: Provision - Vacances / Sorties / Détente | R29: LDD - Livret de Développement Durable | T29: Remboursement - Prêt Immobilier Locatif | V29: Liquidités
A30: 5 | B30: MAI 2019 | C30: Mai | D30: SALAIRE B | H30: PEP - Plan d'Epargne Populaire | J30: Capital "NAISSANCE" - Enfant | L30: Crédit à la consommation - COFIDIS | N30: prélèvement le 05 du mois | P30: Provision - Charges de Co-propriété | R30: Livret A | T30: Carte de transport | V30: Soutien familial
A31: 6 | B31: JUIN 2019 | C31: Juin | D31: Allocations | F31: Dîme (Revenus) | H31: PEA - Plan d'Epargne en Actions | J31: Capital "ACHAT IMMOBILIER" | L31: Crédit à la consommation - MENAFINANCE | N31: prélèvement le 06 du mois | P31: Provision - Mazout/Fuel | R31: Livret B | T31: Mutuelle | V31: Aide aux tiers
A32: 7 | B32: JUILLET 2019 | C32: Juillet | D32: Revenu Foncier Immeuble | F32: DIME | H32: PEL - Plan d'Epargne Logement | J32: Capital "ACHAT TERRAIN" | L32: Crédit à la consommation - COVEFI | N32: prélèvement le 07 du mois | P32: Provision - Habillement | R32: Livret JEUNE | T32: Cotisation de Prévoyance | V32: Cotisation Associative
A33: 8 | B33: AOUT 2019 | C33: Août | D33: Revenu Foncier Appartement | F33: oui | H33: CEL - Compte d'Epargne Logement | J33: Capital "ACHAT APPARTEMENT" | L33: Crédit à la consommation - FRANFINANCE | N33: prélèvement le 08 du mois | P33: Provision - Habillement Enfants | R33: Livret d'épargne | T33: Courses Entretien / Alimentation | V33: Aide humanitaire
A34: 9 | B34: SEPTEMBRE 2019 | C34: Septembre | D34: Dividendes Entreprises | F34: non | H34: LEP - Livret d'Epargne Populaire | J34: Capital "ACHAT VILLA" | L34: Crédit à la consommation | N34: prélèvement le 09 du mois | P34: Provision - Carburant/Essence | R34: Livret Internet | T34: Assurance Auto | V34: Habillement
A35: 10 | B35: OCTOBRE 2019 | C35: Octobre | D35: Dividendes Actions | H35: LDD - Livret de Développement Durable | J35: TCR - INVESTISSEMENTS | L35: Crédit Carte AURORE | N35: prélèvement le 10 du mois | P35: Provision - Permis de conduire | R35: Compte à Terme | T35: Assurance Habitation
A36: 11 | B36: NOVEMBRE 2019 | C36: Novembre | D36: Dividendes Activités Commerciales | H36: Livret A | J36: Trésorerie "TCR - INVESTISSEMENTS" | L36: Crédit Carte CONFORAMA | N36: prélèvement le 11 du mois | P36: Provision - Redevance TV (Taxe audiovisuelle) | R36: Compte courant | T36: Abonnement Internet
A37: 12 | B37: DECEMBRE 2019 | C37: Décembre | D37: DIVIDENDES | H37: Livret B | J37: Trésorerie " INVESTISSEMENTS " | L37: Crédit Carte KANGOUROU | N37: prélèvement le 12 du mois | P37: Provision - Assurance Auto | T37: Abonnement Bouquet TV
A38: 13 | B38: JANVIER 2020 | C38: Janvier | D38: Intérêts sur capitaux | F38: Extra Projection | H38: Livret JEUNE | J38: Capital "INVESTISSEMENTS" | L38: Crédit Carte PASS | N38: prélèvement le 13 du mois | P38: Provision - Entretien Auto | T38: Téléphone portable
A39: 14 | B39: FEVRIER 2020 | C39: Février | D39: APL | F39: PROJECTION | H39: Livret Internet | J39: Epargne "ACHAT VOITURE" | L39: Dette - LOCAPASS | N39: prélèvement le 14 du mois | P39: Provision - Assurance Auto / Réparations | T39: Téléphone
A40: 15 | B40: MARS 2020 | C40: Mars | D40: Revenu Locatif - Immeuble | F40: ExtraP activé | H40: Livret d'épargne | J40: Trésorerie de "RESERVE" | L40: Dette - Loyers impayés | N40: prélèvement le 15 du mois | P40: Provision - Cadeaux (Anniversaires, événements, etc.) | T40: Carburants (Essence/Gasoil)
A41: 16 | B41: AVRIL 2020 | C41: Avril | D41: Revenu Locatif - Appartement | F41: ExtraP Off | H41: PEE - Plan d'Epargne Entreprise | J41: Trésorerie "FRAIS de SCOLARITE" | L41: Dette à un tiers | N41: prélèvement le 16 du mois | P41: Provision - Communications (téléphone, internet, etc.) | T41: Déjeuners en semaine
A42: 17 | B42: MAI 2020 | C42: Mai | D42: Retour de Capital d'Investissement | H42: PERCO - Plan d'Epargne pour la Retraite Collectif | J42: Réserve de "SOUTIEN FAMILIAL" | L42: Prêt Personnel - BNP-PARIBAS | N42: prélèvement le 17 du mois | P42: Provision - Téléphone et Internet | T42: Cotisation Carte Bleue (Visa/Mastercard)
D43: Retour de prêt | H43: PERP - Plan d'Epargne Retraite Populaire | J43: Trésorerie "Service pour DIEU & Bonnes Œuvres" | L43: Prêt Personnel - SOCIETE GENERALE | N43: prélèvement le 18 du mois | T43: Cotisation bancaire
D44: Bourse d'Etat | H44: Epargne Salariale | L44: Prêt Personnel - COFIDIS | N44: prélèvement le 19 du mois | T44: Frais de garde (enfants)
D45: Autres | F45: TYPE GRAND DISPATCHING | H45: Compte à Terme (bloqué) | L45: Prêt Personnel - Banque ACCORD | N45: prélèvement le 20 du mois | T45: Frais de garde
H46: Compte de Trésorerie | L46: Prêt Personnel - EGG | N46: prélèvement le 21 du mois | T46: Abonnement Fitness
F47: € | H47: Compte Titre | L47: Prêt Personnel | N47: prélèvement le 22 du mois | T47: Sport
F48: % | H48: Portefeuille Boursier | N48: prélèvement le 23 du mois | T48: Divertissement
H49: TONTINE - Le Conservateur | N49: prélèvement le 24 du mois | T49: Frais Médicaux
H50: TONTINE | N50: prélèvement le 25 du mois | T50: Argent de poche
F51: TYPE GRAND DISPATCHING | H51: Stocks Options | N51: prélèvement le 26 du mois | T51: Liquidités
N52: prélèvement le 27 du mois | T52: Soutien familial
F53: Activé | N53: prélèvement le 28 du mois | T53: Aide aux tiers
F54: Désactivé | N54: prélèvement le 29 du mois | T54: Cotisation Associative
N55: prélèvement le 30 du mois | T55: Aide humanitaire
N56: prélèvement le 31 du mois | T56: Habillement
B59: Menu 2
B62: Vos comptes d'épargne | D62: ImmoView (Entrées) | F62: ImmoView (Sorties) | H62: Date du mariage
B63: VCDE
B64: - compte d'épargne à saisir - | D64: Loyers bruts | F64: Frais de gérance | H64: jj/mm/aaaa
A65: 1 | B65: =IF('Menu 2'!E24="","",'Menu 2'!E24) -> Livret A - BANXO | D65: Loyers | F65: Assurances
A66: 2 | B66: =IF('Menu 2'!E25="","",'Menu 2'!E25) -> PEA - Bourse direct | D66: Provisions pour charges | F66: Eau
A67: 3 | B67: =IF('Menu 2'!E26="","",'Menu 2'!E26) -> Assurance vie - Finarylife | D67: Dépots de garantie | F67: Electricité/Gaz
A68: 4 | B68: =IF('Menu 2'!E27="","",'Menu 2'!E27) -> Placements financiers | D68: Apports personnels | F68: Crédit immobilier principal | H68: Type financement
A69: 5 | B69: =IF('Menu 2'!E28="","",'Menu 2'!E28) -> Fonds euros - Finarylife | D69: Financement | F69: Crédit secondaire
A70: 6 | B70: =IF('Menu 2'!E29="","",'Menu 2'!E29) | D70: Subventions | F70: Frais bancaires | H70: Fiancés
A71: 7 | B71: =IF('Menu 2'!E30="","",'Menu 2'!E30) | D71: Remboursement d'impôts | F71: Taxe foncière | H71: Famille
A72: 8 | B72: =IF('Menu 2'!E31="","",'Menu 2'!E31) | D72: Autres | F72: Divers (travaux etc.) | H72: Amis / collègues
A73: 9 | B73: =IF('Menu 2'!E32="","",'Menu 2'!E32) | F73: ADI
A74: 10 | B74: =IF('Menu 2'!E33="","",'Menu 2'!E33) | F74: Retraits ponctuels
A75: 11 | B75: =IF('Menu 2'!E34="","",'Menu 2'!E34) | F75: Electricité
A76: 12 | B76: =IF('Menu 2'!E35="","",'Menu 2'!E35) | F76: Gaz | H76: Etat
A77: =A76+1 -> 13 | B77: =IF('Menu 2'!E36="","",'Menu 2'!E36) | F77: Entretien / Nettoyage
A78: =A77+1 -> 14 | B78: =IF('Menu 2'!E37="","",'Menu 2'!E37) | F78: Autres | H78: Non effectué
A79: =A78+1 -> 15 | B79: =IF('Menu 2'!E38="","",'Menu 2'!E38) | H79: Effectué
A80: =A79+1 -> 16 | B80: =IF('Menu 2'!E39="","",'Menu 2'!E39)
A81: =A80+1 -> 17 | B81: =IF('Menu 2'!E40="","",'Menu 2'!E40)
A82: =A81+1 -> 18 | B82: =IF('Menu 2'!E41="","",'Menu 2'!E41)
A83: =A82+1 -> 19 | B83: =IF('Menu 2'!E42="","",'Menu 2'!E42)
A84: =A83+1 -> 20 | B84: =IF('Menu 2'!E43="","",'Menu 2'!E43)
A85: =A84+1 -> 21 | B85: =IF('Menu 2'!E44="","",'Menu 2'!E44)
A86: =A85+1 -> 22 | B86: =IF('Menu 2'!E45="","",'Menu 2'!E45)
A87: =A86+1 -> 23 | B87: =IF('Menu 2'!E46="","",'Menu 2'!E46)
A88: =A87+1 -> 24 | B88: =IF('Menu 2'!E47="","",'Menu 2'!E47)
A89: =A88+1 -> 25 | B89: =IF('Menu 2'!E48="","",'Menu 2'!E48)
A90: =A89+1 -> 26 | B90: =IF('Menu 2'!E49="","",'Menu 2'!E49)
A91: =A90+1 -> 27 | B91: =IF('Menu 2'!E50="","",'Menu 2'!E50)
... A94: =A93+1 -> 30 | B94: =IF('Menu 2'!E53="","",'Menu 2'!E53) -> PATRIMOINE

Sheet Vir 1
A2: Retour au Budget | C2: Synthèses des mouvements sur vos comptes d'épargne et de provisions
E3: ='Budget Gold'!I7 -> 46174
B6: Liste de l'épargne et des provisions | E6: Entrées | F6: Sorties | G6: Mouvements | I6: Solde unitaire
J7: ='Budget Gold'!I7 -> 46174
A8: 1 | B8: =IF('Budget Gold'!E54="Indiquer le nom du projet à financer","",'Budget Gold'!E54) -> PEA - INVESTISSEMENTS | C8: =IF('Budget Gold'!E56="- compte d'épargne à saisir -","",'Budget Gold'!E56) -> PEA - Bourse direct | E8: ='Budget Gold'!J54 -> 250 | F8: ='Budget Gold'!J55 -> 0 | G8: =E8-F8 -> 250 | H8: =IF(G8>0,"(+) à ajouter sur le compte épargne",IF(G8=0,"--- rien à faire ---","(-) de moins sur le compte épargne")) -> (+) à ajouter sur le compte épargne | I8: ='Budget Gold'!I56 -> 39780
A9: =1+A8 -> 2 | B9: =IF('Budget Gold'!E57="Indiquer le nom du projet à financer","",'Budget Gold'!E57) -> Assurance vie "INVESTISSEMENTS" | C9: =IF('Budget Gold'!E59="- compte d'épargne à saisir -","",'Budget Gold'!E59) -> Assurance vie - Finarylife | E9: ='Budget Gold'!J57 -> 200 | F9: ='Budget Gold'!J58 -> 0 | G9: =E9-F9 -> 200 | H9: =IF(G9>0,"(+) à ajouter sur le compte épargne",IF(G9=0,"--- rien à faire ---","(-) de moins sur le compte épargne")) -> (+) à ajouter sur le compte épargne | I9: ='Budget Gold'!I59 -> 2511
A10: =1+A9 -> 3 | B10: =IF('Budget Gold'!E60="Indiquer le nom du projet à financer","",'Budget Gold'!E60) -> Trésorerie "Service pour DIEU & Bonnes Œuvres" | C10: =IF('Budget Gold'!E62="- compte d'épargne à saisir -","",'Budget Gold'!E62) -> Livret A - BANXO | E10: ='Budget Gold'!J60 -> 100 | F10: ='Budget Gold'!J61 -> 0 | G10: =E10-F10 -> 100 | H10: =IF(G10>0,"(+) à ajouter sur le compte épargne",IF(G10=0,"--- rien à faire ---","(-) de moins sur le compte épargne")) -> (+) à ajouter sur le compte épargne | I10: ='Budget Gold'!I62 -> 100
A11: =1+A10 -> 4 | B11: =IF('Budget Gold'!E63="Indiquer le nom du projet à financer","",'Budget Gold'!E63) -> Réserve de "SOUTIEN FAMILIAL" | C11: =IF('Budget Gold'!E65="- compte d'épargne à saisir -","",'Budget Gold'!E65) -> Livret A - BANXO | E11: ='Budget Gold'!J63 -> 25 | F11: ='Budget Gold'!J64 -> 0 | G11: =E11-F11 -> 25 | H11: =IF(G11>0,"(+) à ajouter sur le compte épargne",IF(G11=0,"--- rien à faire ---","(-) de moins sur le compte épargne")) -> (+) à ajouter sur le compte épargne | I11: ='Budget Gold'!I65 -> 25
A12: =1+A11 -> 5 | B12: =IF('Budget Gold'!E66="Indiquer le nom du projet à financer","",'Budget Gold'!E66) -> Epargne pour "Mariage" | C12: =IF('Budget Gold'!E68="- compte d'épargne à saisir -","",'Budget Gold'!E68) -> Livret A - BANXO | E12: ='Budget Gold'!J66 -> 50 | F12: ='Budget Gold'!J67 -> 0 | G12: =E12-F12 -> 50 | H12: =IF(G12>0,"(+) à ajouter sur le compte épargne",IF(G12=0,"--- rien à faire ---","(-) de moins sur le compte épargne")) -> (+) à ajouter sur le compte épargne | I12: ='Budget Gold'!I68 -> 50
A13: =1+A12 -> 6 | B13: =IF('Budget Gold'!E69="Indiquer le nom du projet à financer","",'Budget Gold'!E69) -> Epargne pour "IMPREVUS" | C13: =IF('Budget Gold'!E71="- compte d'épargne à saisir -","",'Budget Gold'!E71) -> Livret A - BANXO | E13: ='Budget Gold'!J69 -> 100 | F13: ='Budget Gold'!J70 -> 0 | G13: =E13-F13 -> 100 | H13: =IF(G13>0,"(+) à ajouter sur le compte épargne",IF(G13=0,"--- rien à faire ---","(-) de moins sur le compte épargne")) -> (+) à ajouter sur le compte épargne | I13: ='Budget Gold'!I71 -> 8100
A14: =1+A13 -> 7 | B14: =IF('Budget Gold'!E72="Indiquer le nom du projet à financer","",'Budget Gold'!E72) -> Epargne pour 'FORMATION" (compétences, etc.) | C14: =IF('Budget Gold'!E74="- compte d'épargne à saisir -","",'Budget Gold'!E74) -> Livret A - BANXO | E14: ='Budget Gold'!J72 -> 25 | F14: ='Budget Gold'!J73 -> 0 | G14: =E14-F14 -> 25 | H14: =IF(G14>0,"(+) à ajouter sur le compte épargne",IF(G14=0,"--- rien à faire ---","(-) de moins sur le compte épargne")) -> (+) à ajouter sur le compte épargne | I14: ='Budget Gold'!I74 -> 25
A15: =1+A14 -> 8 | B15: =IF('Budget Gold'!E75="Indiquer le nom du projet à financer","",'Budget Gold'!E75) -> Epargne "ACHAT VOITURE" | C15: =IF('Budget Gold'!E77="- compte d'épargne à saisir -","",'Budget Gold'!E77) -> Livret A - BANXO | E15: ='Budget Gold'!J75 -> 100 | F15: ='Budget Gold'!J76 -> 0 | G15: =E15-F15 -> 100 | H15: =IF(G15>0,"(+) à ajouter sur le compte épargne",IF(G15=0,"--- rien à faire ---","(-) de moins sur le compte épargne")) -> (+) à ajouter sur le compte épargne | I15: ='Budget Gold'!I77 -> 100
A16: =1+A15 -> 9 | B16: =IF('Budget Gold'!E78="Indiquer le nom du projet à financer","",'Budget Gold'!E78) -> Epargne pour "Projet personnel" | C16: =IF('Budget Gold'!E80="- compte d'épargne à saisir -","",'Budget Gold'!E80) -> Livret A - BANXO | E16: ='Budget Gold'!J78 -> 25 | F16: ='Budget Gold'!J79 -> 0 | G16: =E16-F16 -> 25 | H16: =IF(G16>0,"(+) à ajouter sur le compte épargne",IF(G16=0,"--- rien à faire ---","(-) de moins sur le compte épargne")) -> (+) à ajouter sur le compte épargne | I16: ='Budget Gold'!I80 -> 25
A17: =1+A16 -> 10 | B17: =IF('Budget Gold'!E81="Indiquer le nom du projet à financer","",'Budget Gold'!E81) -> Trésorerie "Jeune prodige conférence" | C17: =IF('Budget Gold'!E83="- compte d'épargne à saisir -","",'Budget Gold'!E83) | E17: ='Budget Gold'!J81 -> 100 | F17: ='Budget Gold'!J82 -> 0 | G17: =E17-F17 -> 100 | H17: =IF(G17>0,"(+) à ajouter sur le compte épargne",IF(G17=0,"--- rien à faire ---","(-) de moins sur le compte épargne")) -> (+) à ajouter sur le compte épargne | I17: ='Budget Gold'!I83 -> 100
A18: =1+A17 -> 11 | B18: =IF('Budget Gold'!E84="Indiquer le nom du projet à financer","",'Budget Gold'!E84) -> Capital "NAISSANCE" - Enfant 1 | C18: =IF('Budget Gold'!E86="- compte d'épargne à saisir -","",'Budget Gold'!E86) | E18: ='Budget Gold'!J84 -> 36.5 | F18: ='Budget Gold'!J85 -> 0 | G18: =E18-F18 -> 36.5 | H18: =IF(G18>0,"(+) à ajouter sur le compte épargne",IF(G18=0,"--- rien à faire ---","(-) de moins sur le compte épargne")) -> (+) à ajouter sur le compte épargne | I18: ='Budget Gold'!I86 -> 36.5
A19: =1+A18 -> 12 | B19: =IF('Budget Gold'!E87="Indiquer le nom du projet à financer","",'Budget Gold'!E87) -> Capital "NAISSANCE" - Enfant 2 | C19: =IF('Budget Gold'!E89="- compte d'épargne à saisir -","",'Budget Gold'!E89) | E19: ='Budget Gold'!J87 -> 36.5 | F19: ='Budget Gold'!J88 -> 0 | G19: =E19-F19 -> 36.5 | H19: =IF(G19>0,"(+) à ajouter sur le compte épargne",IF(G19=0,"--- rien à faire ---","(-) de moins sur le compte épargne")) -> (+) à ajouter sur le compte épargne | I19: ='Budget Gold'!I89 -> 36.5
A20: =1+A19 -> 13 | B20: =IF('Budget Gold'!E90="Indiquer le nom du projet à financer","",'Budget Gold'!E90) | C20: =IF('Budget Gold'!E92="- compte d'épargne à saisir -","",'Budget Gold'!E92) | E20: ='Budget Gold'!J90 -> 0 | F20: ='Budget Gold'!J91 -> 0 | G20: =E20-F20 -> 0 | H20: =IF(G20>0,"(+) à ajouter sur le compte épargne",IF(G20=0,"--- rien à faire ---","(-) de moins sur le compte épargne")) -> --- rien à faire --- | I20: ='Budget Gold'!I92 -> 0
A21: =1+A20 -> 14 | B21: =IF('Budget Gold'!E93="Indiquer le nom du projet à financer","",'Budget Gold'!E93) | C21: =IF('Budget Gold'!E95="- compte d'épargne à saisir -","",'Budget Gold'!E95) | E21: ='Budget Gold'!J93 -> 0 | F21: ='Budget Gold'!J94 -> 0 | G21: =E21-F21 -> 0 | H21: =IF(G21>0,"(+) à ajouter sur le compte épargne",IF(G21=0,"--- rien à faire ---","(-) de moins sur le compte épargne")) -> --- rien à faire --- | I21: ='Budget Gold'!I95 -> 0
A22: =1+A21 -> 15 | B22: =IF('Budget Gold'!E96="Indiquer le nom du projet à financer","",'Budget Gold'!E96) | C22: =IF('Budget Gold'!E98="- compte d'épargne à saisir -","",'Budget Gold'!E98) | E22: ='Budget Gold'!J96 -> 0 | F22: ='Budget Gold'!J97 -> 0 | G22: =E22-F22 -> 0 | H22: =IF(G22>0,"(+) à ajouter sur le compte épargne",IF(G22=0,"--- rien à faire ---","(-) de moins sur le compte épargne")) -> --- rien à faire --- | I22: ='Budget Gold'!I98 -> 0
A23: =1+A22 -> 16 | B23: =IF('Budget Gold'!E99="Indiquer le nom du projet à financer","",'Budget Gold'!E99) | C23: =IF('Budget Gold'!E101="- compte d'épargne à saisir -","",'Budget Gold'!E101) | E23: ='Budget Gold'!J99 -> 0 | F23: ='Budget Gold'!J100 -> 0 | G23: =E23-F23 -> 0 | H23: =IF(G23>0,"(+) à ajouter sur le compte épargne",IF(G23=0,"--- rien à faire ---","(-) de moins sur le compte épargne")) -> --- rien à faire --- | I23: ='Budget Gold'!I101 -> 0
A24: =1+A23 -> 17 | B24: =IF('Budget Gold'!E102="Indiquer le nom du projet à financer","",'Budget Gold'!E102) | C24: =IF('Budget Gold'!E104="- compte d'épargne à saisir -","",'Budget Gold'!E104) | E24: ='Budget Gold'!J102 -> 0 | F24: ='Budget Gold'!J103 -> 0 | G24: =E24-F24 -> 0 | H24: =IF(G24>0,"(+) à ajouter sur le compte épargne",IF(G24=0,"--- rien à faire ---","(-) de moins sur le compte épargne")) -> --- rien à faire --- | I24: ='Budget Gold'!I104 -> 0
A25: =1+A24 -> 18 | B25: =IF('Budget Gold'!E105="Indiquer le nom du projet à financer","",'Budget Gold'!E105) | C25: =IF('Budget Gold'!E107="- compte d'épargne à saisir -","",'Budget Gold'!E107) | E25: ='Budget Gold'!J105 -> 0 | F25: ='Budget Gold'!J106 -> 0 | G25: =E25-F25 -> 0 | H25: =IF(G25>0,"(+) à ajouter sur le compte épargne",IF(G25=0,"--- rien à faire ---","(-) de moins sur le compte épargne")) -> --- rien à faire --- | I25: ='Budget Gold'!I107 -> 0
A26: =1+A25 -> 19 | B26: =IF('Budget Gold'!E108="Indiquer le nom du projet à financer","",'Budget Gold'!E108) | C26: =IF('Budget Gold'!E110="- compte d'épargne à saisir -","",'Budget Gold'!E110) | E26: ='Budget Gold'!J108 -> 0 | F26: ='Budget Gold'!J109 -> 0 | G26: =E26-F26 -> 0 | H26: =IF(G26>0,"(+) à ajouter sur le compte épargne",IF(G26=0,"--- rien à faire ---","(-) de moins sur le compte épargne")) -> --- rien à faire --- | I26: ='Budget Gold'!I110 -> 0
A27: =1+A26 -> 20 | B27: =IF('Budget Gold'!E111="Indiquer le nom du projet à financer","",'Budget Gold'!E111) | C27: =IF('Budget Gold'!E113="- compte d'épargne à saisir -","",'Budget Gold'!E113) | E27: ='Budget Gold'!J111 -> 0 | F27: ='Budget Gold'!J112 -> 0 | G27: =E27-F27 -> 0 | H27: =IF(G27>0,"(+) à ajouter sur le compte épargne",IF(G27=0,"--- rien à faire ---","(-) de moins sur le compte épargne")) -> --- rien à faire --- | I27: ='Budget Gold'!I113 -> 0
A28: =1+A27 -> 21 | B28: =IF('Budget Gold'!E114="Indiquer le nom du projet à financer","",'Budget Gold'!E114) -> PATRIMOINE A - FONCIER et IMMOBILIER (Valeur nette) | C28: =IF('Budget Gold'!E116="- compte d'épargne à saisir -","",'Budget Gold'!E116) -> PATRIMOINE | E28: ='Budget Gold'!J114 -> 0 | F28: ='Budget Gold'!J115 -> 0 | G28: =E28-F28 -> 0 | H28: =IF(G28>0,"(+) à ajouter sur le compte épargne",IF(G28=0,"--- rien à faire ---","(-) de moins sur le compte épargne")) -> --- rien à faire --- | I28: ='Budget Gold'!I116 -> 0
A29: =1+A28 -> 22 | B29: =IF('Budget Gold'!E117="Indiquer le nom du projet à financer","",'Budget Gold'!E117) -> PATRIMOINE B - OBJETS et METAUX PRECIEUX | C29: =IF('Budget Gold'!E119="- compte d'épargne à saisir -","",'Budget Gold'!E119) -> PATRIMOINE | E29: ='Budget Gold'!J117 -> 0 | F29: ='Budget Gold'!J118 -> 0 | G29: =E29-F29 -> 0 | H29: =IF(G29>0,"(+) à ajouter sur le compte épargne",IF(G29=0,"--- rien à faire ---","(-) de moins sur le compte épargne")) -> --- rien à faire --- | I29: ='Budget Gold'!I119 -> 0
A30: =1+A29 -> 23 | B30: =IF('Budget Gold'!E120="Indiquer le nom du projet à financer","",'Budget Gold'!E120) -> PATRIMOINE C - EQUIPEMENTS DE VALEUR, VEHICULES (Valeur nette) | C30: =IF('Budget Gold'!E122="- compte d'épargne à saisir -","",'Budget Gold'!E122) -> PATRIMOINE | E30: ='Budget Gold'!J120 -> 0 | F30: ='Budget Gold'!J121 -> 0 | G30: =E30-F30 -> 0 | H30: =IF(G30>0,"(+) à ajouter sur le compte épargne",IF(G30=0,"--- rien à faire ---","(-) de moins sur le compte épargne")) -> --- rien à faire --- | I30: ='Budget Gold'!I122 -> 0
A31: =1+A30 -> 24 | B31: =IF('Budget Gold'!E123="Indiquer le nom du projet à financer","",'Budget Gold'!E123) -> PATRIMOINE D - AUTRES (Parts de sociétés, cryptomonnaie, créances, etc.) | C31: =IF('Budget Gold'!E125="- compte d'épargne à saisir -","",'Budget Gold'!E125) -> PATRIMOINE | E31: ='Budget Gold'!J123 -> 0 | F31: ='Budget Gold'!J124 -> 0 | G31: =E31-F31 -> 0 | H31: =IF(G31>0,"(+) à ajouter sur le compte épargne",IF(G31=0,"--- rien à faire ---","(-) de moins sur le compte épargne")) -> --- rien à faire --- | I31: ='Budget Gold'!I125 -> 0
A32: =1+A31 -> 25 | B32: =IF('Budget Gold'!E160="Indiquer le nom de la provision à financer","",'Budget Gold'!E160) -> Provision - Achat cuisine | C32: =IF('Budget Gold'!E162="- compte d'épargne à saisir -","",'Budget Gold'!E162) | E32: ='Budget Gold'!J160 -> 1750 | F32: ='Budget Gold'!J161 -> 0 | G32: =E32-F32 -> 1750 | H32: =IF(G32>0,"(+) à ajouter sur le compte épargne",IF(G32=0,"--- rien à faire ---","(-) de moins sur le compte épargne")) -> (+) à ajouter sur le compte épargne | I32: ='Budget Gold'!I162 -> 3750
A33: =1+A32 -> 26 | B33: =IF('Budget Gold'!E163="Indiquer le nom de la provision à financer","",'Budget Gold'!E163) -> Provision - Achat chambre | C33: =IF('Budget Gold'!E165="- compte d'épargne à saisir -","",'Budget Gold'!E165) | E33: ='Budget Gold'!J163 -> 300 | F33: ='Budget Gold'!J164 -> 0 | G33: =E33-F33 -> 300 | H33: =IF(G33>0,"(+) à ajouter sur le compte épargne",IF(G33=0,"--- rien à faire ---","(-) de moins sur le compte épargne")) -> (+) à ajouter sur le compte épargne | I33: ='Budget Gold'!I165 -> 300
A34: =1+A33 -> 27 | B34: =IF('Budget Gold'!E166="Indiquer le nom de la provision à financer","",'Budget Gold'!E166) -> Provision - Vacances / Sorties / Détente | C34: =IF('Budget Gold'!E168="- compte d'épargne à saisir -","",'Budget Gold'!E168) | E34: ='Budget Gold'!J166 -> 50 | F34: ='Budget Gold'!J167 -> 0 | G34: =E34-F34 -> 50 | H34: =IF(G34>0,"(+) à ajouter sur le compte épargne",IF(G34=0,"--- rien à faire ---","(-) de moins sur le compte épargne")) -> (+) à ajouter sur le compte épargne | I34: ='Budget Gold'!I168 -> 50
A35: =1+A34 -> 28 | B35: =IF('Budget Gold'!E169="Indiquer le nom de la provision à financer","",'Budget Gold'!E169) -> Provision - Habillement | C35: =IF('Budget Gold'!E171="- compte d'épargne à saisir -","",'Budget Gold'!E171) | E35: ='Budget Gold'!J169 -> 100 | F35: ='Budget Gold'!J170 -> 0 | G35: =E35-F35 -> 100 | H35: =IF(G35>0,"(+) à ajouter sur le compte épargne",IF(G35=0,"--- rien à faire ---","(-) de moins sur le compte épargne")) -> (+) à ajouter sur le compte épargne | I35: ='Budget Gold'!I171 -> 100
A36: =1+A35 -> 29 | B36: =IF('Budget Gold'!E172="Indiquer le nom de la provision à financer","",'Budget Gold'!E172) -> Provision - Achat bureau | C36: =IF('Budget Gold'!E174="- compte d'épargne à saisir -","",'Budget Gold'!E174) | E36: ='Budget Gold'!J172 -> 300 | F36: ='Budget Gold'!J173 -> 0 | G36: =E36-F36 -> 300 | H36: =IF(G36>0,"(+) à ajouter sur le compte épargne",IF(G36=0,"--- rien à faire ---","(-) de moins sur le compte épargne")) -> (+) à ajouter sur le compte épargne | I36: ='Budget Gold'!I174 -> 300
A37: =1+A36 -> 30 | B37: =IF('Budget Gold'!E175="Indiquer le nom de la provision à financer","",'Budget Gold'!E175) -> Provision - Achat séjour | C37: =IF('Budget Gold'!E177="- compte d'épargne à saisir -","",'Budget Gold'!E177) | E37: ='Budget Gold'!J175 -> 300 | F37: ='Budget Gold'!J176 -> 0 | G37: =E37-F37 -> 300 | H37: =IF(G37>0,"(+) à ajouter sur le compte épargne",IF(G37=0,"--- rien à faire ---","(-) de moins sur le compte épargne")) -> (+) à ajouter sur le compte épargne | I37: ='Budget Gold'!I177 -> 300
A38: =1+A37 -> 31 | B38: =IF('Budget Gold'!E178="Indiquer le nom de la provision à financer","",'Budget Gold'!E178) -> Provision - Cadeaux (Anniversaires, événements, etc.) | C38: =IF('Budget Gold'!E180="- compte d'épargne à saisir -","",'Budget Gold'!E180) | E38: ='Budget Gold'!J178 -> 10 | F38: ='Budget Gold'!J179 -> 0 | G38: =E38-F38 -> 10 | H38: =IF(G38>0,"(+) à ajouter sur le compte épargne",IF(G38=0,"--- rien à faire ---","(-) de moins sur le compte épargne")) -> (+) à ajouter sur le compte épargne | I38: ='Budget Gold'!I180 -> 10
A39: =1+A38 -> 32 | B39: =IF('Budget Gold'!E181="Indiquer le nom de la provision à financer","",'Budget Gold'!E181) -> Provision - Charges de Co-propriété | C39: =IF('Budget Gold'!E183="- compte d'épargne à saisir -","",'Budget Gold'!E183) | E39: ='Budget Gold'!J181 -> 200 | F39: ='Budget Gold'!J182 -> 200 | G39: =E39-F39 -> 0 | H39: =IF(G39>0,"(+) à ajouter sur le compte épargne",IF(G39=0,"--- rien à faire ---","(-) de moins sur le compte épargne")) -> --- rien à faire --- | I39: ='Budget Gold'!I183 -> 0
A40: =1+A39 -> 33 | B40: =IF('Budget Gold'!E184="Indiquer le nom de la provision à financer","",'Budget Gold'!E184) -> Provision - Taxe d'Habitation + Taxe Foncière | C40: =IF('Budget Gold'!E186="- compte d'épargne à saisir -","",'Budget Gold'!E186) | E40: ='Budget Gold'!J184 -> 0 | F40: ='Budget Gold'!J185 -> 0 | G40: =E40-F40 -> 0 | H40: =IF(G40>0,"(+) à ajouter sur le compte épargne",IF(G40=0,"--- rien à faire ---","(-) de moins sur le compte épargne")) -> --- rien à faire --- | I40: ='Budget Gold'!I186 -> 0
A41: =1+A40 -> 34 | B41: =IF('Budget Gold'!E187="Indiquer le nom de la provision à financer","",'Budget Gold'!E187) | C41: =IF('Budget Gold'!E189="- compte d'épargne à saisir -","",'Budget Gold'!E189) | E41: ='Budget Gold'!J187 -> 0 | F41: ='Budget Gold'!J188 -> 0 | G41: =E41-F41 -> 0 | H41: =IF(G41>0,"(+) à ajouter sur le compte épargne",IF(G41=0,"--- rien à faire ---","(-) de moins sur le compte épargne")) -> --- rien à faire --- | I41: ='Budget Gold'!I189 -> 0
A42: =1+A41 -> 35 | B42: =IF('Budget Gold'!E190="Indiquer le nom de la provision à financer","",'Budget Gold'!E190) | C42: =IF('Budget Gold'!E192="- compte d'épargne à saisir -","",'Budget Gold'!E192) | E42: ='Budget Gold'!J190 -> 0 | F42: ='Budget Gold'!J191 -> 0 | G42: =E42-F42 -> 0 | H42: =IF(G42>0,"(+) à ajouter sur le compte épargne",IF(G42=0,"--- rien à faire ---","(-) de moins sur le compte épargne")) -> --- rien à faire --- | I42: ='Budget Gold'!I192 -> 0
A43: =1+A42 -> 36 | B43: =IF('Budget Gold'!E193="Indiquer le nom de la provision à financer","",'Budget Gold'!E193) | C43: =IF('Budget Gold'!E195="- compte d'épargne à saisir -","",'Budget Gold'!E195) | E43: ='Budget Gold'!J193 -> 0 | F43: ='Budget Gold'!J194 -> 0 | G43: =E43-F43 -> 0 | H43: =IF(G43>0,"(+) à ajouter sur le compte épargne",IF(G43=0,"--- rien à faire ---","(-) de moins sur le compte épargne")) -> --- rien à faire --- | I43: ='Budget Gold'!I195 -> 0
A44: =1+A43 -> 37 | B44: =IF('Budget Gold'!E196="Indiquer le nom de la provision à financer","",'Budget Gold'!E196) | C44: =IF('Budget Gold'!E198="- compte d'épargne à saisir -","",'Budget Gold'!E198) | E44: ='Budget Gold'!J196 -> 0 | F44: ='Budget Gold'!J197 -> 0 | G44: =E44-F44 -> 0 | H44: =IF(G44>0,"(+) à ajouter sur le compte épargne",IF(G44=0,"--- rien à faire ---","(-) de moins sur le compte épargne")) -> --- rien à faire --- | I44: ='Budget Gold'!I198 -> 0
A45: =1+A44 -> 38 | B45: =IF('Budget Gold'!E199="Indiquer le nom de la provision à financer","",'Budget Gold'!E199) | C45: =IF('Budget Gold'!E201="- compte d'épargne à saisir -","",'Budget Gold'!E201) | E45: ='Budget Gold'!J199 -> 0 | F45: ='Budget Gold'!J200 -> 0 | G45: =E45-F45 -> 0 | H45: =IF(G45>0,"(+) à ajouter sur le compte épargne",IF(G45=0,"--- rien à faire ---","(-) de moins sur le compte épargne")) -> --- rien à faire --- | I45: ='Budget Gold'!I201 -> 0
A46: =1+A45 -> 39 | B46: =IF('Budget Gold'!E202="Indiquer le nom de la provision à financer","",'Budget Gold'!E202) | C46: =IF('Budget Gold'!E204="- compte d'épargne à saisir -","",'Budget Gold'!E204) | E46: ='Budget Gold'!J202 -> 0 | F46: ='Budget Gold'!J203 -> 0 | G46: =E46-F46 -> 0 | H46: =IF(G46>0,"(+) à ajouter sur le compte épargne",IF(G46=0,"--- rien à faire ---","(-) de moins sur le compte épargne")) -> --- rien à faire --- | I46: ='Budget Gold'!I204 -> 0
A47: =1+A46 -> 40 | B47: =IF('Budget Gold'!E205="Indiquer le nom de la provision à financer","",'Budget Gold'!E205) | C47: =IF('Budget Gold'!E207="- compte d'épargne à saisir -","",'Budget Gold'!E207) | E47: ='Budget Gold'!J205 -> 0 | F47: ='Budget Gold'!J206 -> 0 | G47: =E47-F47 -> 0 | H47: =IF(G47>0,"(+) à ajouter sur le compte épargne",IF(G47=0,"--- rien à faire ---","(-) de moins sur le compte épargne")) -> --- rien à faire --- | I47: ='Budget Gold'!I207 -> 0
A48: =1+A47 -> 41 | B48: =IF('Budget Gold'!E208="Indiquer le nom de la provision à financer","",'Budget Gold'!E208) | C48: =IF('Budget Gold'!E210="- compte d'épargne à saisir -","",'Budget Gold'!E210) | E48: ='Budget Gold'!J208 -> 0 | F48: ='Budget Gold'!J209 -> 0 | G48: =E48-F48 -> 0 | H48: =IF(G48>0,"(+) à ajouter sur le compte épargne",IF(G48=0,"--- rien à faire ---","(-) de moins sur le compte épargne")) -> --- rien à faire --- | I48: ='Budget Gold'!I210 -> 0
A49: =1+A48 -> 42 | B49: =IF('Budget Gold'!E211="Indiquer le nom de la provision à financer","",'Budget Gold'!E211) | C49: =IF('Budget Gold'!E213="- compte d'épargne à saisir -","",'Budget Gold'!E213) | E49: ='Budget Gold'!J211 -> 0 | F49: ='Budget Gold'!J212 -> 0 | G49: =E49-F49 -> 0 | H49: =IF(G49>0,"(+) à ajouter sur le compte épargne",IF(G49=0,"--- rien à faire ---","(-) de moins sur le compte épargne")) -> --- rien à faire --- | I49: ='Budget Gold'!I213 -> 0
A50: =1+A49 -> 43 | B50: =IF('Budget Gold'!E214="Indiquer le nom de la provision à financer","",'Budget Gold'!E214) | C50: =IF('Budget Gold'!E216="- compte d'épargne à saisir -","",'Budget Gold'!E216) | E50: ='Budget Gold'!J214 -> 0 | F50: ='Budget Gold'!J215 -> 0 | G50: =E50-F50 -> 0 | H50: =IF(G50>0,"(+) à ajouter sur le compte épargne",IF(G50=0,"--- rien à faire ---","(-) de moins sur le compte épargne")) -> --- rien à faire --- | I50: ='Budget Gold'!I216 -> 0
A51: =1+A50 -> 44 | B51: =IF('Budget Gold'!E217="Indiquer le nom de la provision à financer","",'Budget Gold'!E217) | C51: =IF('Budget Gold'!E219="- compte d'épargne à saisir -","",'Budget Gold'!E219) | E51: ='Budget Gold'!J217 -> 0 | F51: ='Budget Gold'!J218 -> 0 | G51: =E51-F51 -> 0 | H51: =IF(G51>0,"(+) à ajouter sur le compte épargne",IF(G51=0,"--- rien à faire ---","(-) de moins sur le compte épargne")) -> --- rien à faire --- | I51: ='Budget Gold'!I219 -> 0
H53: TOTAL des avoirs épargne et provisions = | I53: =SUM(I6:I51) -> 55699
A56: Retour au Budget | E56: ='Budget Gold'!I7 -> 46174
C58: Liste des comptes d'épargne | E58: Entrées totales | F58: Sorties totales | G58: Mouvement Global | I58: Solde général
J59: ='Budget Gold'!I7 -> 46174
